Workbook

Sheet O2C - Produtos acabados
A1: Tipo | B1: Cenário | C1: Processo de Negócio | D1: Tipo OV | E1: Cenário de teste | F1: Usina | G1: Cliente | H1: Material | I1: OV Referência | J1: J1BTax | K1: CFOP | L1: OV no BEC | M1: Val. Fiscal | N1: Remessa | O1: Fatura | P1: NF - DocNum | Q1: Val. Contabil | R1: Val. Tax SAP | S1: Val. Tax One | T1: Observação
A2: Cenário | B2: C_001 | C2: Venda Etanol Hidratado D.E | D2: Y002 | E2: Venda de etanol hidratado dentro do estado
A3: Tarefa | B3: C_001 | C3: Venda Etanol Hidratado D.E | D3: YDEV | E3: Retorno da Venda de etanol hidratado dentro do estado
A4: Tarefa | B4: C_001 | C4: Venda Etanol Hidratado D.E | D4: YRET | E4: Recusa da venda de hidratado dentro do estado
A5: Cenário | B5: C_002 | C5: Venda Etanol Hidratado F.E | D5: Y002 | E5: Venda de etanol hidratado fora do estado
A6: Tarefa | B6: C_002 | C6: Venda Etanol Hidratado F.E | D6: YDEV | E6: Retorno da Venda de etanol hidratado fora do estado
A7: Tarefa | B7: C_002 | C7: Venda Etanol Hidratado F.E | D7: YRET | E7: Recusa da venda de hidratado fora do estado
A8: Cenário | B8: C_003 | C8: Venda Etanol Anidro F.E - Distribuidora | D8: Y002 | E8: Venda de etanol Anidro fora do estado - Distribuidora
A9: Tarefa | B9: C_003 | C9: Venda Etanol Anidro F.E | D9: YDEV | E9: Retorno da Venda de etanol Anidro fora do estado
A10: Tarefa | B10: C_003 | C10: Venda Etanol Anidro F.E | D10: YRET | E10: Recusa da venda de Anidro fora do estado
A11: Cenário | B11: C_004 | C11: Venda Etanol Anidro D.E - Distribuidora | D11: Y002 | E11: Venda de etanol Anidro dentro do estado - Distribuidora
A12: Tarefa | B12: C_004 | C12: Venda Etanol Anidro F.E | D12: YDEV | E12: Retorno da Venda de etanol Anidro fora do estado
A13: Tarefa | B13: C_004 | C13: Venda Etanol Anidro F.E | D13: YRET | E13: Recusa da venda de Anidro fora do estado
... A43: Cenário | B43: C_018 | C43: Venda doméstica Açúcar – CTR | D43: Y073 | E43: Venda de açucar C1C para Femsa_CTR
A44: Tarefa | B44: C_018 | C44: Venda doméstica Açúcar – CTR | E44: Recusa da venda de açucar C1C para Femsa_CTR
A45: Tarefa | B45: C_018 | C45: Venda doméstica Açúcar – CTR | E45: Retorno da venda de açucar C1C para Femsa_CTR
A46: Cenário | B46: C_019 | C46: Venda Etanol Anidro ZFM | D46: Y002 | E46: Venda de etanol Anidro Zona Franca de Manaus
A47: Tarefa | B47: C_019 | C47: Venda Etanol Anidro ZFM | E47: Retorno da Venda de etanol Anidro Zona Franca de Manaus
A48: Tarefa | B48: C_019 | C48: Venda Etanol Anidro ZFM | E48: Recusa da venda de Anidro Zona Franca de Manaus
A49: Cenário | B49: C_020 | C49: VEF - Receita Antecipada | D49: YVFP | E49: VEF - Receita Antecipada
A50: Cenário | B50: C_020 | C50: Remessa VEF - Receita Antecipada | D50: YRFP | E50: Remessa VEF - Receita Antecipada
A51: Tarefa | B51: C_020 | C51: Remessa VEF - Receita Antecipada | D51: YVRC | E51: Recusa da VEF - Etanol (YVRC)
A52: Tarefa | B52: C_020 | C52: Remessa VEF - Receita Antecipada | D52: YVRE | E52: Retorno da VEF - Etanol (YVRE)
A53: Cenário | B53: C_021 | C53: FA - Simples Faturamento | D53: Y003 | E53: FA- Simples Faturamento
A54: Cenário | B54: C_021 | C54: Remessa da FA - Receita Remessa | D54: Y033 | E54: Remessa da FA - Receita Remessa
A55: Tarefa | B55: C_021 | C55: Remessa da FA - Receita Remessa | D55: Y3RC | E55: Recusa da FA - Etanol (Y3RC)
A56: Tarefa | B56: C_021 | C56: Remessa da FA - Receita Remessa | D56: Y3RE | E56: Retorno da FA - Etanol (Y3RE)
A57: Cenário | B57: C_022 | C57: Venda Conta e Ordem | D57: Y032 | E57: Venda Conta e Ordem
A58: Cenário | B58: C_022 | C58: Remessa Conta e Ordem | D58: Y044 | E58: Remessa Conta e Ordem
A59: Tarefa | B59: C_022 | C59: Remessa Conta e Ordem | D59: YSRS | E59: Recusa da Conta e Ordem - Etanol (YSRS)
A60: Tarefa | B60: C_022 | C60: Remessa Conta e Ordem | D60: YDSR | E60: Retorno da Conta e Ordem - Etanol (YDSR)
... A71: Tarefa | B71: C_025 | C71: Venda Bagaço_ YBIO | D71: YRET | E71: Recusa da venda Bagaço
A72: Cenário | B72: C_026 | C72: Venda Energia Dentro Estado Consumo | D72: 0 | E72: Venda Energia Dentro Estado Consumo
A73: Tarefa | B73: C_026 | C73: Venda Energia Dentro Estado Consumo | D73: YRET | E73: Anulação
A74: Cenário | B74: C_027 | C74: Revenda Energia Fora Estado | D74: Y202 | E74: Revenda Energia Fora Estado
A75: Tarefa | B75: C_027 | C75: Revenda Energia Fora Estado | D75: YRET | E75: Anulação
A76: Cenário | B76: C_028 | C76: Venda Energia Fora Estado Consumo | D76: Y202 | E76: Venda Energia Fora Estado Consumo
A77: Tarefa | B77: C_028 | C77: Venda Energia Fora Estado Consumo | D77: YRET | E77: Anulação
A78: Cenário | B78: C_029 | C78: Lastro Energia | D78: Y205 | E78: Lastro Energia
A79: Cenário | B79: C_030 | C79: Venda Energia Biomassa | D79: Y202 | E79: Venda Energia Biomassa
A80: Cenário | B80: C_033 | C80: Complemento de débito | D80: Y014 | E80: Complemento de débito
A81: Cenário | B81: C_049 | C81: Venda Intercompany (Depósito-ANP) | D81: Y045 | E81: Venda Intercompany (Depósito-ANP)
A82: Cenário | B82: C_049 | C82: Venda Intercompany (Depósito-ANP) | D82: ME21N | E82: Venda Intercompany (Depósito-ANP)
A83: Cenário | B83: C_049 | C83: Venda Intercompany (Depósito-ANP) | D83: Y038 | E83: Venda Intercompany (Depósito-ANP)
A84: Cenário | B84: C_049 | C84: Venda Intercompany (Depósito-ANP) | D84: YE13 | E84: Venda Intercompany (Depósito-ANP)
... A87: Cenário | B87: C_049 | C87: Venda Intercompany (Depósito-ANP) | D87: Y002 | E87: Venda Intercompany (Depósito-ANP)

Sheet O2C - Diversas
A1: Tipo | B1: Cenário | C1: Processo de Negócio | D1: Tipo OV | E1: Coluna1 | F1: Cenário de teste | G1: Usina | H1: Cliente | I1: Material | J1: OV Referência | K1: J1BTax | L1: CFOP | M1: OV no BEC | N1: Val. Fiscal | O1: Remessa | P1: Fatura | Q1: NF - DocNum | R1: Val. Contabil | S1: Val. Tax SAP | T1: Val. Tax One | U1: Observação
A2: Cenário | B2: C_031 | C2: Venda Melaço | D2: Y007 | E2: =Tabela2[[#This Row],[Processo de Negócio]]&" ("&Tabela2[[#This Row],[Tipo OV]]&")" -> Venda Melaço (Y007) | F2: Venda Melaço
A3: Cenário | B3: C_032 | C3: Venda Agua Vapor | D3: Y002 | E3: =Tabela2[[#This Row],[Processo de Negócio]]&" ("&Tabela2[[#This Row],[Tipo OV]]&")" -> Venda Agua Vapor (Y002) | F3: Venda Agua Vapor
A4: Cenário | B4: C_034 | C4: Transferencia Matriz/Filial | D4: PIMS | E4: =Tabela2[[#This Row],[Processo de Negócio]]&" ("&Tabela2[[#This Row],[Tipo OV]]&")" -> Transferencia Matriz/Filial (PIMS) | F4: Insumos
A5: Cenário | B5: C_035 | C5: Transferencia Matriz/Filial | D5: PIMS | E5: =Tabela2[[#This Row],[Processo de Negócio]]&" ("&Tabela2[[#This Row],[Tipo OV]]&")" -> Transferencia Matriz/Filial (PIMS) | F5: Diesel
A6: Cenário | B6: C_036 | C6: Doação | D6: Y013 | E6: =Tabela2[[#This Row],[Processo de Negócio]]&" ("&Tabela2[[#This Row],[Tipo OV]]&")" -> Doação (Y013) | F6: Doação
A7: Cenário | B7: C_037 | C7: Doação com Movimentação | D7: Y103 | E7: =Tabela2[[#This Row],[Processo de Negócio]]&" ("&Tabela2[[#This Row],[Tipo OV]]&")" -> Doação com Movimentação (Y103) | F7: Doação com Movimentação
A8: Cenário | B8: C_038 | C8: Venda Ativo F.E | D8: Y005 | E8: =Tabela2[[#This Row],[Processo de Negócio]]&" ("&Tabela2[[#This Row],[Tipo OV]]&")" -> Venda Ativo F.E (Y005) | F8: Venda Ativo F.E
A9: Tarefa | B9: C_038 | C9: Venda Ativo F.E | D9: YRET | E9: =Tabela2[[#This Row],[Processo de Negócio]]&" ("&Tabela2[[#This Row],[Tipo OV]]&")" -> Venda Ativo F.E (YRET) | F9: Recusa da venda de ativo F.E
A10: Cenário | B10: C_039 | C10: Venda Sucata - Residuo | D10: Y007 | E10: =Tabela2[[#This Row],[Processo de Negócio]]&" ("&Tabela2[[#This Row],[Tipo OV]]&")" -> Venda Sucata - Residuo (Y007) | F10: Venda Sucata - Residuo
A11: Tarefa | B11: C_039 | C11: Venda Sucata - Residuo | D11: YRE8 | E11: =Tabela2[[#This Row],[Processo de Negócio]]&" ("&Tabela2[[#This Row],[Tipo OV]]&")" -> Venda Sucata - Residuo (YRE8) | F11: Recusa da venda sucata
A12: Tarefa | B12: C_039 | C12: Venda Sucata - Residuo | D12: YDE8 | E12: =Tabela2[[#This Row],[Processo de Negócio]]&" ("&Tabela2[[#This Row],[Tipo OV]]&")" -> Venda Sucata - Residuo (YDE8) | F12: Retorno da venda sucata
A13: Cenário | B13: C_040 | C13: Venda de Serviços | D13: Y017 | E13: =Tabela2[[#This Row],[Processo de Negócio]]&" ("&Tabela2[[#This Row],[Tipo OV]]&")" -> Venda de Serviços (Y017) | F13: Venda de Serviços
... A22: Cenário | B22: C_050 | C22: Inutilização | D22: Y007 | E22: =Tabela2[[#This Row],[Processo de Negócio]]&" ("&Tabela2[[#This Row],[Tipo OV]]&")" -> Inutilização (Y007) | F22: Intercompany (inutilização)

Sheet TNV
A1: ID | B1: Liberado para Testes? | C1: Cenário | D1: Tarefa | E1: Sequência | F1: Descrição | G1: Responsável | H1: BEC (Pedido/Docnum) | I1: Doc Ref BEP | J1: Conferência Elo | K1: Status | L1: Dt Inicial | M1: Tempo Previsto | N1: Dt Conclusão | O1: Observação | P1: ID Tarefa Precedente | Q1: Tarefas por Cenário | R1: Tarefas Concluídas | S1: Cenário Concluído | T1: Elo - Em correção | U1: Keyuser - Aguardando tarefa precedente | V1: Não liberado para testes | W1: Em correção? | X1: Precedentes? | Y1: Bloqueado? | Z1: Dias em pendente Keyuser | AA1: Impedindo processeguir?
A2: =IF(Tabela49[[#This Row],[Cenário]]<>"","TNV-"&MID(Tabela49[[#This Row],[Cenário]],1,4)&"_"&ROW(),"") -> TNV-CT01_2 | C2: CT01 - CTe Vendas | D2: Gerar cenário e pedido | G2: Edson Oliveira | H2: 4705847492 | K2: Keyuser - Concluído | N2: 46001
A3: =IF(Tabela49[[#This Row],[Cenário]]<>"","TNV-"&MID(Tabela49[[#This Row],[Cenário]],1,4)&"_"&ROW(),"") -> TNV-CT01_3 | C3: CT01 - CTe Vendas | D3: Efetuar lançamento (escrituração fiscal) | G3: Edson Oliveira | H3: 46482747 | K3: Keyuser - Concluído | N3: 46001
A4: =IF(Tabela49[[#This Row],[Cenário]]<>"","TNV-"&MID(Tabela49[[#This Row],[Cenário]],1,4)&"_"&ROW(),"") -> TNV-CT01_4 | C4: CT01 - CTe Vendas | D4: Configurar/Parametrizar IVAs | G4: Lívia Martins | K4: Keyuser - Pendente
A5: =IF(Tabela49[[#This Row],[Cenário]]<>"","TNV-"&MID(Tabela49[[#This Row],[Cenário]],1,4)&"_"&ROW(),"") -> TNV-CT01_5 | C5: CT01 - CTe Vendas | D5: Validar ICMS | G5: Giovana Gonçalves | K5: Keyuser - Pendente
A6: =IF(Tabela49[[#This Row],[Cenário]]<>"","TNV-"&MID(Tabela49[[#This Row],[Cenário]],1,4)&"_"&ROW(),"") -> TNV-CT01_6 | C6: CT01 - CTe Vendas | D6: Validar PIS/COFINS/IBS/CBS | G6: Talita Andrade | K6: Keyuser - Pendente
A7: =IF(Tabela49[[#This Row],[Cenário]]<>"","TNV-"&MID(Tabela49[[#This Row],[Cenário]],1,4)&"_"&ROW(),"") -> TNV-CT01_7 | C7: CT01 - CTe Vendas | D7: Validar Retenções | G7: Raquel dos Santos | K7: Keyuser - Pendente
A8: =IF(Tabela49[[#This Row],[Cenário]]<>"","TNV-"&MID(Tabela49[[#This Row],[Cenário]],1,4)&"_"&ROW(),"") -> TNV-CT01_8 | C8: CT01 - CTe Vendas | D8: Validação da contabilização | G8: Naiara Toledo | K8: Keyuser - Pendente
A9: =IF(Tabela49[[#This Row],[Cenário]]<>"","TNV-"&MID(Tabela49[[#This Row],[Cenário]],1,4)&"_"&ROW(),"") -> TNV-CT01_9 | C9: CT01 - CTe Vendas | D9: Validação título financeiro | G9: Elisa Alves | K9: Keyuser - Pendente
A10: =IF(Tabela49[[#This Row],[Cenário]]<>"","TNV-"&MID(Tabela49[[#This Row],[Cenário]],1,4)&"_"&ROW(),"") -> TNV-CT01_10 | C10: CT01 - CTe Vendas | D10: Realizar validação Obrigações Acessórias - TaxOne | G10: Sergio Souza / Giovana Gonçalves | K10: Keyuser - Pendente
A11: =IF(Tabela49[[#This Row],[Cenário]]<>"","TNV-"&MID(Tabela49[[#This Row],[Cenário]],1,4)&"_"&ROW(),"") -> TNV-CT02_11 | C11: CT02 - CTe Compras - Débito Posterior | D11: Gerar cenário e pedido | G11: Edson Oliveira | H11: 4501889037 | K11: Keyuser - Concluído | N11: 46001
A12: =IF(Tabela49[[#This Row],[Cenário]]<>"","TNV-"&MID(Tabela49[[#This Row],[Cenário]],1,4)&"_"&ROW(),"") -> TNV-CT02_12 | C12: CT02 - CTe Compras - Débito Posterior | D12: Efetuar lançamento (escrituração fiscal) | G12: Edson Oliveira | H12: 46482744 | K12: TNV - Em correção | O12: Erro no item 2 - Tributação IBS incorreta
A13: =IF(Tabela49[[#This Row],[Cenário]]<>"","TNV-"&MID(Tabela49[[#This Row],[Cenário]],1,4)&"_"&ROW(),"") -> TNV-CT02_13 | C13: CT02 - CTe Compras - Débito Posterior | D13: Configurar/Parametrizar IVAs | G13: Lívia Martins | K13: Keyuser - Aguardando tarefa precedente
A14: =IF(Tabela49[[#This Row],[Cenário]]<>"","TNV-"&MID(Tabela49[[#This Row],[Cenário]],1,4)&"_"&ROW(),"") -> TNV-CT02_14 | C14: CT02 - CTe Compras - Débito Posterior | D14: Validar ICMS | G14: Giovana Gonçalves | K14: Keyuser - Aguardando tarefa precedente
A15: =IF(Tabela49[[#This Row],[Cenário]]<>"","TNV-"&MID(Tabela49[[#This Row],[Cenário]],1,4)&"_"&ROW(),"") -> TNV-CT02_15 | C15: CT02 - CTe Compras - Débito Posterior | D15: Validar PIS/COFINS/IBS/CBS | G15: Talita Andrade | K15: Keyuser - Aguardando tarefa precedente
A16: =IF(Tabela49[[#This Row],[Cenário]]<>"","TNV-"&MID(Tabela49[[#This Row],[Cenário]],1,4)&"_"&ROW(),"") -> TNV-CT02_16 | C16: CT02 - CTe Compras - Débito Posterior | D16: Validar Retenções | G16: Raquel dos Santos | K16: Keyuser - Aguardando tarefa precedente
A17: =IF(Tabela49[[#This Row],[Cenário]]<>"","TNV-"&MID(Tabela49[[#This Row],[Cenário]],1,4)&"_"&ROW(),"") -> TNV-CT02_17 | C17: CT02 - CTe Compras - Débito Posterior | D17: Validação da contabilização | G17: Naiara Toledo | K17: Keyuser - Aguardando tarefa precedente
A18: =IF(Tabela49[[#This Row],[Cenário]]<>"","TNV-"&MID(Tabela49[[#This Row],[Cenário]],1,4)&"_"&ROW(),"") -> TNV-CT02_18 | C18: CT02 - CTe Compras - Débito Posterior | D18: Validação título financeiro | G18: Elisa Alves | K18: Keyuser - Aguardando tarefa precedente
A19: =IF(Tabela49[[#This Row],[Cenário]]<>"","TNV-"&MID(Tabela49[[#This Row],[Cenário]],1,4)&"_"&ROW(),"") -> TNV-CT02_19 | C19: CT02 - CTe Compras - Débito Posterior | D19: Realizar validação Obrigações Acessórias - TaxOne | G19: Sergio Souza / Giovana Gonçalves | K19: Keyuser - Aguardando tarefa precedente
A20: =IF(Tabela49[[#This Row],[Cenário]]<>"","TNV-"&MID(Tabela49[[#This Row],[Cenário]],1,4)&"_"&ROW(),"") -> TNV-CT05_20 | C20: CT05 - CTe Writer | D20: Gerar cenário e pedido | G20: Edson Oliveira | H20: 46482768 | K20: TNV - Em correção | O20: Ajustes nas linhas de IBS/CBS
A21: =IF(Tabela49[[#This Row],[Cenário]]<>"","TNV-"&MID(Tabela49[[#This Row],[Cenário]],1,4)&"_"&ROW(),"") -> TNV-CT05_21 | C21: CT05 - CTe Writer | D21: Efetuar lançamento (escrituração fiscal) | G21: Edson Oliveira | K21: Keyuser - Aguardando tarefa precedente
A22: =IF(Tabela49[[#This Row],[Cenário]]<>"","TNV-"&MID(Tabela49[[#This Row],[Cenário]],1,4)&"_"&ROW(),"") -> TNV-CT05_22 | C22: CT05 - CTe Writer | D22: Configurar/Parametrizar IVAs | G22: Lívia Martins | K22: Keyuser - Aguardando tarefa precedente
A23: =IF(Tabela49[[#This Row],[Cenário]]<>"","TNV-"&MID(Tabela49[[#This Row],[Cenário]],1,4)&"_"&ROW(),"") -> TNV-CT05_23 | C23: CT05 - CTe Writer | D23: Validar ICMS | G23: Giovana Gonçalves | K23: Keyuser - Aguardando tarefa precedente
A24: =IF(Tabela49[[#This Row],[Cenário]]<>"","TNV-"&MID(Tabela49[[#This Row],[Cenário]],1,4)&"_"&ROW(),"") -> TNV-CT05_24 | C24: CT05 - CTe Writer | D24: Validar PIS/COFINS/IBS/CBS | G24: Talita Andrade | K24: Keyuser - Aguardando tarefa precedente
A25: =IF(Tabela49[[#This Row],[Cenário]]<>"","TNV-"&MID(Tabela49[[#This Row],[Cenário]],1,4)&"_"&ROW(),"") -> TNV-CT05_25 | C25: CT05 - CTe Writer | D25: Validar Retenções | G25: Raquel dos Santos | K25: Keyuser - Aguardando tarefa precedente
A26: =IF(Tabela49[[#This Row],[Cenário]]<>"","TNV-"&MID(Tabela49[[#This Row],[Cenário]],1,4)&"_"&ROW(),"") -> TNV-CT05_26 | C26: CT05 - CTe Writer | D26: Validação da contabilização | G26: Naiara Toledo | K26: Keyuser - Aguardando tarefa precedente
A27: =IF(Tabela49[[#This Row],[Cenário]]<>"","TNV-"&MID(Tabela49[[#This Row],[Cenário]],1,4)&"_"&ROW(),"") -> TNV-CT05_27 | C27: CT05 - CTe Writer | D27: Validação título financeiro | G27: Elisa Alves | K27: Keyuser - Aguardando tarefa precedente
A28: =IF(Tabela49[[#This Row],[Cenário]]<>"","TNV-"&MID(Tabela49[[#This Row],[Cenário]],1,4)&"_"&ROW(),"") -> TNV-CT05_28 | C28: CT05 - CTe Writer | D28: Realizar validação Obrigações Acessórias - TaxOne | G28: Sergio Souza / Giovana Gonçalves | K28: Keyuser - Aguardando tarefa precedente
A29: =IF(Tabela49[[#This Row],[Cenário]]<>"","TNV-"&MID(Tabela49[[#This Row],[Cenário]],1,4)&"_"&ROW(),"") -> TNV-CT09_29 | C29: CT09 - CTe Outros com folha | D29: Gerar cenário e pedido | G29: Edson Oliveira | H29: 4501889077 | K29: Keyuser - Concluído | N29: 46002
A30: =IF(Tabela49[[#This Row],[Cenário]]<>"","TNV-"&MID(Tabela49[[#This Row],[Cenário]],1,4)&"_"&ROW(),"") -> TNV-CT09_30 | C30: CT09 - CTe Outros com folha | D30: Efetuar lançamento (escrituração fiscal) | G30: Edson Oliveira | K30: Não se Aplica
A31: =IF(Tabela49[[#This Row],[Cenário]]<>"","TNV-"&MID(Tabela49[[#This Row],[Cenário]],1,4)&"_"&ROW(),"") -> TNV-CT09_31 | C31: CT09 - CTe Outros com folha | D31: Configurar/Parametrizar IVAs | G31: Lívia Martins | K31: Não se Aplica
A32: =IF(Tabela49[[#This Row],[Cenário]]<>"","TNV-"&MID(Tabela49[[#This Row],[Cenário]],1,4)&"_"&ROW(),"") -> TNV-CT09_32 | C32: CT09 - CTe Outros com folha | D32: Validar ICMS | G32: Giovana Gonçalves | K32: Não se Aplica
A33: =IF(Tabela49[[#This Row],[Cenário]]<>"","TNV-"&MID(Tabela49[[#This Row],[Cenário]],1,4)&"_"&ROW(),"") -> TNV-CT09_33 | C33: CT09 - CTe Outros com folha | D33: Validar PIS/COFINS/IBS/CBS | G33: Talita Andrade | K33: Não se Aplica
A34: =IF(Tabela49[[#This Row],[Cenário]]<>"","TNV-"&MID(Tabela49[[#This Row],[Cenário]],1,4)&"_"&ROW(),"") -> TNV-CT09_34 | C34: CT09 - CTe Outros com folha | D34: Validar Retenções | G34: Raquel dos Santos | K34: Não se Aplica
A35: =IF(Tabela49[[#This Row],[Cenário]]<>"","TNV-"&MID(Tabela49[[#This Row],[Cenário]],1,4)&"_"&ROW(),"") -> TNV-CT09_35 | C35: CT09 - CTe Outros com folha | D35: Validação da contabilização | G35: Naiara Toledo | K35: Não se Aplica
A36: =IF(Tabela49[[#This Row],[Cenário]]<>"","TNV-"&MID(Tabela49[[#This Row],[Cenário]],1,4)&"_"&ROW(),"") -> TNV-CT09_36 | C36: CT09 - CTe Outros com folha | D36: Validação título financeiro | G36: Elisa Alves | K36: Não se Aplica
A37: =IF(Tabela49[[#This Row],[Cenário]]<>"","TNV-"&MID(Tabela49[[#This Row],[Cenário]],1,4)&"_"&ROW(),"") -> TNV-CT09_37 | C37: CT09 - CTe Outros com folha | D37: Realizar validação Obrigações Acessórias - TaxOne | G37: Sergio Souza / Giovana Gonçalves | K37: Não se Aplica
A38: =IF(Tabela49[[#This Row],[Cenário]]<>"","TNV-"&MID(Tabela49[[#This Row],[Cenário]],1,4)&"_"&ROW(),"") -> TNV-CT09_38 | C38: CT09B - CTe Outros sem folha | D38: Gerar cenário e pedido | G38: Edson Oliveira | H38: 4501889041 | K38: Keyuser - Concluído | N38: 46001
A39: =IF(Tabela49[[#This Row],[Cenário]]<>"","TNV-"&MID(Tabela49[[#This Row],[Cenário]],1,4)&"_"&ROW(),"") -> TNV-CT09_39 | C39: CT09B - CTe Outros sem folha | D39: Efetuar lançamento (escrituração fiscal) | G39: Edson Oliveira | H39: 46482745 | K39: Keyuser - Concluído | N39: 46001
A40: =IF(Tabela49[[#This Row],[Cenário]]<>"","TNV-"&MID(Tabela49[[#This Row],[Cenário]],1,4)&"_"&ROW(),"") -> TNV-CT09_40 | C40: CT09B - CTe Outros sem folha | D40: Configurar/Parametrizar IVAs | G40: Lívia Martins | K40: Keyuser - Pendente
A41: =IF(Tabela49[[#This Row],[Cenário]]<>"","TNV-"&MID(Tabela49[[#This Row],[Cenário]],1,4)&"_"&ROW(),"") -> TNV-CT09_41 | C41: CT09B - CTe Outros sem folha | D41: Validar ICMS | G41: Giovana Gonçalves | K41: Keyuser - Pendente
A42: =IF(Tabela49[[#This Row],[Cenário]]<>"","TNV-"&MID(Tabela49[[#This Row],[Cenário]],1,4)&"_"&ROW(),"") -> TNV-CT09_42 | C42: CT09B - CTe Outros sem folha | D42: Validar PIS/COFINS/IBS/CBS | G42: Talita Andrade | K42: Keyuser - Pendente
A43: =IF(Tabela49[[#This Row],[Cenário]]<>"","TNV-"&MID(Tabela49[[#This Row],[Cenário]],1,4)&"_"&ROW(),"") -> TNV-CT09_43 | C43: CT09B - CTe Outros sem folha | D43: Validar Retenções | G43: Raquel dos Santos | K43: Keyuser - Pendente
A44: =IF(Tabela49[[#This Row],[Cenário]]<>"","TNV-"&MID(Tabela49[[#This Row],[Cenário]],1,4)&"_"&ROW(),"") -> TNV-CT09_44 | C44: CT09B - CTe Outros sem folha | D44: Validação da contabilização | G44: Naiara Toledo | K44: Keyuser - Pendente
A45: =IF(Tabela49[[#This Row],[Cenário]]<>"","TNV-"&MID(Tabela49[[#This Row],[Cenário]],1,4)&"_"&ROW(),"") -> TNV-CT09_45 | C45: CT09B - CTe Outros sem folha | D45: Validação título financeiro | G45: Elisa Alves | K45: Keyuser - Pendente
A46: =IF(Tabela49[[#This Row],[Cenário]]<>"","TNV-"&MID(Tabela49[[#This Row],[Cenário]],1,4)&"_"&ROW(),"") -> TNV-CT09_46 | C46: CT09B - CTe Outros sem folha | D46: Realizar validação Obrigações Acessórias - TaxOne | G46: Sergio Souza / Giovana Gonçalves | K46: Keyuser - Pendente
A47: =IF(Tabela49[[#This Row],[Cenário]]<>"","TNV-"&MID(Tabela49[[#This Row],[Cenário]],1,4)&"_"&ROW(),"") -> TNV-CT10_47 | C47: CT10 - CTe Serviços 67 | D47: Gerar cenário e pedido | G47: Edson Oliveira | H47: 4501889057 | K47: Keyuser - Concluído | N47: 46002
A48: =IF(Tabela49[[#This Row],[Cenário]]<>"","TNV-"&MID(Tabela49[[#This Row],[Cenário]],1,4)&"_"&ROW(),"") -> TNV-CT10_48 | C48: CT10 - CTe Serviços 67 | D48: Efetuar lançamento (escrituração fiscal) | G48: Edson Oliveira | K48: TNV - Em correção | O48: Dump durante a execução: Time Out
A49: =IF(Tabela49[[#This Row],[Cenário]]<>"","TNV-"&MID(Tabela49[[#This Row],[Cenário]],1,4)&"_"&ROW(),"") -> TNV-CT10_49 | C49: CT10 - CTe Serviços 67 | D49: Configurar/Parametrizar IVAs | G49: Lívia Martins | K49: Keyuser - Aguardando tarefa precedente
A50: =IF(Tabela49[[#This Row],[Cenário]]<>"","TNV-"&MID(Tabela49[[#This Row],[Cenário]],1,4)&"_"&ROW(),"") -> TNV-CT10_50 | C50: CT10 - CTe Serviços 67 | D50: Validar ICMS | G50: Giovana Gonçalves | K50: Keyuser - Aguardando tarefa precedente
A51: =IF(Tabela49[[#This Row],[Cenário]]<>"","TNV-"&MID(Tabela49[[#This Row],[Cenário]],1,4)&"_"&ROW(),"") -> TNV-CT10_51 | C51: CT10 - CTe Serviços 67 | D51: Validar PIS/COFINS/IBS/CBS | G51: Talita Andrade | K51: Keyuser - Aguardando tarefa precedente
A52: =IF(Tabela49[[#This Row],[Cenário]]<>"","TNV-"&MID(Tabela49[[#This Row],[Cenário]],1,4)&"_"&ROW(),"") -> TNV-CT10_52 | C52: CT10 - CTe Serviços 67 | D52: Validar Retenções | G52: Raquel dos Santos | K52: Keyuser - Aguardando tarefa precedente
A53: =IF(Tabela49[[#This Row],[Cenário]]<>"","TNV-"&MID(Tabela49[[#This Row],[Cenário]],1,4)&"_"&ROW(),"") -> TNV-CT10_53 | C53: CT10 - CTe Serviços 67 | D53: Validação da contabilização | G53: Naiara Toledo | K53: Keyuser - Aguardando tarefa precedente
A54: =IF(Tabela49[[#This Row],[Cenário]]<>"","TNV-"&MID(Tabela49[[#This Row],[Cenário]],1,4)&"_"&ROW(),"") -> TNV-CT10_54 | C54: CT10 - CTe Serviços 67 | D54: Validação título financeiro | G54: Elisa Alves | K54: Keyuser - Aguardando tarefa precedente
A55: =IF(Tabela49[[#This Row],[Cenário]]<>"","TNV-"&MID(Tabela49[[#This Row],[Cenário]],1,4)&"_"&ROW(),"") -> TNV-CT10_55 | C55: CT10 - CTe Serviços 67 | D55: Realizar validação Obrigações Acessórias - TaxOne | G55: Sergio Souza / Giovana Gonçalves | K55: Keyuser - Aguardando tarefa precedente
A56: =IF(Tabela49[[#This Row],[Cenário]]<>"","TNV-"&MID(Tabela49[[#This Row],[Cenário]],1,4)&"_"&ROW(),"") -> TNV-MD01_56 | C56: MD01 - Fatura Energia | D56: Gerar cenário e pedido | G56: Edson Oliveira | H56: 4501887886 | K56: Keyuser - Concluído | N56: 46002
A57: =IF(Tabela49[[#This Row],[Cenário]]<>"","TNV-"&MID(Tabela49[[#This Row],[Cenário]],1,4)&"_"&ROW(),"") -> TNV-MD01_57 | C57: MD01 - Fatura Energia | D57: Efetuar lançamento (escrituração fiscal) | G57: Edson Oliveira | K57: TNV - Em correção | O57: Configuração IBS/CBS na categoria do cenário
A58: =IF(Tabela49[[#This Row],[Cenário]]<>"","TNV-"&MID(Tabela49[[#This Row],[Cenário]],1,4)&"_"&ROW(),"") -> TNV-MD01_58 | C58: MD01 - Fatura Energia | D58: Configurar/Parametrizar IVAs | G58: Lívia Martins | K58: Keyuser - Aguardando tarefa precedente
A59: =IF(Tabela49[[#This Row],[Cenário]]<>"","TNV-"&MID(Tabela49[[#This Row],[Cenário]],1,4)&"_"&ROW(),"") -> TNV-MD01_59 | C59: MD01 - Fatura Energia | D59: Validar ICMS | G59: Giovana Gonçalves | K59: Keyuser - Aguardando tarefa precedente
A60: =IF(Tabela49[[#This Row],[Cenário]]<>"","TNV-"&MID(Tabela49[[#This Row],[Cenário]],1,4)&"_"&ROW(),"") -> TNV-MD01_60 | C60: MD01 - Fatura Energia | D60: Validar PIS/COFINS/IBS/CBS | G60: Talita Andrade | K60: Keyuser - Aguardando tarefa precedente
A61: =IF(Tabela49[[#This Row],[Cenário]]<>"","TNV-"&MID(Tabela49[[#This Row],[Cenário]],1,4)&"_"&ROW(),"") -> TNV-MD01_61 | C61: MD01 - Fatura Energia | D61: Validar Retenções | G61: Raquel dos Santos | K61: Keyuser - Aguardando tarefa precedente
A62: =IF(Tabela49[[#This Row],[Cenário]]<>"","TNV-"&MID(Tabela49[[#This Row],[Cenário]],1,4)&"_"&ROW(),"") -> TNV-MD01_62 | C62: MD01 - Fatura Energia | D62: Validação da contabilização | G62: Naiara Toledo | K62: Keyuser - Aguardando tarefa precedente
A63: =IF(Tabela49[[#This Row],[Cenário]]<>"","TNV-"&MID(Tabela49[[#This Row],[Cenário]],1,4)&"_"&ROW(),"") -> TNV-MD01_63 | C63: MD01 - Fatura Energia | D63: Validação título financeiro | G63: Elisa Alves | K63: Keyuser - Aguardando tarefa precedente
A64: =IF(Tabela49[[#This Row],[Cenário]]<>"","TNV-"&MID(Tabela49[[#This Row],[Cenário]],1,4)&"_"&ROW(),"") -> TNV-MD01_64 | C64: MD01 - Fatura Energia | D64: Realizar validação Obrigações Acessórias - TaxOne | G64: Sergio Souza / Giovana Gonçalves | K64: Keyuser - Aguardando tarefa precedente
A65: =IF(Tabela49[[#This Row],[Cenário]]<>"","TNV-"&MID(Tabela49[[#This Row],[Cenário]],1,4)&"_"&ROW(),"") -> TNV-MD03_65 | C65: MD03 - Nota de Débito | D65: Gerar cenário e pedido | G65: Edson Oliveira | H65: 4501889051 | K65: Keyuser - Concluído | N65: 46002
A66: =IF(Tabela49[[#This Row],[Cenário]]<>"","TNV-"&MID(Tabela49[[#This Row],[Cenário]],1,4)&"_"&ROW(),"") -> TNV-MD03_66 | C66: MD03 - Nota de Débito | D66: Efetuar lançamento (escrituração fiscal) | G66: Edson Oliveira | H66: 46482798 | K66: TNV - Em correção | O66: Corrigir campo imposto estatístico
A67: =IF(Tabela49[[#This Row],[Cenário]]<>"","TNV-"&MID(Tabela49[[#This Row],[Cenário]],1,4)&"_"&ROW(),"") -> TNV-MD03_67 | C67: MD03 - Nota de Débito | D67: Configurar/Parametrizar IVAs | G67: Lívia Martins | K67: Keyuser - Aguardando tarefa precedente
A68: =IF(Tabela49[[#This Row],[Cenário]]<>"","TNV-"&MID(Tabela49[[#This Row],[Cenário]],1,4)&"_"&ROW(),"") -> TNV-MD03_68 | C68: MD03 - Nota de Débito | D68: Validar ICMS | G68: Giovana Gonçalves | K68: Keyuser - Aguardando tarefa precedente
A69: =IF(Tabela49[[#This Row],[Cenário]]<>"","TNV-"&MID(Tabela49[[#This Row],[Cenário]],1,4)&"_"&ROW(),"") -> TNV-MD03_69 | C69: MD03 - Nota de Débito | D69: Validar PIS/COFINS/IBS/CBS | G69: Talita Andrade | K69: Keyuser - Aguardando tarefa precedente
A70: =IF(Tabela49[[#This Row],[Cenário]]<>"","TNV-"&MID(Tabela49[[#This Row],[Cenário]],1,4)&"_"&ROW(),"") -> TNV-MD03_70 | C70: MD03 - Nota de Débito | D70: Validar Retenções | G70: Raquel dos Santos | K70: Keyuser - Aguardando tarefa precedente
A71: =IF(Tabela49[[#This Row],[Cenário]]<>"","TNV-"&MID(Tabela49[[#This Row],[Cenário]],1,4)&"_"&ROW(),"") -> TNV-MD03_71 | C71: MD03 - Nota de Débito | D71: Validação da contabilização | G71: Naiara Toledo | K71: Keyuser - Aguardando tarefa precedente
A72: =IF(Tabela49[[#This Row],[Cenário]]<>"","TNV-"&MID(Tabela49[[#This Row],[Cenário]],1,4)&"_"&ROW(),"") -> TNV-MD03_72 | C72: MD03 - Nota de Débito | D72: Validação título financeiro | G72: Elisa Alves | K72: Keyuser - Aguardando tarefa precedente
A73: =IF(Tabela49[[#This Row],[Cenário]]<>"","TNV-"&MID(Tabela49[[#This Row],[Cenário]],1,4)&"_"&ROW(),"") -> TNV-MD03_73 | C73: MD03 - Nota de Débito | D73: Realizar validação Obrigações Acessórias - TaxOne | G73: Sergio Souza / Giovana Gonçalves | K73: Keyuser - Aguardando tarefa precedente
A74: =IF(Tabela49[[#This Row],[Cenário]]<>"","TNV-"&MID(Tabela49[[#This Row],[Cenário]],1,4)&"_"&ROW(),"") -> TNV-MD04_74 | C74: MD04 - Telecomunicações | D74: Gerar cenário e pedido | G74: Edson Oliveira | H74: 4501889052 | K74: Keyuser - Concluído | N74: 46002
A75: =IF(Tabela49[[#This Row],[Cenário]]<>"","TNV-"&MID(Tabela49[[#This Row],[Cenário]],1,4)&"_"&ROW(),"") -> TNV-MD04_75 | C75: MD04 - Telecomunicações | D75: Efetuar lançamento (escrituração fiscal) | G75: Edson Oliveira | K75: TNV - Em correção | O75: Configuração IBS/CBS na categoria do cenário
A76: =IF(Tabela49[[#This Row],[Cenário]]<>"","TNV-"&MID(Tabela49[[#This Row],[Cenário]],1,4)&"_"&ROW(),"") -> TNV-MD04_76 | C76: MD04 - Telecomunicações | D76: Configurar/Parametrizar IVAs | G76: Lívia Martins | K76: Keyuser - Aguardando tarefa precedente
A77: =IF(Tabela49[[#This Row],[Cenário]]<>"","TNV-"&MID(Tabela49[[#This Row],[Cenário]],1,4)&"_"&ROW(),"") -> TNV-MD04_77 | C77: MD04 - Telecomunicações | D77: Validar ICMS | G77: Giovana Gonçalves | K77: Keyuser - Aguardando tarefa precedente
A78: =IF(Tabela49[[#This Row],[Cenário]]<>"","TNV-"&MID(Tabela49[[#This Row],[Cenário]],1,4)&"_"&ROW(),"") -> TNV-MD04_78 | C78: MD04 - Telecomunicações | D78: Validar PIS/COFINS/IBS/CBS | G78: Talita Andrade | K78: Keyuser - Aguardando tarefa precedente
A79: =IF(Tabela49[[#This Row],[Cenário]]<>"","TNV-"&MID(Tabela49[[#This Row],[Cenário]],1,4)&"_"&ROW(),"") -> TNV-MD04_79 | C79: MD04 - Telecomunicações | D79: Validar Retenções | G79: Raquel dos Santos | K79: Keyuser - Aguardando tarefa precedente
A80: =IF(Tabela49[[#This Row],[Cenário]]<>"","TNV-"&MID(Tabela49[[#This Row],[Cenário]],1,4)&"_"&ROW(),"") -> TNV-MD04_80 | C80: MD04 - Telecomunicações | D80: Validação da contabilização | G80: Naiara Toledo | K80: Keyuser - Aguardando tarefa precedente
A81: =IF(Tabela49[[#This Row],[Cenário]]<>"","TNV-"&MID(Tabela49[[#This Row],[Cenário]],1,4)&"_"&ROW(),"") -> TNV-MD04_81 | C81: MD04 - Telecomunicações | D81: Validação título financeiro | G81: Elisa Alves | K81: Keyuser - Aguardando tarefa precedente
A82: =IF(Tabela49[[#This Row],[Cenário]]<>"","TNV-"&MID(Tabela49[[#This Row],[Cenário]],1,4)&"_"&ROW(),"") -> TNV-MD04_82 | C82: MD04 - Telecomunicações | D82: Realizar validação Obrigações Acessórias - TaxOne | G82: Sergio Souza / Giovana Gonçalves | K82: Keyuser - Aguardando tarefa precedente
A83: =IF(Tabela49[[#This Row],[Cenário]]<>"","TNV-"&MID(Tabela49[[#This Row],[Cenário]],1,4)&"_"&ROW(),"") -> TNV-MD06_83 | C83: MD06 - Locação | D83: Gerar cenário e pedido | G83: Edson Oliveira | H83: 4501889053 | K83: Keyuser - Concluído | N83: 46002
A84: =IF(Tabela49[[#This Row],[Cenário]]<>"","TNV-"&MID(Tabela49[[#This Row],[Cenário]],1,4)&"_"&ROW(),"") -> TNV-MD06_84 | C84: MD06 - Locação | D84: Efetuar lançamento (escrituração fiscal) | G84: Edson Oliveira | H84: 46482702 | K84: TNV - Em correção | O84: Configuração IBS/CBS na categoria do cenário
A85: =IF(Tabela49[[#This Row],[Cenário]]<>"","TNV-"&MID(Tabela49[[#This Row],[Cenário]],1,4)&"_"&ROW(),"") -> TNV-MD06_85 | C85: MD06 - Locação | D85: Configurar/Parametrizar IVAs | G85: Lívia Martins | K85: Keyuser - Aguardando tarefa precedente
A86: =IF(Tabela49[[#This Row],[Cenário]]<>"","TNV-"&MID(Tabela49[[#This Row],[Cenário]],1,4)&"_"&ROW(),"") -> TNV-MD06_86 | C86: MD06 - Locação | D86: Validar ICMS | G86: Giovana Gonçalves | K86: Keyuser - Aguardando tarefa precedente
A87: =IF(Tabela49[[#This Row],[Cenário]]<>"","TNV-"&MID(Tabela49[[#This Row],[Cenário]],1,4)&"_"&ROW(),"") -> TNV-MD06_87 | C87: MD06 - Locação | D87: Validar PIS/COFINS/IBS/CBS | G87: Talita Andrade | K87: Keyuser - Aguardando tarefa precedente
A88: =IF(Tabela49[[#This Row],[Cenário]]<>"","TNV-"&MID(Tabela49[[#This Row],[Cenário]],1,4)&"_"&ROW(),"") -> TNV-MD06_88 | C88: MD06 - Locação | D88: Validar Retenções | G88: Raquel dos Santos | K88: Keyuser - Aguardando tarefa precedente
A89: =IF(Tabela49[[#This Row],[Cenário]]<>"","TNV-"&MID(Tabela49[[#This Row],[Cenário]],1,4)&"_"&ROW(),"") -> TNV-MD06_89 | C89: MD06 - Locação | D89: Validação da contabilização | G89: Naiara Toledo | K89: Keyuser - Aguardando tarefa precedente
A90: =IF(Tabela49[[#This Row],[Cenário]]<>"","TNV-"&MID(Tabela49[[#This Row],[Cenário]],1,4)&"_"&ROW(),"") -> TNV-MD06_90 | C90: MD06 - Locação | D90: Validação título financeiro | G90: Elisa Alves | K90: Keyuser - Aguardando tarefa precedente
A91: =IF(Tabela49[[#This Row],[Cenário]]<>"","TNV-"&MID(Tabela49[[#This Row],[Cenário]],1,4)&"_"&ROW(),"") -> TNV-MD06_91 | C91: MD06 - Locação | D91: Realizar validação Obrigações Acessórias - TaxOne | G91: Sergio Souza / Giovana Gonçalves | K91: Keyuser - Aguardando tarefa precedente
A92: =IF(Tabela49[[#This Row],[Cenário]]<>"","TNV-"&MID(Tabela49[[#This Row],[Cenário]],1,4)&"_"&ROW(),"") -> TNV-MD08_92 | C92: MD08 - RPA | D92: Gerar cenário e pedido | G92: Edson Oliveira | H92: 4501889078 | K92: Keyuser - Concluído | N92: 46002 | O92: Configuração IBS/CBS na categoria do cenário
A93: =IF(Tabela49[[#This Row],[Cenário]]<>"","TNV-"&MID(Tabela49[[#This Row],[Cenário]],1,4)&"_"&ROW(),"") -> TNV-MD08_93 | C93: MD08 - RPA | D93: Efetuar lançamento (escrituração fiscal) | G93: Edson Oliveira | K93: Keyuser - Aguardando tarefa precedente
A94: =IF(Tabela49[[#This Row],[Cenário]]<>"","TNV-"&MID(Tabela49[[#This Row],[Cenário]],1,4)&"_"&ROW(),"") -> TNV-MD08_94 | C94: MD08 - RPA | D94: Configurar/Parametrizar IVAs | G94: Lívia Martins | K94: Keyuser - Aguardando tarefa precedente
A95: =IF(Tabela49[[#This Row],[Cenário]]<>"","TNV-"&MID(Tabela49[[#This Row],[Cenário]],1,4)&"_"&ROW(),"") -> TNV-MD08_95 | C95: MD08 - RPA | D95: Validar ICMS | G95: Giovana Gonçalves | K95: Keyuser - Aguardando tarefa precedente
A96: =IF(Tabela49[[#This Row],[Cenário]]<>"","TNV-"&MID(Tabela49[[#This Row],[Cenário]],1,4)&"_"&ROW(),"") -> TNV-MD08_96 | C96: MD08 - RPA | D96: Validar PIS/COFINS/IBS/CBS | G96: Talita Andrade | K96: Keyuser - Aguardando tarefa precedente
A97: =IF(Tabela49[[#This Row],[Cenário]]<>"","TNV-"&MID(Tabela49[[#This Row],[Cenário]],1,4)&"_"&ROW(),"") -> TNV-MD08_97 | C97: MD08 - RPA | D97: Validar Retenções | G97: Raquel dos Santos | K97: Keyuser - Aguardando tarefa precedente
A98: =IF(Tabela49[[#This Row],[Cenário]]<>"","TNV-"&MID(Tabela49[[#This Row],[Cenário]],1,4)&"_"&ROW(),"") -> TNV-MD08_98 | C98: MD08 - RPA | D98: Validação da contabilização | G98: Naiara Toledo | K98: Keyuser - Aguardando tarefa precedente
A99: =IF(Tabela49[[#This Row],[Cenário]]<>"","TNV-"&MID(Tabela49[[#This Row],[Cenário]],1,4)&"_"&ROW(),"") -> TNV-MD08_99 | C99: MD08 - RPA | D99: Validação título financeiro | G99: Elisa Alves | K99: Keyuser - Aguardando tarefa precedente
A100: =IF(Tabela49[[#This Row],[Cenário]]<>"","TNV-"&MID(Tabela49[[#This Row],[Cenário]],1,4)&"_"&ROW(),"") -> TNV-MD08_100 | C100: MD08 - RPA | D100: Realizar validação Obrigações Acessórias - TaxOne | G100: Sergio Souza / Giovana Gonçalves | K100: Keyuser - Aguardando tarefa precedente
...

Sheet Analise-TNV
A1: OUTBOUND
H3: Responsável | I3: Testes QTD | J3: Testes %
H4: Keyuser - Aguardando tarefa precedente | I4: 79 | J4: 0.66949153
H5: Keyuser - Concluído | I5: 15 | J5: 0.12711864
H6: Keyuser - Pendente | I6: 14 | J6: 0.11864407
H7: TNV - Em correção | I7: 10 | J7: 0.084745763
H8: Total Geral | I8: 118 | J8: 1
H13: META DO DIA
H14: Expectativa para conclusão | I14: 46003
H15: Dias uteis até conclusão | I15: =NETWORKDAYS(TODAY(),I14) -> 2
H16: Testes Pendentes | I16: =COUNTIFS(Tabela49[[#All],[Status]],"*")-(COUNTIFS(Tabela49[[#All],[Status]],"Keyuser - Concluído ")+COUNTIFS(Tabela49[[#All],[Status]],"Não se Aplica")) -> 104
H17: Meta para o dia | I17: =I16/I15 -> 52
H20: Status | I20: TNV - Em correção
H22: Responsável | I22: Cenário | J22: Tarefa | K22: Responsável | L22: Contagem de ID
H23: TNV-CT02_12 | I23: CT02 - CTe Compras - Débito Posterior | J23: Efetuar lançamento (escrituração fiscal) | K23: Edson Oliveira | L23: 1
H24: TNV-CT05_20 | I24: CT05 - CTe Writer | J24: Gerar cenário e pedido | K24: Edson Oliveira | L24: 1
H25: TNV-CT10_48 | I25: CT10 - CTe Serviços 67 | J25: Efetuar lançamento (escrituração fiscal) | K25: Edson Oliveira | L25: 1
H26: TNV-MD01_57 | I26: MD01 - Fatura Energia | J26: Efetuar lançamento (escrituração fiscal) | K26: Edson Oliveira | L26: 1
A27: Data | B27: Concluídos | C27: Méta Dia | D27: Saldo Dia | H27: TNV-MD03_66 | I27: MD03 - Nota de Débito | J27: Efetuar lançamento (escrituração fiscal) | K27: Edson Oliveira | L27: 1
A28: 46001 | B28: =COUNTIFS(TNV!N:N,A28,TNV!K:K,"Keyuser - Concluído ") -> 5 | C28: 5 | D28: =B28-C28 -> 0 | H28: TNV-MD04_75 | I28: MD04 - Telecomunicações | J28: Efetuar lançamento (escrituração fiscal) | K28: Edson Oliveira | L28: 1
A29: 46002 | B29: =COUNTIFS(TNV!N:N,A29,TNV!K:K,"Keyuser - Concluído ") -> 10 | C29: 53 | D29: =B29-C29 -> -43 | H29: TNV-MD06_84 | I29: MD06 - Locação | J29: Efetuar lançamento (escrituração fiscal) | K29: Edson Oliveira | L29: 1
H30: TNV-NS01_102 | I30: NS01 - Serviços Diversos | J30: Efetuar lançamento (escrituração fiscal) | K30: Edson Oliveira | L30: 1
H31: TNV-NS02_111 | I31: NS02 - Serviços DPO | J31: Efetuar lançamento (escrituração fiscal) | K31: Edson Oliveira | L31: 1
H32: TNV-NS03_120 | I32: NS03 - Serviços - Folha de Serviço | J32: Efetuar lançamento (escrituração fiscal) | K32: Edson Oliveira | L32: 1
H33: Total Geral | L33: 10
A37: LIBERADOS
A39: Status | B39: Keyuser - Pendente | F39: Status | G39: Keyuser - Aguardando tarefa precedente
A40: Liberado para Testes? | B40: (vazio) | F40: Liberado para Testes? | G40: (Tudo)
A42: Responsável | B42: ID | C42: Cenário | D42: Testes QTD | F42: Responsável | G42: ID | H42: Tarefa | I42: Cenário | J42: Testes QTD
A43: Lívia Martins | B43: TNV-CT01_4 | C43: CT01 - CTe Vendas | D43: 1 | F43: Raquel dos Santos | J43: 11
B44: TNV-CT09_40 | C44: CT09B - CTe Outros sem folha | D44: 1 | F44: Elisa Alves | J44: 11
A45: Elisa Alves | B45: TNV-CT01_9 | C45: CT01 - CTe Vendas | D45: 1 | F45: Naiara Toledo | J45: 11
B46: TNV-CT09_45 | C46: CT09B - CTe Outros sem folha | D46: 1 | F46: Lívia Martins | J46: 11
A47: Naiara Toledo | B47: TNV-CT01_8 | C47: CT01 - CTe Vendas | D47: 1 | F47: Sergio Souza / Giovana Gonçalves | J47: 11
B48: TNV-CT09_44 | C48: CT09B - CTe Outros sem folha | D48: 1 | F48: Giovana Gonçalves | J48: 11
A49: Giovana Gonçalves | B49: TNV-CT01_5 | C49: CT01 - CTe Vendas | D49: 1 | F49: Talita Andrade | J49: 11
B50: TNV-CT09_41 | C50: CT09B - CTe Outros sem folha | D50: 1 | F50: Edson Oliveira | J50: 2
A51: Sergio Souza / Giovana Gonçalves | B51: TNV-CT01_10 | C51: CT01 - CTe Vendas | D51: 1 | F51: Total Geral | J51: 79
B52: TNV-CT09_46 | C52: CT09B - CTe Outros sem folha | D52: 1
A53: Talita Andrade | B53: TNV-CT01_6 | C53: CT01 - CTe Vendas | D53: 1
B54: TNV-CT09_42 | C54: CT09B - CTe Outros sem folha | D54: 1
A55: Raquel dos Santos | B55: TNV-CT01_7 | C55: CT01 - CTe Vendas | D55: 1
B56: TNV-CT09_43 | C56: CT09B - CTe Outros sem folha | D56: 1
A57: Total Geral | D57: 14
A63: COM PROBLEMAS
A65: Status | B65: TNV - Em correção | C65: TI bp - Em correção
A67: Responsável | B67: ID | C67: Cenário | D67: Testes QTD
A68: Edson Oliveira | B68: TNV-CT02_12 | C68: CT02 - CTe Compras - Débito Posterior | D68: 1
B69: TNV-CT05_20 | C69: CT05 - CTe Writer | D69: 1
B70: TNV-CT10_48 | C70: CT10 - CTe Serviços 67 | D70: 1
B71: TNV-MD01_57 | C71: MD01 - Fatura Energia | D71: 1
B72: TNV-MD03_66 | C72: MD03 - Nota de Débito | D72: 1
B73: TNV-MD04_75 | C73: MD04 - Telecomunicações | D73: 1
B74: TNV-MD06_84 | C74: MD06 - Locação | D74: 1
B75: TNV-NS01_102 | C75: NS01 - Serviços Diversos | D75: 1
B76: TNV-NS02_111 | C76: NS02 - Serviços DPO | D76: 1
B77: TNV-NS03_120 | C77: NS03 - Serviços - Folha de Serviço | D77: 1
A78: Total Geral | D78: 10

Sheet Outbound
A1: ID | B1: Liberado para Testes? | C1: Cenário | D1: Tarefa | E1: Sequência | F1: Descrição | G1: Responsável | H1: DOC BEC | I1: Doc Ref BEP | J1: Conferência Elo | K1: Status | L1: Dt Inicial | M1: Tempo Previsto | N1: Dt Conclusão | O1: Observação | P1: ID Tarefa Precedente | Q1: Tarefas por Cenário | R1: Tarefas Concluídas | S1: Cenário Concluído | T1: Elo - Em correção | U1: Keyuser - Aguardando tarefa precedente | V1: Não liberado para testes | W1: Em correção? | X1: Precedentes? | Y1: Bloqueado? | Z1: Dias em pendente Keyuser | AA1: Impedindo processeguir?
A2: ="OUT-"&IFERROR(MID(Tabela4[[#This Row],[Cenário]],SEARCH("(",Tabela4[[#This Row],[Cenário]])+1,SEARCH(")",Tabela4[[#This Row],[Cenário]])-SEARCH("(",Tabela4[[#This Row],[Cenário]])-1),"")&"_"&ROW() -> OUT-Y002_2 | B2: Sim | C2: Venda Etanol Hidratado D.E (Y002) | D2: Criar ordem de venda | E2: 1 | F2: Criar ordem de venda | G2: Vania Esteves | H2: 15603600 | I2: BEP: 15572935 | J2: OK | K2: Keyuser - Concluído | L2: 45944 | N2: 45944 | Q2: =COUNTIF(Tabela4[[#All],[Cenário]],Tabela4[[#This Row],[Cenário]]) -> 8 | R2: =COUNTIFS(Tabela4[[#All],[Cenário]],Tabela4[[#This Row],[Cenário]],Tabela4[[#All],[Status]],"Keyuser - Concluído ") -> 7 | S2: =IF(Tabela4[[#This Row],[Tarefas por Cenário]]-Tabela4[[#This Row],[Tarefas Concluídas]]>0,"Não","Sim") -> Não | T2: =COUNTIFS(Tabela4[[#All],[Cenário]],Tabela4[[#This Row],[Cenário]],Tabela4[[#All],[Status]],Tabela4[[#Headers],[Elo - Em correção ]]) -> 0 | U2: =COUNTIFS(Tabela4[[#All],[Cenário]],Tabela4[[#This Row],[Cenário]],Tabela4[[#All],[Status]],Tabela4[[#Headers],[Keyuser - Aguardando tarefa precedente]]) -> 0 | V2: =COUNTIFS(Tabela4[[#All],[Cenário]],Tabela4[[#This Row],[Cenário]],Tabela4[[#All],[Status]],Tabela4[[#Headers],[Não liberado para testes]]) -> 1 | W2: =IF(Tabela4[[#This Row],[Elo - Em correção ]]>0,"Sim","Não") -> Não | X2: =IF(Tabela4[[#This Row],[Keyuser - Aguardando tarefa precedente]]>0,"Sim","Não") -> Não | Y2: =IF(Tabela4[[#This Row],[Não liberado para testes]]>0,"Sim","Não") -> Sim | Z2: =IF(Tabela4[[#This Row],[Status]]="Keyuser - Pendente",NETWORKDAYS(Tabela4[[#This Row],[Dt Inicial]],TODAY()),"") | AA2: =AND(Tabela4[[#This Row],[Status]]="Keyuser - Aguardando tarefa precedente",K1="Keyuser - Concluído ") -> FALSE
A3: ="OUT-"&IFERROR(MID(Tabela4[[#This Row],[Cenário]],SEARCH("(",Tabela4[[#This Row],[Cenário]])+1,SEARCH(")",Tabela4[[#This Row],[Cenário]])-SEARCH("(",Tabela4[[#This Row],[Cenário]])-1),"")&"_"&ROW() -> OUT-Y002_3 | B3: Sim | C3: Venda Etanol Hidratado D.E (Y002) | D3: Realizar validação tributária - Ordem de venda | E3: 2 | F3: Realizar validação tributária - Ordem de venda | G3: Livia Beserra | H3: 15603600 | I3: BEP: 15572935 | J3: OK | K3: Keyuser - Concluído | L3: 45944 | N3: 45944 | Q3: =COUNTIF(Tabela4[[#All],[Cenário]],Tabela4[[#This Row],[Cenário]]) -> 8 | R3: =COUNTIFS(Tabela4[[#All],[Cenário]],Tabela4[[#This Row],[Cenário]],Tabela4[[#All],[Status]],"Keyuser - Concluído ") -> 7 | S3: =IF(Tabela4[[#This Row],[Tarefas por Cenário]]-Tabela4[[#This Row],[Tarefas Concluídas]]>0,"Não","Sim") -> Não | T3: =COUNTIFS(Tabela4[[#All],[Cenário]],Tabela4[[#This Row],[Cenário]],Tabela4[[#All],[Status]],Tabela4[[#Headers],[Elo - Em correção ]]) -> 0 | U3: =COUNTIFS(Tabela4[[#All],[Cenário]],Tabela4[[#This Row],[Cenário]],Tabela4[[#All],[Status]],Tabela4[[#Headers],[Keyuser - Aguardando tarefa precedente]]) -> 0 | V3: =COUNTIFS(Tabela4[[#All],[Cenário]],Tabela4[[#This Row],[Cenário]],Tabela4[[#All],[Status]],Tabela4[[#Headers],[Não liberado para testes]]) -> 1 | W3: =IF(Tabela4[[#This Row],[Elo - Em correção ]]>0,"Sim","Não") -> Não | X3: =IF(Tabela4[[#This Row],[Keyuser - Aguardando tarefa precedente]]>0,"Sim","Não") -> Não | Y3: =IF(Tabela4[[#This Row],[Não liberado para testes]]>0,"Sim","Não") -> Sim | Z3: =IF(Tabela4[[#This Row],[Status]]="Keyuser - Pendente",NETWORKDAYS(Tabela4[[#This Row],[Dt Inicial]],TODAY()),"") | AA3: =AND(Tabela4[[#This Row],[Status]]="Keyuser - Aguardando tarefa precedente",K2="Keyuser - Concluído ") -> FALSE
A4: ="OUT-"&IFERROR(MID(Tabela4[[#This Row],[Cenário]],SEARCH("(",Tabela4[[#This Row],[Cenário]])+1,SEARCH(")",Tabela4[[#This Row],[Cenário]])-SEARCH("(",Tabela4[[#This Row],[Cenário]])-1),"")&"_"&ROW() -> OUT-Y002_4 | B4: Sim | C4: Venda Etanol Hidratado D.E (Y002) | D4: Liberar ordem de venda | E4: 3 | F4: Liberar ordem de venda | G4: Patrick Vianna / Aline Russo | H4: 15603600 | I4: BEP: 15572935 | J4: OK | K4: Keyuser - Concluído | L4: 45945 | N4: 45945 | Q4: =COUNTIF(Tabela4[[#All],[Cenário]],Tabela4[[#This Row],[Cenário]]) -> 8 | R4: =COUNTIFS(Tabela4[[#All],[Cenário]],Tabela4[[#This Row],[Cenário]],Tabela4[[#All],[Status]],"Keyuser - Concluído ") -> 7 | S4: =IF(Tabela4[[#This Row],[Tarefas por Cenário]]-Tabela4[[#This Row],[Tarefas Concluídas]]>0,"Não","Sim") -> Não | T4: =COUNTIFS(Tabela4[[#All],[Cenário]],Tabela4[[#This Row],[Cenário]],Tabela4[[#All],[Status]],Tabela4[[#Headers],[Elo - Em correção ]]) -> 0 | U4: =COUNTIFS(Tabela4[[#All],[Cenário]],Tabela4[[#This Row],[Cenário]],Tabela4[[#All],[Status]],Tabela4[[#Headers],[Keyuser - Aguardando tarefa precedente]]) -> 0 | V4: =COUNTIFS(Tabela4[[#All],[Cenário]],Tabela4[[#This Row],[Cenário]],Tabela4[[#All],[Status]],Tabela4[[#Headers],[Não liberado para testes]]) -> 1 | W4: =IF(Tabela4[[#This Row],[Elo - Em correção ]]>0,"Sim","Não") -> Não | X4: =IF(Tabela4[[#This Row],[Keyuser - Aguardando tarefa precedente]]>0,"Sim","Não") -> Não | Y4: =IF(Tabela4[[#This Row],[Não liberado para testes]]>0,"Sim","Não") -> Sim | Z4: =IF(Tabela4[[#This Row],[Status]]="Keyuser - Pendente",NETWORKDAYS(Tabela4[[#This Row],[Dt Inicial]],TODAY()),"") | AA4: =AND(Tabela4[[#This Row],[Status]]="Keyuser - Aguardando tarefa precedente",K3="Keyuser - Concluído ") -> FALSE
A5: ="OUT-"&IFERROR(MID(Tabela4[[#This Row],[Cenário]],SEARCH("(",Tabela4[[#This Row],[Cenário]])+1,SEARCH(")",Tabela4[[#This Row],[Cenário]])-SEARCH("(",Tabela4[[#This Row],[Cenário]])-1),"")&"_"&ROW() -> OUT-Y002_5 | B5: Sim | C5: Venda Etanol Hidratado D.E (Y002) | D5: Realizar faturamento | E5: 4 | F5: Realizar faturamento | G5: Francisco Netto | H5: DocNum - 46482170 | K5: Keyuser - Concluído | L5: 45945 | N5: 45945 | Q5: =COUNTIF(Tabela4[[#All],[Cenário]],Tabela4[[#This Row],[Cenário]]) -> 8 | R5: =COUNTIFS(Tabela4[[#All],[Cenário]],Tabela4[[#This Row],[Cenário]],Tabela4[[#All],[Status]],"Keyuser - Concluído ") -> 7 | S5: =IF(Tabela4[[#This Row],[Tarefas por Cenário]]-Tabela4[[#This Row],[Tarefas Concluídas]]>0,"Não","Sim") -> Não | T5: =COUNTIFS(Tabela4[[#All],[Cenário]],Tabela4[[#This Row],[Cenário]],Tabela4[[#All],[Status]],Tabela4[[#Headers],[Elo - Em correção ]]) -> 0 | U5: =COUNTIFS(Tabela4[[#All],[Cenário]],Tabela4[[#This Row],[Cenário]],Tabela4[[#All],[Status]],Tabela4[[#Headers],[Keyuser - Aguardando tarefa precedente]]) -> 0 | V5: =COUNTIFS(Tabela4[[#All],[Cenário]],Tabela4[[#This Row],[Cenário]],Tabela4[[#All],[Status]],Tabela4[[#Headers],[Não liberado para testes]]) -> 1 | W5: =IF(Tabela4[[#This Row],[Elo - Em correção ]]>0,"Sim","Não") -> Não | X5: =IF(Tabela4[[#This Row],[Keyuser - Aguardando tarefa precedente]]>0,"Sim","Não") -> Não | Y5: =IF(Tabela4[[#This Row],[Não liberado para testes]]>0,"Sim","Não") -> Sim | Z5: =IF(Tabela4[[#This Row],[Status]]="Keyuser - Pendente",NETWORKDAYS(Tabela4[[#This Row],[Dt Inicial]],TODAY()),"") | AA5: =AND(Tabela4[[#This Row],[Status]]="Keyuser - Aguardando tarefa precedente",K4="Keyuser - Concluído ") -> FALSE
A6: ="OUT-"&IFERROR(MID(Tabela4[[#This Row],[Cenário]],SEARCH("(",Tabela4[[#This Row],[Cenário]])+1,SEARCH(")",Tabela4[[#This Row],[Cenário]])-SEARCH("(",Tabela4[[#This Row],[Cenário]])-1),"")&"_"&ROW() -> OUT-Y002_6 | B6: Sim | C6: Venda Etanol Hidratado D.E (Y002) | D6: Realizar validação tributária - SAP, XML e DANFE | E6: 5 | F6: Realizar validação tributária - SAP (xml e DANFE) | G6: Sergio Souza / Giovana Gonçalves | H6: DocNum - 46482170 | K6: Keyuser - Concluído | L6: 45945 | N6: 45945 | Q6: =COUNTIF(Tabela4[[#All],[Cenário]],Tabela4[[#This Row],[Cenário]]) -> 8 | R6: =COUNTIFS(Tabela4[[#All],[Cenário]],Tabela4[[#This Row],[Cenário]],Tabela4[[#All],[Status]],"Keyuser - Concluído ") -> 7 | S6: =IF(Tabela4[[#This Row],[Tarefas por Cenário]]-Tabela4[[#This Row],[Tarefas Concluídas]]>0,"Não","Sim") -> Não | T6: =COUNTIFS(Tabela4[[#All],[Cenário]],Tabela4[[#This Row],[Cenário]],Tabela4[[#All],[Status]],Tabela4[[#Headers],[Elo - Em correção ]]) -> 0 | U6: =COUNTIFS(Tabela4[[#All],[Cenário]],Tabela4[[#This Row],[Cenário]],Tabela4[[#All],[Status]],Tabela4[[#Headers],[Keyuser - Aguardando tarefa precedente]]) -> 0 | V6: =COUNTIFS(Tabela4[[#All],[Cenário]],Tabela4[[#This Row],[Cenário]],Tabela4[[#All],[Status]],Tabela4[[#Headers],[Não liberado para testes]]) -> 1 | W6: =IF(Tabela4[[#This Row],[Elo - Em correção ]]>0,"Sim","Não") -> Não | X6: =IF(Tabela4[[#This Row],[Keyuser - Aguardando tarefa precedente]]>0,"Sim","Não") -> Não | Y6: =IF(Tabela4[[#This Row],[Não liberado para testes]]>0,"Sim","Não") -> Sim | Z6: =IF(Tabela4[[#This Row],[Status]]="Keyuser - Pendente",NETWORKDAYS(Tabela4[[#This Row],[Dt Inicial]],TODAY()),"") | AA6: =AND(Tabela4[[#This Row],[Status]]="Keyuser - Aguardando tarefa precedente",K5="Keyuser - Concluído ") -> FALSE
A7: ="OUT-"&IFERROR(MID(Tabela4[[#This Row],[Cenário]],SEARCH("(",Tabela4[[#This Row],[Cenário]])+1,SEARCH(")",Tabela4[[#This Row],[Cenário]])-SEARCH("(",Tabela4[[#This Row],[Cenário]])-1),"")&"_"&ROW() -> OUT-Y002_7 | B7: Sim | C7: Venda Etanol Hidratado D.E (Y002) | D7: Realizar validação contábil | E7: 6 | F7: Realizar validação contábil | G7: Naiara Toledo | H7: DocNum - 46482170 | K7: Keyuser - Concluído | L7: 45945 | N7: 45945 | Q7: =COUNTIF(Tabela4[[#All],[Cenário]],Tabela4[[#This Row],[Cenário]]) -> 8 | R7: =COUNTIFS(Tabela4[[#All],[Cenário]],Tabela4[[#This Row],[Cenário]],Tabela4[[#All],[Status]],"Keyuser - Concluído ") -> 7 | S7: =IF(Tabela4[[#This Row],[Tarefas por Cenário]]-Tabela4[[#This Row],[Tarefas Concluídas]]>0,"Não","Sim") -> Não | T7: =COUNTIFS(Tabela4[[#All],[Cenário]],Tabela4[[#This Row],[Cenário]],Tabela4[[#All],[Status]],Tabela4[[#Headers],[Elo - Em correção ]]) -> 0 | U7: =COUNTIFS(Tabela4[[#All],[Cenário]],Tabela4[[#This Row],[Cenário]],Tabela4[[#All],[Status]],Tabela4[[#Headers],[Keyuser - Aguardando tarefa precedente]]) -> 0 | V7: =COUNTIFS(Tabela4[[#All],[Cenário]],Tabela4[[#This Row],[Cenário]],Tabela4[[#All],[Status]],Tabela4[[#Headers],[Não liberado para testes]]) -> 1 | W7: =IF(Tabela4[[#This Row],[Elo - Em correção ]]>0,"Sim","Não") -> Não | X7: =IF(Tabela4[[#This Row],[Keyuser - Aguardando tarefa precedente]]>0,"Sim","Não") -> Não | Y7: =IF(Tabela4[[#This Row],[Não liberado para testes]]>0,"Sim","Não") -> Sim | Z7: =IF(Tabela4[[#This Row],[Status]]="Keyuser - Pendente",NETWORKDAYS(Tabela4[[#This Row],[Dt Inicial]],TODAY()),"") | AA7: =AND(Tabela4[[#This Row],[Status]]="Keyuser - Aguardando tarefa precedente",K6="Keyuser - Concluído ") -> FALSE
A8: ="OUT-"&IFERROR(MID(Tabela4[[#This Row],[Cenário]],SEARCH("(",Tabela4[[#This Row],[Cenário]])+1,SEARCH(")",Tabela4[[#This Row],[Cenário]])-SEARCH("(",Tabela4[[#This Row],[Cenário]])-1),"")&"_"&ROW() -> OUT-Y002_8 | B8: Não | C8: Venda Etanol Hidratado D.E (Y002) | D8: Realizar validação Obrigações Acessórias - TaxOne | E8: 7 | F8: Realizar validação Obrigações Acessórias - TaxOne | G8: Sergio Souza / Giovana Gonçalves | K8: Não liberado para testes | Q8: =COUNTIF(Tabela4[[#All],[Cenário]],Tabela4[[#This Row],[Cenário]]) -> 8 | R8: =COUNTIFS(Tabela4[[#All],[Cenário]],Tabela4[[#This Row],[Cenário]],Tabela4[[#All],[Status]],"Keyuser - Concluído ") -> 7 | S8: =IF(Tabela4[[#This Row],[Tarefas por Cenário]]-Tabela4[[#This Row],[Tarefas Concluídas]]>0,"Não","Sim") -> Não | T8: =COUNTIFS(Tabela4[[#All],[Cenário]],Tabela4[[#This Row],[Cenário]],Tabela4[[#All],[Status]],Tabela4[[#Headers],[Elo - Em correção ]]) -> 0 | U8: =COUNTIFS(Tabela4[[#All],[Cenário]],Tabela4[[#This Row],[Cenário]],Tabela4[[#All],[Status]],Tabela4[[#Headers],[Keyuser - Aguardando tarefa precedente]]) -> 0 | V8: =COUNTIFS(Tabela4[[#All],[Cenário]],Tabela4[[#This Row],[Cenário]],Tabela4[[#All],[Status]],Tabela4[[#Headers],[Não liberado para testes]]) -> 1 | W8: =IF(Tabela4[[#This Row],[Elo - Em correção ]]>0,"Sim","Não") -> Não | X8: =IF(Tabela4[[#This Row],[Keyuser - Aguardando tarefa precedente]]>0,"Sim","Não") -> Não | Y8: =IF(Tabela4[[#This Row],[Não liberado para testes]]>0,"Sim","Não") -> Sim | Z8: =IF(Tabela4[[#This Row],[Status]]="Keyuser - Pendente",NETWORKDAYS(Tabela4[[#This Row],[Dt Inicial]],TODAY()),"") | AA8: =AND(Tabela4[[#This Row],[Status]]="Keyuser - Aguardando tarefa precedente",K7="Keyuser - Concluído ") -> FALSE
A9: ="OUT-"&IFERROR(MID(Tabela4[[#This Row],[Cenário]],SEARCH("(",Tabela4[[#This Row],[Cenário]])+1,SEARCH(")",Tabela4[[#This Row],[Cenário]])-SEARCH("(",Tabela4[[#This Row],[Cenário]])-1),"")&"_"&ROW() -> OUT-Y002_9 | B9: Sim | C9: Venda Etanol Hidratado D.E (Y002) | D9: Realizar validação Títulos Financeiros | E9: 8 | F9: Realizar validação Títulos Financeiros | G9: Patrick Vianna / Aline Russo | H9: 15603600 | I9: BEP: 15572935 | J9: OK | K9: Keyuser - Concluído | L9: 45950 | N9: 45950 | Q9: =COUNTIF(Tabela4[[#All],[Cenário]],Tabela4[[#This Row],[Cenário]]) -> 8 | R9: =COUNTIFS(Tabela4[[#All],[Cenário]],Tabela4[[#This Row],[Cenário]],Tabela4[[#All],[Status]],"Keyuser - Concluído ") -> 7 | S9: =IF(Tabela4[[#This Row],[Tarefas por Cenário]]-Tabela4[[#This Row],[Tarefas Concluídas]]>0,"Não","Sim") -> Não | T9: =COUNTIFS(Tabela4[[#All],[Cenário]],Tabela4[[#This Row],[Cenário]],Tabela4[[#All],[Status]],Tabela4[[#Headers],[Elo - Em correção ]]) -> 0 | U9: =COUNTIFS(Tabela4[[#All],[Cenário]],Tabela4[[#This Row],[Cenário]],Tabela4[[#All],[Status]],Tabela4[[#Headers],[Keyuser - Aguardando tarefa precedente]]) -> 0 | V9: =COUNTIFS(Tabela4[[#All],[Cenário]],Tabela4[[#This Row],[Cenário]],Tabela4[[#All],[Status]],Tabela4[[#Headers],[Não liberado para testes]]) -> 1 | W9: =IF(Tabela4[[#This Row],[Elo - Em correção ]]>0,"Sim","Não") -> Não | X9: =IF(Tabela4[[#This Row],[Keyuser - Aguardando tarefa precedente]]>0,"Sim","Não") -> Não | Y9: =IF(Tabela4[[#This Row],[Não liberado para testes]]>0,"Sim","Não") -> Sim | Z9: =IF(Tabela4[[#This Row],[Status]]="Keyuser - Pendente",NETWORKDAYS(Tabela4[[#This Row],[Dt Inicial]],TODAY()),"") | AA9: =AND(Tabela4[[#This Row],[Status]]="Keyuser - Aguardando tarefa precedente",K8="Keyuser - Concluído ") -> FALSE
A10: ="OUT-"&IFERROR(MID(Tabela4[[#This Row],[Cenário]],SEARCH("(",Tabela4[[#This Row],[Cenário]])+1,SEARCH(")",Tabela4[[#This Row],[Cenário]])-SEARCH("(",Tabela4[[#This Row],[Cenário]])-1),"")&"_"&ROW() -> OUT-YDEV_10 | B10: Sim | C10: Venda Etanol Hidratado D.E (YDEV) | D10: Criar ordem de venda | E10: 1 | F10: Criar ordem de venda | G10: Marcos Nunes | H10: 60668325 | K10: Keyuser - Concluído | L10: 45958 | N10: 45958 | Q10: =COUNTIF(Tabela4[[#All],[Cenário]],Tabela4[[#This Row],[Cenário]]) -> 6 | R10: =COUNTIFS(Tabela4[[#All],[Cenário]],Tabela4[[#This Row],[Cenário]],Tabela4[[#All],[Status]],"Keyuser - Concluído ") -> 5 | S10: =IF(Tabela4[[#This Row],[Tarefas por Cenário]]-Tabela4[[#This Row],[Tarefas Concluídas]]>0,"Não","Sim") -> Não | T10: =COUNTIFS(Tabela4[[#All],[Cenário]],Tabela4[[#This Row],[Cenário]],Tabela4[[#All],[Status]],Tabela4[[#Headers],[Elo - Em correção ]]) -> 0 | U10: =COUNTIFS(Tabela4[[#All],[Cenário]],Tabela4[[#This Row],[Cenário]],Tabela4[[#All],[Status]],Tabela4[[#Headers],[Keyuser - Aguardando tarefa precedente]]) -> 0 | V10: =COUNTIFS(Tabela4[[#All],[Cenário]],Tabela4[[#This Row],[Cenário]],Tabela4[[#All],[Status]],Tabela4[[#Headers],[Não liberado para testes]]) -> 1 | W10: =IF(Tabela4[[#This Row],[Elo - Em correção ]]>0,"Sim","Não") -> Não | X10: =IF(Tabela4[[#This Row],[Keyuser - Aguardando tarefa precedente]]>0,"Sim","Não") -> Não | Y10: =IF(Tabela4[[#This Row],[Não liberado para testes]]>0,"Sim","Não") -> Sim | Z10: =IF(Tabela4[[#This Row],[Status]]="Keyuser - Pendente",NETWORKDAYS(Tabela4[[#This Row],[Dt Inicial]],TODAY()),"") | AA10: =AND(Tabela4[[#This Row],[Status]]="Keyuser - Aguardando tarefa precedente",K9="Keyuser - Concluído ") -> FALSE
A11: ="OUT-"&IFERROR(MID(Tabela4[[#This Row],[Cenário]],SEARCH("(",Tabela4[[#This Row],[Cenário]])+1,SEARCH(")",Tabela4[[#This Row],[Cenário]])-SEARCH("(",Tabela4[[#This Row],[Cenário]])-1),"")&"_"&ROW() -> OUT-YDEV_11 | B11: Sim | C11: Venda Etanol Hidratado D.E (YDEV) | D11: Realizar validação tributária - Ordem de venda | E11: 2 | F11: Realizar validação tributária - Ordem de venda | G11: Livia Beserra | H11: 60668325 | K11: Keyuser - Concluído | L11: 45958 | N11: 45958 | Q11: =COUNTIF(Tabela4[[#All],[Cenário]],Tabela4[[#This Row],[Cenário]]) -> 6 | R11: =COUNTIFS(Tabela4[[#All],[Cenário]],Tabela4[[#This Row],[Cenário]],Tabela4[[#All],[Status]],"Keyuser - Concluído ") -> 5 | S11: =IF(Tabela4[[#This Row],[Tarefas por Cenário]]-Tabela4[[#This Row],[Tarefas Concluídas]]>0,"Não","Sim") -> Não | T11: =COUNTIFS(Tabela4[[#All],[Cenário]],Tabela4[[#This Row],[Cenário]],Tabela4[[#All],[Status]],Tabela4[[#Headers],[Elo - Em correção ]]) -> 0 | U11: =COUNTIFS(Tabela4[[#All],[Cenário]],Tabela4[[#This Row],[Cenário]],Tabela4[[#All],[Status]],Tabela4[[#Headers],[Keyuser - Aguardando tarefa precedente]]) -> 0 | V11: =COUNTIFS(Tabela4[[#All],[Cenário]],Tabela4[[#This Row],[Cenário]],Tabela4[[#All],[Status]],Tabela4[[#Headers],[Não liberado para testes]]) -> 1 | W11: =IF(Tabela4[[#This Row],[Elo - Em correção ]]>0,"Sim","Não") -> Não | X11: =IF(Tabela4[[#This Row],[Keyuser - Aguardando tarefa precedente]]>0,"Sim","Não") -> Não | Y11: =IF(Tabela4[[#This Row],[Não liberado para testes]]>0,"Sim","Não") -> Sim | Z11: =IF(Tabela4[[#This Row],[Status]]="Keyuser - Pendente",NETWORKDAYS(Tabela4[[#This Row],[Dt Inicial]],TODAY()),"") | AA11: =AND(Tabela4[[#This Row],[Status]]="Keyuser - Aguardando tarefa precedente",K10="Keyuser - Concluído ") -> FALSE
A12: ="OUT-"&IFERROR(MID(Tabela4[[#This Row],[Cenário]],SEARCH("(",Tabela4[[#This Row],[Cenário]])+1,SEARCH(")",Tabela4[[#This Row],[Cenário]])-SEARCH("(",Tabela4[[#This Row],[Cenário]])-1),"")&"_"&ROW() -> OUT-YDEV_12 | B12: Sim | C12: Venda Etanol Hidratado D.E (YDEV) | D12: Realizar faturamento | E12: 3 | F12: Realizar faturamento | G12: Marcos Nunes | H12: Doc Num - 46482274 | K12: Keyuser - Concluído | L12: 45958 | N12: 45958 | O12: Nota nr 149727 | Q12: =COUNTIF(Tabela4[[#All],[Cenário]],Tabela4[[#This Row],[Cenário]]) -> 6 | R12: =COUNTIFS(Tabela4[[#All],[Cenário]],Tabela4[[#This Row],[Cenário]],Tabela4[[#All],[Status]],"Keyuser - Concluído ") -> 5 | S12: =IF(Tabela4[[#This Row],[Tarefas por Cenário]]-Tabela4[[#This Row],[Tarefas Concluídas]]>0,"Não","Sim") -> Não | T12: =COUNTIFS(Tabela4[[#All],[Cenário]],Tabela4[[#This Row],[Cenário]],Tabela4[[#All],[Status]],Tabela4[[#Headers],[Elo - Em correção ]]) -> 0 | U12: =COUNTIFS(Tabela4[[#All],[Cenário]],Tabela4[[#This Row],[Cenário]],Tabela4[[#All],[Status]],Tabela4[[#Headers],[Keyuser - Aguardando tarefa precedente]]) -> 0 | V12: =COUNTIFS(Tabela4[[#All],[Cenário]],Tabela4[[#This Row],[Cenário]],Tabela4[[#All],[Status]],Tabela4[[#Headers],[Não liberado para testes]]) -> 1 | W12: =IF(Tabela4[[#This Row],[Elo - Em correção ]]>0,"Sim","Não") -> Não | X12: =IF(Tabela4[[#This Row],[Keyuser - Aguardando tarefa precedente]]>0,"Sim","Não") -> Não | Y12: =IF(Tabela4[[#This Row],[Não liberado para testes]]>0,"Sim","Não") -> Sim | Z12: =IF(Tabela4[[#This Row],[Status]]="Keyuser - Pendente",NETWORKDAYS(Tabela4[[#This Row],[Dt Inicial]],TODAY()),"") | AA12: =AND(Tabela4[[#This Row],[Status]]="Keyuser - Aguardando tarefa precedente",K11="Keyuser - Concluído ") -> FALSE
A13: ="OUT-"&IFERROR(MID(Tabela4[[#This Row],[Cenário]],SEARCH("(",Tabela4[[#This Row],[Cenário]])+1,SEARCH(")",Tabela4[[#This Row],[Cenário]])-SEARCH("(",Tabela4[[#This Row],[Cenário]])-1),"")&"_"&ROW() -> OUT-YDEV_13 | B13: Sim | C13: Venda Etanol Hidratado D.E (YDEV) | D13: Realizar validação tributária - SAP, XML e DANFE | E13: 4 | F13: Realizar validação tributária - SAP (xml e DANFE) | G13: Sergio Souza / Giovana Gonçalves | H13: Doc Num - 46482274 | K13: Keyuser - Concluído | L13: 45959 | N13: 45959 | Q13: =COUNTIF(Tabela4[[#All],[Cenário]],Tabela4[[#This Row],[Cenário]]) -> 6 | R13: =COUNTIFS(Tabela4[[#All],[Cenário]],Tabela4[[#This Row],[Cenário]],Tabela4[[#All],[Status]],"Keyuser - Concluído ") -> 5 | S13: =IF(Tabela4[[#This Row],[Tarefas por Cenário]]-Tabela4[[#This Row],[Tarefas Concluídas]]>0,"Não","Sim") -> Não | T13: =COUNTIFS(Tabela4[[#All],[Cenário]],Tabela4[[#This Row],[Cenário]],Tabela4[[#All],[Status]],Tabela4[[#Headers],[Elo - Em correção ]]) -> 0 | U13: =COUNTIFS(Tabela4[[#All],[Cenário]],Tabela4[[#This Row],[Cenário]],Tabela4[[#All],[Status]],Tabela4[[#Headers],[Keyuser - Aguardando tarefa precedente]]) -> 0 | V13: =COUNTIFS(Tabela4[[#All],[Cenário]],Tabela4[[#This Row],[Cenário]],Tabela4[[#All],[Status]],Tabela4[[#Headers],[Não liberado para testes]]) -> 1 | W13: =IF(Tabela4[[#This Row],[Elo - Em correção ]]>0,"Sim","Não") -> Não | X13: =IF(Tabela4[[#This Row],[Keyuser - Aguardando tarefa precedente]]>0,"Sim","Não") -> Não | Y13: =IF(Tabela4[[#This Row],[Não liberado para testes]]>0,"Sim","Não") -> Sim | Z13: =IF(Tabela4[[#This Row],[Status]]="Keyuser - Pendente",NETWORKDAYS(Tabela4[[#This Row],[Dt Inicial]],TODAY()),"") | AA13: =AND(Tabela4[[#This Row],[Status]]="Keyuser - Aguardando tarefa precedente",K12="Keyuser - Concluído ") -> FALSE
A14: ="OUT-"&IFERROR(MID(Tabela4[[#This Row],[Cenário]],SEARCH("(",Tabela4[[#This Row],[Cenário]])+1,SEARCH(")",Tabela4[[#This Row],[Cenário]])-SEARCH("(",Tabela4[[#This Row],[Cenário]])-1),"")&"_"&ROW() -> OUT-YDEV_14 | B14: Sim | C14: Venda Etanol Hidratado D.E (YDEV) | D14: Realizar validação contábil | E14: 5 | F14: Realizar validação contábil | G14: Naiara Toledo | H14: Doc Num - 46482274 | K14: Keyuser - Concluído | L14: 45960 | N14: 45960 | Q14: =COUNTIF(Tabela4[[#All],[Cenário]],Tabela4[[#This Row],[Cenário]]) -> 6 | R14: =COUNTIFS(Tabela4[[#All],[Cenário]],Tabela4[[#This Row],[Cenário]],Tabela4[[#All],[Status]],"Keyuser - Concluído ") -> 5 | S14: =IF(Tabela4[[#This Row],[Tarefas por Cenário]]-Tabela4[[#This Row],[Tarefas Concluídas]]>0,"Não","Sim") -> Não | T14: =COUNTIFS(Tabela4[[#All],[Cenário]],Tabela4[[#This Row],[Cenário]],Tabela4[[#All],[Status]],Tabela4[[#Headers],[Elo - Em correção ]]) -> 0 | U14: =COUNTIFS(Tabela4[[#All],[Cenário]],Tabela4[[#This Row],[Cenário]],Tabela4[[#All],[Status]],Tabela4[[#Headers],[Keyuser - Aguardando tarefa precedente]]) -> 0 | V14: =COUNTIFS(Tabela4[[#All],[Cenário]],Tabela4[[#This Row],[Cenário]],Tabela4[[#All],[Status]],Tabela4[[#Headers],[Não liberado para testes]]) -> 1 | W14: =IF(Tabela4[[#This Row],[Elo - Em correção ]]>0,"Sim","Não") -> Não | X14: =IF(Tabela4[[#This Row],[Keyuser - Aguardando tarefa precedente]]>0,"Sim","Não") -> Não | Y14: =IF(Tabela4[[#This Row],[Não liberado para testes]]>0,"Sim","Não") -> Sim | Z14: =IF(Tabela4[[#This Row],[Status]]="Keyuser - Pendente",NETWORKDAYS(Tabela4[[#This Row],[Dt Inicial]],TODAY()),"") | AA14: =AND(Tabela4[[#This Row],[Status]]="Keyuser - Aguardando tarefa precedente",K13="Keyuser - Concluído ") -> FALSE
A15: ="OUT-"&IFERROR(MID(Tabela4[[#This Row],[Cenário]],SEARCH("(",Tabela4[[#This Row],[Cenário]])+1,SEARCH(")",Tabela4[[#This Row],[Cenário]])-SEARCH("(",Tabela4[[#This Row],[Cenário]])-1),"")&"_"&ROW() -> OUT-YDEV_15 | B15: Não | C15: Venda Etanol Hidratado D.E (YDEV) | D15: Realizar validação Obrigações Acessórias - TaxOne | E15: 6 | F15: Realizar validação Obrigações Acessórias - TaxOne | G15: Sergio Souza / Giovana Gonçalves | K15: Não liberado para testes | Q15: =COUNTIF(Tabela4[[#All],[Cenário]],Tabela4[[#This Row],[Cenário]]) -> 6 | R15: =COUNTIFS(Tabela4[[#All],[Cenário]],Tabela4[[#This Row],[Cenário]],Tabela4[[#All],[Status]],"Keyuser - Concluído ") -> 5 | S15: =IF(Tabela4[[#This Row],[Tarefas por Cenário]]-Tabela4[[#This Row],[Tarefas Concluídas]]>0,"Não","Sim") -> Não | T15: =COUNTIFS(Tabela4[[#All],[Cenário]],Tabela4[[#This Row],[Cenário]],Tabela4[[#All],[Status]],Tabela4[[#Headers],[Elo - Em correção ]]) -> 0 | U15: =COUNTIFS(Tabela4[[#All],[Cenário]],Tabela4[[#This Row],[Cenário]],Tabela4[[#All],[Status]],Tabela4[[#Headers],[Keyuser - Aguardando tarefa precedente]]) -> 0 | V15: =COUNTIFS(Tabela4[[#All],[Cenário]],Tabela4[[#This Row],[Cenário]],Tabela4[[#All],[Status]],Tabela4[[#Headers],[Não liberado para testes]]) -> 1 | W15: =IF(Tabela4[[#This Row],[Elo - Em correção ]]>0,"Sim","Não") -> Não | X15: =IF(Tabela4[[#This Row],[Keyuser - Aguardando tarefa precedente]]>0,"Sim","Não") -> Não | Y15: =IF(Tabela4[[#This Row],[Não liberado para testes]]>0,"Sim","Não") -> Sim | Z15: =IF(Tabela4[[#This Row],[Status]]="Keyuser - Pendente",NETWORKDAYS(Tabela4[[#This Row],[Dt Inicial]],TODAY()),"") | AA15: =AND(Tabela4[[#This Row],[Status]]="Keyuser - Aguardando tarefa precedente",K14="Keyuser - Concluído ") -> FALSE
A16: ="OUT-"&IFERROR(MID(Tabela4[[#This Row],[Cenário]],SEARCH("(",Tabela4[[#This Row],[Cenário]])+1,SEARCH(")",Tabela4[[#This Row],[Cenário]])-SEARCH("(",Tabela4[[#This Row],[Cenário]])-1),"")&"_"&ROW() -> OUT-YRET_16 | B16: Sim | C16: Venda Etanol Hidratado D.E (YRET) | D16: Criar ordem de venda | E16: 1 | F16: Criar ordem de venda | G16: Marcos Nunes | H16: 60668326 | K16: Keyuser - Concluído | L16: 45958 | N16: 45958 | Q16: =COUNTIF(Tabela4[[#All],[Cenário]],Tabela4[[#This Row],[Cenário]]) -> 6 | R16: =COUNTIFS(Tabela4[[#All],[Cenário]],Tabela4[[#This Row],[Cenário]],Tabela4[[#All],[Status]],"Keyuser - Concluído ") -> 5 | S16: =IF(Tabela4[[#This Row],[Tarefas por Cenário]]-Tabela4[[#This Row],[Tarefas Concluídas]]>0,"Não","Sim") -> Não | T16: =COUNTIFS(Tabela4[[#All],[Cenário]],Tabela4[[#This Row],[Cenário]],Tabela4[[#All],[Status]],Tabela4[[#Headers],[Elo - Em correção ]]) -> 0 | U16: =COUNTIFS(Tabela4[[#All],[Cenário]],Tabela4[[#This Row],[Cenário]],Tabela4[[#All],[Status]],Tabela4[[#Headers],[Keyuser - Aguardando tarefa precedente]]) -> 0 | V16: =COUNTIFS(Tabela4[[#All],[Cenário]],Tabela4[[#This Row],[Cenário]],Tabela4[[#All],[Status]],Tabela4[[#Headers],[Não liberado para testes]]) -> 1 | W16: =IF(Tabela4[[#This Row],[Elo - Em correção ]]>0,"Sim","Não") -> Não | X16: =IF(Tabela4[[#This Row],[Keyuser - Aguardando tarefa precedente]]>0,"Sim","Não") -> Não | Y16: =IF(Tabela4[[#This Row],[Não liberado para testes]]>0,"Sim","Não") -> Sim | Z16: =IF(Tabela4[[#This Row],[Status]]="Keyuser - Pendente",NETWORKDAYS(Tabela4[[#This Row],[Dt Inicial]],TODAY()),"") | AA16: =AND(Tabela4[[#This Row],[Status]]="Keyuser - Aguardando tarefa precedente",K15="Keyuser - Concluído ") -> FALSE
A17: ="OUT-"&IFERROR(MID(Tabela4[[#This Row],[Cenário]],SEARCH("(",Tabela4[[#This Row],[Cenário]])+1,SEARCH(")",Tabela4[[#This Row],[Cenário]])-SEARCH("(",Tabela4[[#This Row],[Cenário]])-1),"")&"_"&ROW() -> OUT-YRET_17 | B17: Sim | C17: Venda Etanol Hidratado D.E (YRET) | D17: Realizar validação tributária - Ordem de venda | E17: 2 | F17: Realizar validação tributária - Ordem de venda | G17: Livia Beserra | H17: 60668326 | K17: Keyuser - Concluído | L17: 45958 | N17: 45958 | Q17: =COUNTIF(Tabela4[[#All],[Cenário]],Tabela4[[#This Row],[Cenário]]) -> 6 | R17: =COUNTIFS(Tabela4[[#All],[Cenário]],Tabela4[[#This Row],[Cenário]],Tabela4[[#All],[Status]],"Keyuser - Concluído ") -> 5 | S17: =IF(Tabela4[[#This Row],[Tarefas por Cenário]]-Tabela4[[#This Row],[Tarefas Concluídas]]>0,"Não","Sim") -> Não | T17: =COUNTIFS(Tabela4[[#All],[Cenário]],Tabela4[[#This Row],[Cenário]],Tabela4[[#All],[Status]],Tabela4[[#Headers],[Elo - Em correção ]]) -> 0 | U17: =COUNTIFS(Tabela4[[#All],[Cenário]],Tabela4[[#This Row],[Cenário]],Tabela4[[#All],[Status]],Tabela4[[#Headers],[Keyuser - Aguardando tarefa precedente]]) -> 0 | V17: =COUNTIFS(Tabela4[[#All],[Cenário]],Tabela4[[#This Row],[Cenário]],Tabela4[[#All],[Status]],Tabela4[[#Headers],[Não liberado para testes]]) -> 1 | W17: =IF(Tabela4[[#This Row],[Elo - Em correção ]]>0,"Sim","Não") -> Não | X17: =IF(Tabela4[[#This Row],[Keyuser - Aguardando tarefa precedente]]>0,"Sim","Não") -> Não | Y17: =IF(Tabela4[[#This Row],[Não liberado para testes]]>0,"Sim","Não") -> Sim | Z17: =IF(Tabela4[[#This Row],[Status]]="Keyuser - Pendente",NETWORKDAYS(Tabela4[[#This Row],[Dt Inicial]],TODAY()),"") | AA17: =AND(Tabela4[[#This Row],[Status]]="Keyuser - Aguardando tarefa precedente",K16="Keyuser - Concluído ") -> FALSE
A18: ="OUT-"&IFERROR(MID(Tabela4[[#This Row],[Cenário]],SEARCH("(",Tabela4[[#This Row],[Cenário]])+1,SEARCH(")",Tabela4[[#This Row],[Cenário]])-SEARCH("(",Tabela4[[#This Row],[Cenário]])-1),"")&"_"&ROW() -> OUT-YRET_18 | B18: Sim | C18: Venda Etanol Hidratado D.E (YRET) | D18: Realizar faturamento | E18: 3 | F18: Realizar faturamento | G18: Marcos Nunes | H18: DocNum - 46482290 | K18: Keyuser - Concluído | L18: 45959 | N18: 45959 | O18: Nota nr 149732 | Q18: =COUNTIF(Tabela4[[#All],[Cenário]],Tabela4[[#This Row],[Cenário]]) -> 6 | R18: =COUNTIFS(Tabela4[[#All],[Cenário]],Tabela4[[#This Row],[Cenário]],Tabela4[[#All],[Status]],"Keyuser - Concluído ") -> 5 | S18: =IF(Tabela4[[#This Row],[Tarefas por Cenário]]-Tabela4[[#This Row],[Tarefas Concluídas]]>0,"Não","Sim") -> Não | T18: =COUNTIFS(Tabela4[[#All],[Cenário]],Tabela4[[#This Row],[Cenário]],Tabela4[[#All],[Status]],Tabela4[[#Headers],[Elo - Em correção ]]) -> 0 | U18: =COUNTIFS(Tabela4[[#All],[Cenário]],Tabela4[[#This Row],[Cenário]],Tabela4[[#All],[Status]],Tabela4[[#Headers],[Keyuser - Aguardando tarefa precedente]]) -> 0 | V18: =COUNTIFS(Tabela4[[#All],[Cenário]],Tabela4[[#This Row],[Cenário]],Tabela4[[#All],[Status]],Tabela4[[#Headers],[Não liberado para testes]]) -> 1 | W18: =IF(Tabela4[[#This Row],[Elo - Em correção ]]>0,"Sim","Não") -> Não | X18: =IF(Tabela4[[#This Row],[Keyuser - Aguardando tarefa precedente]]>0,"Sim","Não") -> Não | Y18: =IF(Tabela4[[#This Row],[Não liberado para testes]]>0,"Sim","Não") -> Sim | Z18: =IF(Tabela4[[#This Row],[Status]]="Keyuser - Pendente",NETWORKDAYS(Tabela4[[#This Row],[Dt Inicial]],TODAY()),"") | AA18: =AND(Tabela4[[#This Row],[Status]]="Keyuser - Aguardando tarefa precedente",K17="Keyuser - Concluído ") -> FALSE
A19: ="OUT-"&IFERROR(MID(Tabela4[[#This Row],[Cenário]],SEARCH("(",Tabela4[[#This Row],[Cenário]])+1,SEARCH(")",Tabela4[[#This Row],[Cenário]])-SEARCH("(",Tabela4[[#This Row],[Cenário]])-1),"")&"_"&ROW() -> OUT-YRET_19 | B19: Sim | C19: Venda Etanol Hidratado D.E (YRET) | D19: Realizar validação tributária - SAP, XML e DANFE | E19: 4 | F19: Realizar validação tributária - SAP (xml e DANFE) | G19: Sergio Souza / Giovana Gonçalves | H19: DocNum - 46482290 | K19: Keyuser - Concluído | L19: 45959 | N19: 45959 | Q19: =COUNTIF(Tabela4[[#All],[Cenário]],Tabela4[[#This Row],[Cenário]]) -> 6 | R19: =COUNTIFS(Tabela4[[#All],[Cenário]],Tabela4[[#This Row],[Cenário]],Tabela4[[#All],[Status]],"Keyuser - Concluído ") -> 5 | S19: =IF(Tabela4[[#This Row],[Tarefas por Cenário]]-Tabela4[[#This Row],[Tarefas Concluídas]]>0,"Não","Sim") -> Não | T19: =COUNTIFS(Tabela4[[#All],[Cenário]],Tabela4[[#This Row],[Cenário]],Tabela4[[#All],[Status]],Tabela4[[#Headers],[Elo - Em correção ]]) -> 0 | U19: =COUNTIFS(Tabela4[[#All],[Cenário]],Tabela4[[#This Row],[Cenário]],Tabela4[[#All],[Status]],Tabela4[[#Headers],[Keyuser - Aguardando tarefa precedente]]) -> 0 | V19: =COUNTIFS(Tabela4[[#All],[Cenário]],Tabela4[[#This Row],[Cenário]],Tabela4[[#All],[Status]],Tabela4[[#Headers],[Não liberado para testes]]) -> 1 | W19: =IF(Tabela4[[#This Row],[Elo - Em correção ]]>0,"Sim","Não") -> Não | X19: =IF(Tabela4[[#This Row],[Keyuser - Aguardando tarefa precedente]]>0,"Sim","Não") -> Não | Y19: =IF(Tabela4[[#This Row],[Não liberado para testes]]>0,"Sim","Não") -> Sim | Z19: =IF(Tabela4[[#This Row],[Status]]="Keyuser - Pendente",NETWORKDAYS(Tabela4[[#This Row],[Dt Inicial]],TODAY()),"") | AA19: =AND(Tabela4[[#This Row],[Status]]="Keyuser - Aguardando tarefa precedente",K18="Keyuser - Concluído ") -> FALSE
A20: ="OUT-"&IFERROR(MID(Tabela4[[#This Row],[Cenário]],SEARCH("(",Tabela4[[#This Row],[Cenário]])+1,SEARCH(")",Tabela4[[#This Row],[Cenário]])-SEARCH("(",Tabela4[[#This Row],[Cenário]])-1),"")&"_"&ROW() -> OUT-YRET_20 | B20: Sim | C20: Venda Etanol Hidratado D.E (YRET) | D20: Realizar validação contábil | E20: 5 | F20: Realizar validação contábil | G20: Naiara Toledo | H20: DocNum - 46482290 | K20: Keyuser - Concluído | L20: 45960 | N20: 45960 | Q20: =COUNTIF(Tabela4[[#All],[Cenário]],Tabela4[[#This Row],[Cenário]]) -> 6 | R20: =COUNTIFS(Tabela4[[#All],[Cenário]],Tabela4[[#This Row],[Cenário]],Tabela4[[#All],[Status]],"Keyuser - Concluído ") -> 5 | S20: =IF(Tabela4[[#This Row],[Tarefas por Cenário]]-Tabela4[[#This Row],[Tarefas Concluídas]]>0,"Não","Sim") -> Não | T20: =COUNTIFS(Tabela4[[#All],[Cenário]],Tabela4[[#This Row],[Cenário]],Tabela4[[#All],[Status]],Tabela4[[#Headers],[Elo - Em correção ]]) -> 0 | U20: =COUNTIFS(Tabela4[[#All],[Cenário]],Tabela4[[#This Row],[Cenário]],Tabela4[[#All],[Status]],Tabela4[[#Headers],[Keyuser - Aguardando tarefa precedente]]) -> 0 | V20: =COUNTIFS(Tabela4[[#All],[Cenário]],Tabela4[[#This Row],[Cenário]],Tabela4[[#All],[Status]],Tabela4[[#Headers],[Não liberado para testes]]) -> 1 | W20: =IF(Tabela4[[#This Row],[Elo - Em correção ]]>0,"Sim","Não") -> Não | X20: =IF(Tabela4[[#This Row],[Keyuser - Aguardando tarefa precedente]]>0,"Sim","Não") -> Não | Y20: =IF(Tabela4[[#This Row],[Não liberado para testes]]>0,"Sim","Não") -> Sim | Z20: =IF(Tabela4[[#This Row],[Status]]="Keyuser - Pendente",NETWORKDAYS(Tabela4[[#This Row],[Dt Inicial]],TODAY()),"") | AA20: =AND(Tabela4[[#This Row],[Status]]="Keyuser - Aguardando tarefa precedente",K19="Keyuser - Concluído ") -> FALSE
A21: ="OUT-"&IFERROR(MID(Tabela4[[#This Row],[Cenário]],SEARCH("(",Tabela4[[#This Row],[Cenário]])+1,SEARCH(")",Tabela4[[#This Row],[Cenário]])-SEARCH("(",Tabela4[[#This Row],[Cenário]])-1),"")&"_"&ROW() -> OUT-YRET_21 | B21: Não | C21: Venda Etanol Hidratado D.E (YRET) | D21: Realizar validação Obrigações Acessórias - TaxOne | E21: 6 | F21: Realizar validação Obrigações Acessórias - TaxOne | G21: Sergio Souza / Giovana Gonçalves | K21: Não liberado para testes | Q21: =COUNTIF(Tabela4[[#All],[Cenário]],Tabela4[[#This Row],[Cenário]]) -> 6 | R21: =COUNTIFS(Tabela4[[#All],[Cenário]],Tabela4[[#This Row],[Cenário]],Tabela4[[#All],[Status]],"Keyuser - Concluído ") -> 5 | S21: =IF(Tabela4[[#This Row],[Tarefas por Cenário]]-Tabela4[[#This Row],[Tarefas Concluídas]]>0,"Não","Sim") -> Não | T21: =COUNTIFS(Tabela4[[#All],[Cenário]],Tabela4[[#This Row],[Cenário]],Tabela4[[#All],[Status]],Tabela4[[#Headers],[Elo - Em correção ]]) -> 0 | U21: =COUNTIFS(Tabela4[[#All],[Cenário]],Tabela4[[#This Row],[Cenário]],Tabela4[[#All],[Status]],Tabela4[[#Headers],[Keyuser - Aguardando tarefa precedente]]) -> 0 | V21: =COUNTIFS(Tabela4[[#All],[Cenário]],Tabela4[[#This Row],[Cenário]],Tabela4[[#All],[Status]],Tabela4[[#Headers],[Não liberado para testes]]) -> 1 | W21: =IF(Tabela4[[#This Row],[Elo - Em correção ]]>0,"Sim","Não") -> Não | X21: =IF(Tabela4[[#This Row],[Keyuser - Aguardando tarefa precedente]]>0,"Sim","Não") -> Não | Y21: =IF(Tabela4[[#This Row],[Não liberado para testes]]>0,"Sim","Não") -> Sim | Z21: =IF(Tabela4[[#This Row],[Status]]="Keyuser - Pendente",NETWORKDAYS(Tabela4[[#This Row],[Dt Inicial]],TODAY()),"") | AA21: =AND(Tabela4[[#This Row],[Status]]="Keyuser - Aguardando tarefa precedente",K20="Keyuser - Concluído ") -> FALSE
A22: ="OUT-"&IFERROR(MID(Tabela4[[#This Row],[Cenário]],SEARCH("(",Tabela4[[#This Row],[Cenário]])+1,SEARCH(")",Tabela4[[#This Row],[Cenário]])-SEARCH("(",Tabela4[[#This Row],[Cenário]])-1),"")&"_"&ROW() -> OUT-Y002_22 | B22: Sim | C22: Venda Etanol Hidratado F.E (Y002) | D22: Criar ordem de venda | E22: 1 | F22: Criar ordem de venda | G22: Vania Esteves | H22: 15603629 | I22: BEP: 15608806 | J22: OK | K22: Keyuser - Concluído | L22: 45951 | N22: 45951 | Q22: =COUNTIF(Tabela4[[#All],[Cenário]],Tabela4[[#This Row],[Cenário]]) -> 8 | R22: =COUNTIFS(Tabela4[[#All],[Cenário]],Tabela4[[#This Row],[Cenário]],Tabela4[[#All],[Status]],"Keyuser - Concluído ") -> 7 | S22: =IF(Tabela4[[#This Row],[Tarefas por Cenário]]-Tabela4[[#This Row],[Tarefas Concluídas]]>0,"Não","Sim") -> Não | T22: =COUNTIFS(Tabela4[[#All],[Cenário]],Tabela4[[#This Row],[Cenário]],Tabela4[[#All],[Status]],Tabela4[[#Headers],[Elo - Em correção ]]) -> 0 | U22: =COUNTIFS(Tabela4[[#All],[Cenário]],Tabela4[[#This Row],[Cenário]],Tabela4[[#All],[Status]],Tabela4[[#Headers],[Keyuser - Aguardando tarefa precedente]]) -> 0 | V22: =COUNTIFS(Tabela4[[#All],[Cenário]],Tabela4[[#This Row],[Cenário]],Tabela4[[#All],[Status]],Tabela4[[#Headers],[Não liberado para testes]]) -> 1 | W22: =IF(Tabela4[[#This Row],[Elo - Em correção ]]>0,"Sim","Não") -> Não | X22: =IF(Tabela4[[#This Row],[Keyuser - Aguardando tarefa precedente]]>0,"Sim","Não") -> Não | Y22: =IF(Tabela4[[#This Row],[Não liberado para testes]]>0,"Sim","Não") -> Sim | Z22: =IF(Tabela4[[#This Row],[Status]]="Keyuser - Pendente",NETWORKDAYS(Tabela4[[#This Row],[Dt Inicial]],TODAY()),"") | AA22: =AND(Tabela4[[#This Row],[Status]]="Keyuser - Aguardando tarefa precedente",K21="Keyuser - Concluído ") -> FALSE
A23: ="OUT-"&IFERROR(MID(Tabela4[[#This Row],[Cenário]],SEARCH("(",Tabela4[[#This Row],[Cenário]])+1,SEARCH(")",Tabela4[[#This Row],[Cenário]])-SEARCH("(",Tabela4[[#This Row],[Cenário]])-1),"")&"_"&ROW() -> OUT-Y002_23 | B23: Sim | C23: Venda Etanol Hidratado F.E (Y002) | D23: Realizar validação tributária - Ordem de venda | E23: 2 | F23: Realizar validação tributária - Ordem de venda | G23: Livia Beserra | H23: 15603629 | I23: BEP: 15608806 | J23: OK | K23: Keyuser - Concluído | L23: 45951 | N23: 45951 | Q23: =COUNTIF(Tabela4[[#All],[Cenário]],Tabela4[[#This Row],[Cenário]]) -> 8 | R23: =COUNTIFS(Tabela4[[#All],[Cenário]],Tabela4[[#This Row],[Cenário]],Tabela4[[#All],[Status]],"Keyuser - Concluído ") -> 7 | S23: =IF(Tabela4[[#This Row],[Tarefas por Cenário]]-Tabela4[[#This Row],[Tarefas Concluídas]]>0,"Não","Sim") -> Não | T23: =COUNTIFS(Tabela4[[#All],[Cenário]],Tabela4[[#This Row],[Cenário]],Tabela4[[#All],[Status]],Tabela4[[#Headers],[Elo - Em correção ]]) -> 0 | U23: =COUNTIFS(Tabela4[[#All],[Cenário]],Tabela4[[#This Row],[Cenário]],Tabela4[[#All],[Status]],Tabela4[[#Headers],[Keyuser - Aguardando tarefa precedente]]) -> 0 | V23: =COUNTIFS(Tabela4[[#All],[Cenário]],Tabela4[[#This Row],[Cenário]],Tabela4[[#All],[Status]],Tabela4[[#Headers],[Não liberado para testes]]) -> 1 | W23: =IF(Tabela4[[#This Row],[Elo - Em correção ]]>0,"Sim","Não") -> Não | X23: =IF(Tabela4[[#This Row],[Keyuser - Aguardando tarefa precedente]]>0,"Sim","Não") -> Não | Y23: =IF(Tabela4[[#This Row],[Não liberado para testes]]>0,"Sim","Não") -> Sim | Z23: =IF(Tabela4[[#This Row],[Status]]="Keyuser - Pendente",NETWORKDAYS(Tabela4[[#This Row],[Dt Inicial]],TODAY()),"") | AA23: =AND(Tabela4[[#This Row],[Status]]="Keyuser - Aguardando tarefa precedente",K22="Keyuser - Concluído ") -> FALSE
A24: ="OUT-"&IFERROR(MID(Tabela4[[#This Row],[Cenário]],SEARCH("(",Tabela4[[#This Row],[Cenário]])+1,SEARCH(")",Tabela4[[#This Row],[Cenário]])-SEARCH("(",Tabela4[[#This Row],[Cenário]])-1),"")&"_"&ROW() -> OUT-Y002_24 | B24: Sim | C24: Venda Etanol Hidratado F.E (Y002) | D24: Liberar ordem de venda | E24: 3 | F24: Liberar ordem de venda | G24: Patrick Vianna / Aline Russo | H24: 15603629 | I24: BEP: 15608806 | J24: OK | K24: Keyuser - Concluído | L24: 45951 | N24: 45951 | Q24: =COUNTIF(Tabela4[[#All],[Cenário]],Tabela4[[#This Row],[Cenário]]) -> 8 | R24: =COUNTIFS(Tabela4[[#All],[Cenário]],Tabela4[[#This Row],[Cenário]],Tabela4[[#All],[Status]],"Keyuser - Concluído ") -> 7 | S24: =IF(Tabela4[[#This Row],[Tarefas por Cenário]]-Tabela4[[#This Row],[Tarefas Concluídas]]>0,"Não","Sim") -> Não | T24: =COUNTIFS(Tabela4[[#All],[Cenário]],Tabela4[[#This Row],[Cenário]],Tabela4[[#All],[Status]],Tabela4[[#Headers],[Elo - Em correção ]]) -> 0 | U24: =COUNTIFS(Tabela4[[#All],[Cenário]],Tabela4[[#This Row],[Cenário]],Tabela4[[#All],[Status]],Tabela4[[#Headers],[Keyuser - Aguardando tarefa precedente]]) -> 0 | V24: =COUNTIFS(Tabela4[[#All],[Cenário]],Tabela4[[#This Row],[Cenário]],Tabela4[[#All],[Status]],Tabela4[[#Headers],[Não liberado para testes]]) -> 1 | W24: =IF(Tabela4[[#This Row],[Elo - Em correção ]]>0,"Sim","Não") -> Não | X24: =IF(Tabela4[[#This Row],[Keyuser - Aguardando tarefa precedente]]>0,"Sim","Não") -> Não | Y24: =IF(Tabela4[[#This Row],[Não liberado para testes]]>0,"Sim","Não") -> Sim | Z24: =IF(Tabela4[[#This Row],[Status]]="Keyuser - Pendente",NETWORKDAYS(Tabela4[[#This Row],[Dt Inicial]],TODAY()),"") | AA24: =AND(Tabela4[[#This Row],[Status]]="Keyuser - Aguardando tarefa precedente",K23="Keyuser - Concluído ") -> FALSE
A25: ="OUT-"&IFERROR(MID(Tabela4[[#This Row],[Cenário]],SEARCH("(",Tabela4[[#This Row],[Cenário]])+1,SEARCH(")",Tabela4[[#This Row],[Cenário]])-SEARCH("(",Tabela4[[#This Row],[Cenário]])-1),"")&"_"&ROW() -> OUT-Y002_25 | B25: Sim | C25: Venda Etanol Hidratado F.E (Y002) | D25: Realizar faturamento | E25: 4 | F25: Realizar faturamento | G25: Francisco Netto | H25: DocNum - 46482219 | K25: Keyuser - Concluído | L25: 45951 | N25: 45951 | Q25: =COUNTIF(Tabela4[[#All],[Cenário]],Tabela4[[#This Row],[Cenário]]) -> 8 | R25: =COUNTIFS(Tabela4[[#All],[Cenário]],Tabela4[[#This Row],[Cenário]],Tabela4[[#All],[Status]],"Keyuser - Concluído ") -> 7 | S25: =IF(Tabela4[[#This Row],[Tarefas por Cenário]]-Tabela4[[#This Row],[Tarefas Concluídas]]>0,"Não","Sim") -> Não | T25: =COUNTIFS(Tabela4[[#All],[Cenário]],Tabela4[[#This Row],[Cenário]],Tabela4[[#All],[Status]],Tabela4[[#Headers],[Elo - Em correção ]]) -> 0 | U25: =COUNTIFS(Tabela4[[#All],[Cenário]],Tabela4[[#This Row],[Cenário]],Tabela4[[#All],[Status]],Tabela4[[#Headers],[Keyuser - Aguardando tarefa precedente]]) -> 0 | V25: =COUNTIFS(Tabela4[[#All],[Cenário]],Tabela4[[#This Row],[Cenário]],Tabela4[[#All],[Status]],Tabela4[[#Headers],[Não liberado para testes]]) -> 1 | W25: =IF(Tabela4[[#This Row],[Elo - Em correção ]]>0,"Sim","Não") -> Não | X25: =IF(Tabela4[[#This Row],[Keyuser - Aguardando tarefa precedente]]>0,"Sim","Não") -> Não | Y25: =IF(Tabela4[[#This Row],[Não liberado para testes]]>0,"Sim","Não") -> Sim | Z25: =IF(Tabela4[[#This Row],[Status]]="Keyuser - Pendente",NETWORKDAYS(Tabela4[[#This Row],[Dt Inicial]],TODAY()),"") | AA25: =AND(Tabela4[[#This Row],[Status]]="Keyuser - Aguardando tarefa precedente",K24="Keyuser - Concluído ") -> FALSE
A26: ="OUT-"&IFERROR(MID(Tabela4[[#This Row],[Cenário]],SEARCH("(",Tabela4[[#This Row],[Cenário]])+1,SEARCH(")",Tabela4[[#This Row],[Cenário]])-SEARCH("(",Tabela4[[#This Row],[Cenário]])-1),"")&"_"&ROW() -> OUT-Y002_26 | B26: Sim | C26: Venda Etanol Hidratado F.E (Y002) | D26: Realizar validação tributária - SAP, XML e DANFE | E26: 5 | F26: Realizar validação tributária - SAP (xml e DANFE) | G26: Sergio Souza / Giovana Gonçalves | H26: DocNum - 46482219 | K26: Keyuser - Concluído | L26: 45952 | N26: 45952 | Q26: =COUNTIF(Tabela4[[#All],[Cenário]],Tabela4[[#This Row],[Cenário]]) -> 8 | R26: =COUNTIFS(Tabela4[[#All],[Cenário]],Tabela4[[#This Row],[Cenário]],Tabela4[[#All],[Status]],"Keyuser - Concluído ") -> 7 | S26: =IF(Tabela4[[#This Row],[Tarefas por Cenário]]-Tabela4[[#This Row],[Tarefas Concluídas]]>0,"Não","Sim") -> Não | T26: =COUNTIFS(Tabela4[[#All],[Cenário]],Tabela4[[#This Row],[Cenário]],Tabela4[[#All],[Status]],Tabela4[[#Headers],[Elo - Em correção ]]) -> 0 | U26: =COUNTIFS(Tabela4[[#All],[Cenário]],Tabela4[[#This Row],[Cenário]],Tabela4[[#All],[Status]],Tabela4[[#Headers],[Keyuser - Aguardando tarefa precedente]]) -> 0 | V26: =COUNTIFS(Tabela4[[#All],[Cenário]],Tabela4[[#This Row],[Cenário]],Tabela4[[#All],[Status]],Tabela4[[#Headers],[Não liberado para testes]]) -> 1 | W26: =IF(Tabela4[[#This Row],[Elo - Em correção ]]>0,"Sim","Não") -> Não | X26: =IF(Tabela4[[#This Row],[Keyuser - Aguardando tarefa precedente]]>0,"Sim","Não") -> Não | Y26: =IF(Tabela4[[#This Row],[Não liberado para testes]]>0,"Sim","Não") -> Sim | Z26: =IF(Tabela4[[#This Row],[Status]]="Keyuser - Pendente",NETWORKDAYS(Tabela4[[#This Row],[Dt Inicial]],TODAY()),"") | AA26: =AND(Tabela4[[#This Row],[Status]]="Keyuser - Aguardando tarefa precedente",K25="Keyuser - Concluído ") -> FALSE
A27: ="OUT-"&IFERROR(MID(Tabela4[[#This Row],[Cenário]],SEARCH("(",Tabela4[[#This Row],[Cenário]])+1,SEARCH(")",Tabela4[[#This Row],[Cenário]])-SEARCH("(",Tabela4[[#This Row],[Cenário]])-1),"")&"_"&ROW() -> OUT-Y002_27 | B27: Sim | C27: Venda Etanol Hidratado F.E (Y002) | D27: Realizar validação contábil | E27: 6 | F27: Realizar validação contábil | G27: Naiara Toledo | H27: Doc Num - 46482219 | K27: Keyuser - Concluído | L27: 45952 | N27: 45952 | Q27: =COUNTIF(Tabela4[[#All],[Cenário]],Tabela4[[#This Row],[Cenário]]) -> 8 | R27: =COUNTIFS(Tabela4[[#All],[Cenário]],Tabela4[[#This Row],[Cenário]],Tabela4[[#All],[Status]],"Keyuser - Concluído ") -> 7 | S27: =IF(Tabela4[[#This Row],[Tarefas por Cenário]]-Tabela4[[#This Row],[Tarefas Concluídas]]>0,"Não","Sim") -> Não | T27: =COUNTIFS(Tabela4[[#All],[Cenário]],Tabela4[[#This Row],[Cenário]],Tabela4[[#All],[Status]],Tabela4[[#Headers],[Elo - Em correção ]]) -> 0 | U27: =COUNTIFS(Tabela4[[#All],[Cenário]],Tabela4[[#This Row],[Cenário]],Tabela4[[#All],[Status]],Tabela4[[#Headers],[Keyuser - Aguardando tarefa precedente]]) -> 0 | V27: =COUNTIFS(Tabela4[[#All],[Cenário]],Tabela4[[#This Row],[Cenário]],Tabela4[[#All],[Status]],Tabela4[[#Headers],[Não liberado para testes]]) -> 1 | W27: =IF(Tabela4[[#This Row],[Elo - Em correção ]]>0,"Sim","Não") -> Não | X27: =IF(Tabela4[[#This Row],[Keyuser - Aguardando tarefa precedente]]>0,"Sim","Não") -> Não | Y27: =IF(Tabela4[[#This Row],[Não liberado para testes]]>0,"Sim","Não") -> Sim | Z27: =IF(Tabela4[[#This Row],[Status]]="Keyuser - Pendente",NETWORKDAYS(Tabela4[[#This Row],[Dt Inicial]],TODAY()),"") | AA27: =AND(Tabela4[[#This Row],[Status]]="Keyuser - Aguardando tarefa precedente",K26="Keyuser - Concluído ") -> FALSE
A28: ="OUT-"&IFERROR(MID(Tabela4[[#This Row],[Cenário]],SEARCH("(",Tabela4[[#This Row],[Cenário]])+1,SEARCH(")",Tabela4[[#This Row],[Cenário]])-SEARCH("(",Tabela4[[#This Row],[Cenário]])-1),"")&"_"&ROW() -> OUT-Y002_28 | B28: Não | C28: Venda Etanol Hidratado F.E (Y002) | D28: Realizar validação Obrigações Acessórias - TaxOne | E28: 7 | F28: Realizar validação Obrigações Acessórias - TaxOne | G28: Sergio Souza / Giovana Gonçalves | K28: Não liberado para testes | Q28: =COUNTIF(Tabela4[[#All],[Cenário]],Tabela4[[#This Row],[Cenário]]) -> 8 | R28: =COUNTIFS(Tabela4[[#All],[Cenário]],Tabela4[[#This Row],[Cenário]],Tabela4[[#All],[Status]],"Keyuser - Concluído ") -> 7 | S28: =IF(Tabela4[[#This Row],[Tarefas por Cenário]]-Tabela4[[#This Row],[Tarefas Concluídas]]>0,"Não","Sim") -> Não | T28: =COUNTIFS(Tabela4[[#All],[Cenário]],Tabela4[[#This Row],[Cenário]],Tabela4[[#All],[Status]],Tabela4[[#Headers],[Elo - Em correção ]]) -> 0 | U28: =COUNTIFS(Tabela4[[#All],[Cenário]],Tabela4[[#This Row],[Cenário]],Tabela4[[#All],[Status]],Tabela4[[#Headers],[Keyuser - Aguardando tarefa precedente]]) -> 0 | V28: =COUNTIFS(Tabela4[[#All],[Cenário]],Tabela4[[#This Row],[Cenário]],Tabela4[[#All],[Status]],Tabela4[[#Headers],[Não liberado para testes]]) -> 1 | W28: =IF(Tabela4[[#This Row],[Elo - Em correção ]]>0,"Sim","Não") -> Não | X28: =IF(Tabela4[[#This Row],[Keyuser - Aguardando tarefa precedente]]>0,"Sim","Não") -> Não | Y28: =IF(Tabela4[[#This Row],[Não liberado para testes]]>0,"Sim","Não") -> Sim | Z28: =IF(Tabela4[[#This Row],[Status]]="Keyuser - Pendente",NETWORKDAYS(Tabela4[[#This Row],[Dt Inicial]],TODAY()),"") | AA28: =AND(Tabela4[[#This Row],[Status]]="Keyuser - Aguardando tarefa precedente",K27="Keyuser - Concluído ") -> FALSE
A29: ="OUT-"&IFERROR(MID(Tabela4[[#This Row],[Cenário]],SEARCH("(",Tabela4[[#This Row],[Cenário]])+1,SEARCH(")",Tabela4[[#This Row],[Cenário]])-SEARCH("(",Tabela4[[#This Row],[Cenário]])-1),"")&"_"&ROW() -> OUT-Y002_29 | B29: Sim | C29: Venda Etanol Hidratado F.E (Y002) | D29: Realizar validação Títulos Financeiros | E29: 8 | F29: Realizar validação Títulos Financeiros | G29: Patrick Vianna / Aline Russo | H29: 15603629 | I29: BEP: 15608806 | J29: OK | K29: Keyuser - Concluído | L29: 45952 | N29: 45952 | Q29: =COUNTIF(Tabela4[[#All],[Cenário]],Tabela4[[#This Row],[Cenário]]) -> 8 | R29: =COUNTIFS(Tabela4[[#All],[Cenário]],Tabela4[[#This Row],[Cenário]],Tabela4[[#All],[Status]],"Keyuser - Concluído ") -> 7 | S29: =IF(Tabela4[[#This Row],[Tarefas por Cenário]]-Tabela4[[#This Row],[Tarefas Concluídas]]>0,"Não","Sim") -> Não | T29: =COUNTIFS(Tabela4[[#All],[Cenário]],Tabela4[[#This Row],[Cenário]],Tabela4[[#All],[Status]],Tabela4[[#Headers],[Elo - Em correção ]]) -> 0 | U29: =COUNTIFS(Tabela4[[#All],[Cenário]],Tabela4[[#This Row],[Cenário]],Tabela4[[#All],[Status]],Tabela4[[#Headers],[Keyuser - Aguardando tarefa precedente]]) -> 0 | V29: =COUNTIFS(Tabela4[[#All],[Cenário]],Tabela4[[#This Row],[Cenário]],Tabela4[[#All],[Status]],Tabela4[[#Headers],[Não liberado para testes]]) -> 1 | W29: =IF(Tabela4[[#This Row],[Elo - Em correção ]]>0,"Sim","Não") -> Não | X29: =IF(Tabela4[[#This Row],[Keyuser - Aguardando tarefa precedente]]>0,"Sim","Não") -> Não | Y29: =IF(Tabela4[[#This Row],[Não liberado para testes]]>0,"Sim","Não") -> Sim | Z29: =IF(Tabela4[[#This Row],[Status]]="Keyuser - Pendente",NETWORKDAYS(Tabela4[[#This Row],[Dt Inicial]],TODAY()),"") | AA29: =AND(Tabela4[[#This Row],[Status]]="Keyuser - Aguardando tarefa precedente",K28="Keyuser - Concluído ") -> FALSE
A30: ="OUT-"&IFERROR(MID(Tabela4[[#This Row],[Cenário]],SEARCH("(",Tabela4[[#This Row],[Cenário]])+1,SEARCH(")",Tabela4[[#This Row],[Cenário]])-SEARCH("(",Tabela4[[#This Row],[Cenário]])-1),"")&"_"&ROW() -> OUT-YDEV_30 | B30: Sim | C30: Venda Etanol Hidratado F.E (YDEV) | D30: Criar ordem de venda | E30: 1 | F30: Criar ordem de venda | G30: Marcos Nunes | H30: 60668330 | K30: Keyuser - Concluído | L30: 45958 | N30: 45958 | Q30: =COUNTIF(Tabela4[[#All],[Cenário]],Tabela4[[#This Row],[Cenário]]) -> 6 | R30: =COUNTIFS(Tabela4[[#All],[Cenário]],Tabela4[[#This Row],[Cenário]],Tabela4[[#All],[Status]],"Keyuser - Concluído ") -> 5 | S30: =IF(Tabela4[[#This Row],[Tarefas por Cenário]]-Tabela4[[#This Row],[Tarefas Concluídas]]>0,"Não","Sim") -> Não | T30: =COUNTIFS(Tabela4[[#All],[Cenário]],Tabela4[[#This Row],[Cenário]],Tabela4[[#All],[Status]],Tabela4[[#Headers],[Elo - Em correção ]]) -> 0 | U30: =COUNTIFS(Tabela4[[#All],[Cenário]],Tabela4[[#This Row],[Cenário]],Tabela4[[#All],[Status]],Tabela4[[#Headers],[Keyuser - Aguardando tarefa precedente]]) -> 0 | V30: =COUNTIFS(Tabela4[[#All],[Cenário]],Tabela4[[#This Row],[Cenário]],Tabela4[[#All],[Status]],Tabela4[[#Headers],[Não liberado para testes]]) -> 1 | W30: =IF(Tabela4[[#This Row],[Elo - Em correção ]]>0,"Sim","Não") -> Não | X30: =IF(Tabela4[[#This Row],[Keyuser - Aguardando tarefa precedente]]>0,"Sim","Não") -> Não | Y30: =IF(Tabela4[[#This Row],[Não liberado para testes]]>0,"Sim","Não") -> Sim | Z30: =IF(Tabela4[[#This Row],[Status]]="Keyuser - Pendente",NETWORKDAYS(Tabela4[[#This Row],[Dt Inicial]],TODAY()),"") | AA30: =AND(Tabela4[[#This Row],[Status]]="Keyuser - Aguardando tarefa precedente",K29="Keyuser - Concluído ") -> FALSE
A31: ="OUT-"&IFERROR(MID(Tabela4[[#This Row],[Cenário]],SEARCH("(",Tabela4[[#This Row],[Cenário]])+1,SEARCH(")",Tabela4[[#This Row],[Cenário]])-SEARCH("(",Tabela4[[#This Row],[Cenário]])-1),"")&"_"&ROW() -> OUT-YDEV_31 | B31: Sim | C31: Venda Etanol Hidratado F.E (YDEV) | D31: Realizar validação tributária - Ordem de venda | E31: 2 | F31: Realizar validação tributária - Ordem de venda | G31: Livia Beserra | H31: 60668330 | K31: Keyuser - Concluído | L31: 45958 | N31: 45958 | Q31: =COUNTIF(Tabela4[[#All],[Cenário]],Tabela4[[#This Row],[Cenário]]) -> 6 | R31: =COUNTIFS(Tabela4[[#All],[Cenário]],Tabela4[[#This Row],[Cenário]],Tabela4[[#All],[Status]],"Keyuser - Concluído ") -> 5 | S31: =IF(Tabela4[[#This Row],[Tarefas por Cenário]]-Tabela4[[#This Row],[Tarefas Concluídas]]>0,"Não","Sim") -> Não | T31: =COUNTIFS(Tabela4[[#All],[Cenário]],Tabela4[[#This Row],[Cenário]],Tabela4[[#All],[Status]],Tabela4[[#Headers],[Elo - Em correção ]]) -> 0 | U31: =COUNTIFS(Tabela4[[#All],[Cenário]],Tabela4[[#This Row],[Cenário]],Tabela4[[#All],[Status]],Tabela4[[#Headers],[Keyuser - Aguardando tarefa precedente]]) -> 0 | V31: =COUNTIFS(Tabela4[[#All],[Cenário]],Tabela4[[#This Row],[Cenário]],Tabela4[[#All],[Status]],Tabela4[[#Headers],[Não liberado para testes]]) -> 1 | W31: =IF(Tabela4[[#This Row],[Elo - Em correção ]]>0,"Sim","Não") -> Não | X31: =IF(Tabela4[[#This Row],[Keyuser - Aguardando tarefa precedente]]>0,"Sim","Não") -> Não | Y31: =IF(Tabela4[[#This Row],[Não liberado para testes]]>0,"Sim","Não") -> Sim | Z31: =IF(Tabela4[[#This Row],[Status]]="Keyuser - Pendente",NETWORKDAYS(Tabela4[[#This Row],[Dt Inicial]],TODAY()),"") | AA31: =AND(Tabela4[[#This Row],[Status]]="Keyuser - Aguardando tarefa precedente",K30="Keyuser - Concluído ") -> FALSE
A32: ="OUT-"&IFERROR(MID(Tabela4[[#This Row],[Cenário]],SEARCH("(",Tabela4[[#This Row],[Cenário]])+1,SEARCH(")",Tabela4[[#This Row],[Cenário]])-SEARCH("(",Tabela4[[#This Row],[Cenário]])-1),"")&"_"&ROW() -> OUT-YDEV_32 | B32: Sim | C32: Venda Etanol Hidratado F.E (YDEV) | D32: Realizar faturamento | E32: 3 | F32: Realizar faturamento | G32: Marcos Nunes | H32: DocNum - 46482285 | K32: Keyuser - Concluído | L32: 45959 | N32: 45959 | O32: Nota nr 18089 | Q32: =COUNTIF(Tabela4[[#All],[Cenário]],Tabela4[[#This Row],[Cenário]]) -> 6 | R32: =COUNTIFS(Tabela4[[#All],[Cenário]],Tabela4[[#This Row],[Cenário]],Tabela4[[#All],[Status]],"Keyuser - Concluído ") -> 5 | S32: =IF(Tabela4[[#This Row],[Tarefas por Cenário]]-Tabela4[[#This Row],[Tarefas Concluídas]]>0,"Não","Sim") -> Não | T32: =COUNTIFS(Tabela4[[#All],[Cenário]],Tabela4[[#This Row],[Cenário]],Tabela4[[#All],[Status]],Tabela4[[#Headers],[Elo - Em correção ]]) -> 0 | U32: =COUNTIFS(Tabela4[[#All],[Cenário]],Tabela4[[#This Row],[Cenário]],Tabela4[[#All],[Status]],Tabela4[[#Headers],[Keyuser - Aguardando tarefa precedente]]) -> 0 | V32: =COUNTIFS(Tabela4[[#All],[Cenário]],Tabela4[[#This Row],[Cenário]],Tabela4[[#All],[Status]],Tabela4[[#Headers],[Não liberado para testes]]) -> 1 | W32: =IF(Tabela4[[#This Row],[Elo - Em correção ]]>0,"Sim","Não") -> Não | X32: =IF(Tabela4[[#This Row],[Keyuser - Aguardando tarefa precedente]]>0,"Sim","Não") -> Não | Y32: =IF(Tabela4[[#This Row],[Não liberado para testes]]>0,"Sim","Não") -> Sim | Z32: =IF(Tabela4[[#This Row],[Status]]="Keyuser - Pendente",NETWORKDAYS(Tabela4[[#This Row],[Dt Inicial]],TODAY()),"") | AA32: =AND(Tabela4[[#This Row],[Status]]="Keyuser - Aguardando tarefa precedente",K31="Keyuser - Concluído ") -> FALSE
A33: ="OUT-"&IFERROR(MID(Tabela4[[#This Row],[Cenário]],SEARCH("(",Tabela4[[#This Row],[Cenário]])+1,SEARCH(")",Tabela4[[#This Row],[Cenário]])-SEARCH("(",Tabela4[[#This Row],[Cenário]])-1),"")&"_"&ROW() -> OUT-YDEV_33 | B33: Sim | C33: Venda Etanol Hidratado F.E (YDEV) | D33: Realizar validação tributária - SAP, XML e DANFE | E33: 4 | F33: Realizar validação tributária - SAP (xml e DANFE) | G33: Sergio Souza / Giovana Gonçalves | H33: DocNum - 46482285 | K33: Keyuser - Concluído | L33: 45959 | N33: 45959 | Q33: =COUNTIF(Tabela4[[#All],[Cenário]],Tabela4[[#This Row],[Cenário]]) -> 6 | R33: =COUNTIFS(Tabela4[[#All],[Cenário]],Tabela4[[#This Row],[Cenário]],Tabela4[[#All],[Status]],"Keyuser - Concluído ") -> 5 | S33: =IF(Tabela4[[#This Row],[Tarefas por Cenário]]-Tabela4[[#This Row],[Tarefas Concluídas]]>0,"Não","Sim") -> Não | T33: =COUNTIFS(Tabela4[[#All],[Cenário]],Tabela4[[#This Row],[Cenário]],Tabela4[[#All],[Status]],Tabela4[[#Headers],[Elo - Em correção ]]) -> 0 | U33: =COUNTIFS(Tabela4[[#All],[Cenário]],Tabela4[[#This Row],[Cenário]],Tabela4[[#All],[Status]],Tabela4[[#Headers],[Keyuser - Aguardando tarefa precedente]]) -> 0 | V33: =COUNTIFS(Tabela4[[#All],[Cenário]],Tabela4[[#This Row],[Cenário]],Tabela4[[#All],[Status]],Tabela4[[#Headers],[Não liberado para testes]]) -> 1 | W33: =IF(Tabela4[[#This Row],[Elo - Em correção ]]>0,"Sim","Não") -> Não | X33: =IF(Tabela4[[#This Row],[Keyuser - Aguardando tarefa precedente]]>0,"Sim","Não") -> Não | Y33: =IF(Tabela4[[#This Row],[Não liberado para testes]]>0,"Sim","Não") -> Sim | Z33: =IF(Tabela4[[#This Row],[Status]]="Keyuser - Pendente",NETWORKDAYS(Tabela4[[#This Row],[Dt Inicial]],TODAY()),"") | AA33: =AND(Tabela4[[#This Row],[Status]]="Keyuser - Aguardando tarefa precedente",K32="Keyuser - Concluído ") -> FALSE
A34: ="OUT-"&IFERROR(MID(Tabela4[[#This Row],[Cenário]],SEARCH("(",Tabela4[[#This Row],[Cenário]])+1,SEARCH(")",Tabela4[[#This Row],[Cenário]])-SEARCH("(",Tabela4[[#This Row],[Cenário]])-1),"")&"_"&ROW() -> OUT-YDEV_34 | B34: Sim | C34: Venda Etanol Hidratado F.E (YDEV) | D34: Realizar validação contábil | E34: 5 | F34: Realizar validação contábil | G34: Naiara Toledo | H34: DocNum - 46482285 | K34: Keyuser - Concluído | L34: 45960 | N34: 45960 | Q34: =COUNTIF(Tabela4[[#All],[Cenário]],Tabela4[[#This Row],[Cenário]]) -> 6 | R34: =COUNTIFS(Tabela4[[#All],[Cenário]],Tabela4[[#This Row],[Cenário]],Tabela4[[#All],[Status]],"Keyuser - Concluído ") -> 5 | S34: =IF(Tabela4[[#This Row],[Tarefas por Cenário]]-Tabela4[[#This Row],[Tarefas Concluídas]]>0,"Não","Sim") -> Não | T34: =COUNTIFS(Tabela4[[#All],[Cenário]],Tabela4[[#This Row],[Cenário]],Tabela4[[#All],[Status]],Tabela4[[#Headers],[Elo - Em correção ]]) -> 0 | U34: =COUNTIFS(Tabela4[[#All],[Cenário]],Tabela4[[#This Row],[Cenário]],Tabela4[[#All],[Status]],Tabela4[[#Headers],[Keyuser - Aguardando tarefa precedente]]) -> 0 | V34: =COUNTIFS(Tabela4[[#All],[Cenário]],Tabela4[[#This Row],[Cenário]],Tabela4[[#All],[Status]],Tabela4[[#Headers],[Não liberado para testes]]) -> 1 | W34: =IF(Tabela4[[#This Row],[Elo - Em correção ]]>0,"Sim","Não") -> Não | X34: =IF(Tabela4[[#This Row],[Keyuser - Aguardando tarefa precedente]]>0,"Sim","Não") -> Não | Y34: =IF(Tabela4[[#This Row],[Não liberado para testes]]>0,"Sim","Não") -> Sim | Z34: =IF(Tabela4[[#This Row],[Status]]="Keyuser - Pendente",NETWORKDAYS(Tabela4[[#This Row],[Dt Inicial]],TODAY()),"") | AA34: =AND(Tabela4[[#This Row],[Status]]="Keyuser - Aguardando tarefa precedente",K33="Keyuser - Concluído ") -> FALSE
A35: ="OUT-"&IFERROR(MID(Tabela4[[#This Row],[Cenário]],SEARCH("(",Tabela4[[#This Row],[Cenário]])+1,SEARCH(")",Tabela4[[#This Row],[Cenário]])-SEARCH("(",Tabela4[[#This Row],[Cenário]])-1),"")&"_"&ROW() -> OUT-YDEV_35 | B35: Não | C35: Venda Etanol Hidratado F.E (YDEV) | D35: Realizar validação Obrigações Acessórias - TaxOne | E35: 6 | F35: Realizar validação Obrigações Acessórias - TaxOne | G35: Sergio Souza / Giovana Gonçalves | K35: Não liberado para testes | Q35: =COUNTIF(Tabela4[[#All],[Cenário]],Tabela4[[#This Row],[Cenário]]) -> 6 | R35: =COUNTIFS(Tabela4[[#All],[Cenário]],Tabela4[[#This Row],[Cenário]],Tabela4[[#All],[Status]],"Keyuser - Concluído ") -> 5 | S35: =IF(Tabela4[[#This Row],[Tarefas por Cenário]]-Tabela4[[#This Row],[Tarefas Concluídas]]>0,"Não","Sim") -> Não | T35: =COUNTIFS(Tabela4[[#All],[Cenário]],Tabela4[[#This Row],[Cenário]],Tabela4[[#All],[Status]],Tabela4[[#Headers],[Elo - Em correção ]]) -> 0 | U35: =COUNTIFS(Tabela4[[#All],[Cenário]],Tabela4[[#This Row],[Cenário]],Tabela4[[#All],[Status]],Tabela4[[#Headers],[Keyuser - Aguardando tarefa precedente]]) -> 0 | V35: =COUNTIFS(Tabela4[[#All],[Cenário]],Tabela4[[#This Row],[Cenário]],Tabela4[[#All],[Status]],Tabela4[[#Headers],[Não liberado para testes]]) -> 1 | W35: =IF(Tabela4[[#This Row],[Elo - Em correção ]]>0,"Sim","Não") -> Não | X35: =IF(Tabela4[[#This Row],[Keyuser - Aguardando tarefa precedente]]>0,"Sim","Não") -> Não | Y35: =IF(Tabela4[[#This Row],[Não liberado para testes]]>0,"Sim","Não") -> Sim | Z35: =IF(Tabela4[[#This Row],[Status]]="Keyuser - Pendente",NETWORKDAYS(Tabela4[[#This Row],[Dt Inicial]],TODAY()),"") | AA35: =AND(Tabela4[[#This Row],[Status]]="Keyuser - Aguardando tarefa precedente",K34="Keyuser - Concluído ") -> FALSE
A36: ="OUT-"&IFERROR(MID(Tabela4[[#This Row],[Cenário]],SEARCH("(",Tabela4[[#This Row],[Cenário]])+1,SEARCH(")",Tabela4[[#This Row],[Cenário]])-SEARCH("(",Tabela4[[#This Row],[Cenário]])-1),"")&"_"&ROW() -> OUT-YRET_36 | B36: Sim | C36: Venda Etanol Hidratado F.E (YRET) | D36: Criar ordem de venda | E36: 1 | F36: Criar ordem de venda | G36: Marcos Nunes | H36: 60668337 | K36: Keyuser - Concluído | L36: 45958 | N36: 45958 | Q36: =COUNTIF(Tabela4[[#All],[Cenário]],Tabela4[[#This Row],[Cenário]]) -> 6 | R36: =COUNTIFS(Tabela4[[#All],[Cenário]],Tabela4[[#This Row],[Cenário]],Tabela4[[#All],[Status]],"Keyuser - Concluído ") -> 5 | S36: =IF(Tabela4[[#This Row],[Tarefas por Cenário]]-Tabela4[[#This Row],[Tarefas Concluídas]]>0,"Não","Sim") -> Não | T36: =COUNTIFS(Tabela4[[#All],[Cenário]],Tabela4[[#This Row],[Cenário]],Tabela4[[#All],[Status]],Tabela4[[#Headers],[Elo - Em correção ]]) -> 0 | U36: =COUNTIFS(Tabela4[[#All],[Cenário]],Tabela4[[#This Row],[Cenário]],Tabela4[[#All],[Status]],Tabela4[[#Headers],[Keyuser - Aguardando tarefa precedente]]) -> 0 | V36: =COUNTIFS(Tabela4[[#All],[Cenário]],Tabela4[[#This Row],[Cenário]],Tabela4[[#All],[Status]],Tabela4[[#Headers],[Não liberado para testes]]) -> 1 | W36: =IF(Tabela4[[#This Row],[Elo - Em correção ]]>0,"Sim","Não") -> Não | X36: =IF(Tabela4[[#This Row],[Keyuser - Aguardando tarefa precedente]]>0,"Sim","Não") -> Não | Y36: =IF(Tabela4[[#This Row],[Não liberado para testes]]>0,"Sim","Não") -> Sim | Z36: =IF(Tabela4[[#This Row],[Status]]="Keyuser - Pendente",NETWORKDAYS(Tabela4[[#This Row],[Dt Inicial]],TODAY()),"") | AA36: =AND(Tabela4[[#This Row],[Status]]="Keyuser - Aguardando tarefa precedente",K35="Keyuser - Concluído ") -> FALSE
A37: ="OUT-"&IFERROR(MID(Tabela4[[#This Row],[Cenário]],SEARCH("(",Tabela4[[#This Row],[Cenário]])+1,SEARCH(")",Tabela4[[#This Row],[Cenário]])-SEARCH("(",Tabela4[[#This Row],[Cenário]])-1),"")&"_"&ROW() -> OUT-YRET_37 | B37: Sim | C37: Venda Etanol Hidratado F.E (YRET) | D37: Realizar validação tributária - Ordem de venda | E37: 2 | F37: Realizar validação tributária - Ordem de venda | G37: Livia Beserra | H37: 60668337 | K37: Keyuser - Concluído | L37: 45958 | N37: 45958 | Q37: =COUNTIF(Tabela4[[#All],[Cenário]],Tabela4[[#This Row],[Cenário]]) -> 6 | R37: =COUNTIFS(Tabela4[[#All],[Cenário]],Tabela4[[#This Row],[Cenário]],Tabela4[[#All],[Status]],"Keyuser - Concluído ") -> 5 | S37: =IF(Tabela4[[#This Row],[Tarefas por Cenário]]-Tabela4[[#This Row],[Tarefas Concluídas]]>0,"Não","Sim") -> Não | T37: =COUNTIFS(Tabela4[[#All],[Cenário]],Tabela4[[#This Row],[Cenário]],Tabela4[[#All],[Status]],Tabela4[[#Headers],[Elo - Em correção ]]) -> 0 | U37: =COUNTIFS(Tabela4[[#All],[Cenário]],Tabela4[[#This Row],[Cenário]],Tabela4[[#All],[Status]],Tabela4[[#Headers],[Keyuser - Aguardando tarefa precedente]]) -> 0 | V37: =COUNTIFS(Tabela4[[#All],[Cenário]],Tabela4[[#This Row],[Cenário]],Tabela4[[#All],[Status]],Tabela4[[#Headers],[Não liberado para testes]]) -> 1 | W37: =IF(Tabela4[[#This Row],[Elo - Em correção ]]>0,"Sim","Não") -> Não | X37: =IF(Tabela4[[#This Row],[Keyuser - Aguardando tarefa precedente]]>0,"Sim","Não") -> Não | Y37: =IF(Tabela4[[#This Row],[Não liberado para testes]]>0,"Sim","Não") -> Sim | Z37: =IF(Tabela4[[#This Row],[Status]]="Keyuser - Pendente",NETWORKDAYS(Tabela4[[#This Row],[Dt Inicial]],TODAY()),"") | AA37: =AND(Tabela4[[#This Row],[Status]]="Keyuser - Aguardando tarefa precedente",K36="Keyuser - Concluído ") -> FALSE
A38: ="OUT-"&IFERROR(MID(Tabela4[[#This Row],[Cenário]],SEARCH("(",Tabela4[[#This Row],[Cenário]])+1,SEARCH(")",Tabela4[[#This Row],[Cenário]])-SEARCH("(",Tabela4[[#This Row],[Cenário]])-1),"")&"_"&ROW() -> OUT-YRET_38 | B38: Sim | C38: Venda Etanol Hidratado F.E (YRET) | D38: Realizar faturamento | E38: 3 | F38: Realizar faturamento | G38: Marcos Nunes | H38: DocNum - 46482293 | K38: Keyuser - Concluído | L38: 45959 | N38: 45959 | O38: Nota nr 313 | Q38: =COUNTIF(Tabela4[[#All],[Cenário]],Tabela4[[#This Row],[Cenário]]) -> 6 | R38: =COUNTIFS(Tabela4[[#All],[Cenário]],Tabela4[[#This Row],[Cenário]],Tabela4[[#All],[Status]],"Keyuser - Concluído ") -> 5 | S38: =IF(Tabela4[[#This Row],[Tarefas por Cenário]]-Tabela4[[#This Row],[Tarefas Concluídas]]>0,"Não","Sim") -> Não | T38: =COUNTIFS(Tabela4[[#All],[Cenário]],Tabela4[[#This Row],[Cenário]],Tabela4[[#All],[Status]],Tabela4[[#Headers],[Elo - Em correção ]]) -> 0 | U38: =COUNTIFS(Tabela4[[#All],[Cenário]],Tabela4[[#This Row],[Cenário]],Tabela4[[#All],[Status]],Tabela4[[#Headers],[Keyuser - Aguardando tarefa precedente]]) -> 0 | V38: =COUNTIFS(Tabela4[[#All],[Cenário]],Tabela4[[#This Row],[Cenário]],Tabela4[[#All],[Status]],Tabela4[[#Headers],[Não liberado para testes]]) -> 1 | W38: =IF(Tabela4[[#This Row],[Elo - Em correção ]]>0,"Sim","Não") -> Não | X38: =IF(Tabela4[[#This Row],[Keyuser - Aguardando tarefa precedente]]>0,"Sim","Não") -> Não | Y38: =IF(Tabela4[[#This Row],[Não liberado para testes]]>0,"Sim","Não") -> Sim | Z38: =IF(Tabela4[[#This Row],[Status]]="Keyuser - Pendente",NETWORKDAYS(Tabela4[[#This Row],[Dt Inicial]],TODAY()),"") | AA38: =AND(Tabela4[[#This Row],[Status]]="Keyuser - Aguardando tarefa precedente",K37="Keyuser - Concluído ") -> FALSE
A39: ="OUT-"&IFERROR(MID(Tabela4[[#This Row],[Cenário]],SEARCH("(",Tabela4[[#This Row],[Cenário]])+1,SEARCH(")",Tabela4[[#This Row],[Cenário]])-SEARCH("(",Tabela4[[#This Row],[Cenário]])-1),"")&"_"&ROW() -> OUT-YRET_39 | B39: Sim | C39: Venda Etanol Hidratado F.E (YRET) | D39: Realizar validação tributária - SAP, XML e DANFE | E39: 4 | F39: Realizar validação tributária - SAP (xml e DANFE) | G39: Sergio Souza / Giovana Gonçalves | H39: DocNum - 46482293 | K39: Keyuser - Concluído | L39: 45959 | N39: 45959 | Q39: =COUNTIF(Tabela4[[#All],[Cenário]],Tabela4[[#This Row],[Cenário]]) -> 6 | R39: =COUNTIFS(Tabela4[[#All],[Cenário]],Tabela4[[#This Row],[Cenário]],Tabela4[[#All],[Status]],"Keyuser - Concluído ") -> 5 | S39: =IF(Tabela4[[#This Row],[Tarefas por Cenário]]-Tabela4[[#This Row],[Tarefas Concluídas]]>0,"Não","Sim") -> Não | T39: =COUNTIFS(Tabela4[[#All],[Cenário]],Tabela4[[#This Row],[Cenário]],Tabela4[[#All],[Status]],Tabela4[[#Headers],[Elo - Em correção ]]) -> 0 | U39: =COUNTIFS(Tabela4[[#All],[Cenário]],Tabela4[[#This Row],[Cenário]],Tabela4[[#All],[Status]],Tabela4[[#Headers],[Keyuser - Aguardando tarefa precedente]]) -> 0 | V39: =COUNTIFS(Tabela4[[#All],[Cenário]],Tabela4[[#This Row],[Cenário]],Tabela4[[#All],[Status]],Tabela4[[#Headers],[Não liberado para testes]]) -> 1 | W39: =IF(Tabela4[[#This Row],[Elo - Em correção ]]>0,"Sim","Não") -> Não | X39: =IF(Tabela4[[#This Row],[Keyuser - Aguardando tarefa precedente]]>0,"Sim","Não") -> Não | Y39: =IF(Tabela4[[#This Row],[Não liberado para testes]]>0,"Sim","Não") -> Sim | Z39: =IF(Tabela4[[#This Row],[Status]]="Keyuser - Pendente",NETWORKDAYS(Tabela4[[#This Row],[Dt Inicial]],TODAY()),"") | AA39: =AND(Tabela4[[#This Row],[Status]]="Keyuser - Aguardando tarefa precedente",K38="Keyuser - Concluído ") -> FALSE
A40: ="OUT-"&IFERROR(MID(Tabela4[[#This Row],[Cenário]],SEARCH("(",Tabela4[[#This Row],[Cenário]])+1,SEARCH(")",Tabela4[[#This Row],[Cenário]])-SEARCH("(",Tabela4[[#This Row],[Cenário]])-1),"")&"_"&ROW() -> OUT-YRET_40 | B40: Sim | C40: Venda Etanol Hidratado F.E (YRET) | D40: Realizar validação contábil | E40: 5 | F40: Realizar validação contábil | G40: Naiara Toledo | H40: DocNum - 46482293 | K40: Keyuser - Concluído | L40: 45960 | N40: 45960 | Q40: =COUNTIF(Tabela4[[#All],[Cenário]],Tabela4[[#This Row],[Cenário]]) -> 6 | R40: =COUNTIFS(Tabela4[[#All],[Cenário]],Tabela4[[#This Row],[Cenário]],Tabela4[[#All],[Status]],"Keyuser - Concluído ") -> 5 | S40: =IF(Tabela4[[#This Row],[Tarefas por Cenário]]-Tabela4[[#This Row],[Tarefas Concluídas]]>0,"Não","Sim") -> Não | T40: =COUNTIFS(Tabela4[[#All],[Cenário]],Tabela4[[#This Row],[Cenário]],Tabela4[[#All],[Status]],Tabela4[[#Headers],[Elo - Em correção ]]) -> 0 | U40: =COUNTIFS(Tabela4[[#All],[Cenário]],Tabela4[[#This Row],[Cenário]],Tabela4[[#All],[Status]],Tabela4[[#Headers],[Keyuser - Aguardando tarefa precedente]]) -> 0 | V40: =COUNTIFS(Tabela4[[#All],[Cenário]],Tabela4[[#This Row],[Cenário]],Tabela4[[#All],[Status]],Tabela4[[#Headers],[Não liberado para testes]]) -> 1 | W40: =IF(Tabela4[[#This Row],[Elo - Em correção ]]>0,"Sim","Não") -> Não | X40: =IF(Tabela4[[#This Row],[Keyuser - Aguardando tarefa precedente]]>0,"Sim","Não") -> Não | Y40: =IF(Tabela4[[#This Row],[Não liberado para testes]]>0,"Sim","Não") -> Sim | Z40: =IF(Tabela4[[#This Row],[Status]]="Keyuser - Pendente",NETWORKDAYS(Tabela4[[#This Row],[Dt Inicial]],TODAY()),"") | AA40: =AND(Tabela4[[#This Row],[Status]]="Keyuser - Aguardando tarefa precedente",K39="Keyuser - Concluído ") -> FALSE
A41: ="OUT-"&IFERROR(MID(Tabela4[[#This Row],[Cenário]],SEARCH("(",Tabela4[[#This Row],[Cenário]])+1,SEARCH(")",Tabela4[[#This Row],[Cenário]])-SEARCH("(",Tabela4[[#This Row],[Cenário]])-1),"")&"_"&ROW() -> OUT-YRET_41 | B41: Não | C41: Venda Etanol Hidratado F.E (YRET) | D41: Realizar validação Obrigações Acessórias - TaxOne | E41: 6 | F41: Realizar validação Obrigações Acessórias - TaxOne | G41: Sergio Souza / Giovana Gonçalves | K41: Não liberado para testes | Q41: =COUNTIF(Tabela4[[#All],[Cenário]],Tabela4[[#This Row],[Cenário]]) -> 6 | R41: =COUNTIFS(Tabela4[[#All],[Cenário]],Tabela4[[#This Row],[Cenário]],Tabela4[[#All],[Status]],"Keyuser - Concluído ") -> 5 | S41: =IF(Tabela4[[#This Row],[Tarefas por Cenário]]-Tabela4[[#This Row],[Tarefas Concluídas]]>0,"Não","Sim") -> Não | T41: =COUNTIFS(Tabela4[[#All],[Cenário]],Tabela4[[#This Row],[Cenário]],Tabela4[[#All],[Status]],Tabela4[[#Headers],[Elo - Em correção ]]) -> 0 | U41: =COUNTIFS(Tabela4[[#All],[Cenário]],Tabela4[[#This Row],[Cenário]],Tabela4[[#All],[Status]],Tabela4[[#Headers],[Keyuser - Aguardando tarefa precedente]]) -> 0 | V41: =COUNTIFS(Tabela4[[#All],[Cenário]],Tabela4[[#This Row],[Cenário]],Tabela4[[#All],[Status]],Tabela4[[#Headers],[Não liberado para testes]]) -> 1 | W41: =IF(Tabela4[[#This Row],[Elo - Em correção ]]>0,"Sim","Não") -> Não | X41: =IF(Tabela4[[#This Row],[Keyuser - Aguardando tarefa precedente]]>0,"Sim","Não") -> Não | Y41: =IF(Tabela4[[#This Row],[Não liberado para testes]]>0,"Sim","Não") -> Sim | Z41: =IF(Tabela4[[#This Row],[Status]]="Keyuser - Pendente",NETWORKDAYS(Tabela4[[#This Row],[Dt Inicial]],TODAY()),"") | AA41: =AND(Tabela4[[#This Row],[Status]]="Keyuser - Aguardando tarefa precedente",K40="Keyuser - Concluído ") -> FALSE
A42: ="OUT-"&IFERROR(MID(Tabela4[[#This Row],[Cenário]],SEARCH("(",Tabela4[[#This Row],[Cenário]])+1,SEARCH(")",Tabela4[[#This Row],[Cenário]])-SEARCH("(",Tabela4[[#This Row],[Cenário]])-1),"")&"_"&ROW() -> OUT-Y002_42 | B42: Sim | C42: Venda Etanol Anidro F.E - Distribuidora (Y002) | D42: Criar ordem de venda | E42: 1 | F42: Criar ordem de venda | G42: Vania Esteves | H42: 15603605 | I42: BEP: 15581731 | J42: OK | K42: Keyuser - Concluído | L42: 45946 | N42: 45946 | Q42: =COUNTIF(Tabela4[[#All],[Cenário]],Tabela4[[#This Row],[Cenário]]) -> 8 | R42: =COUNTIFS(Tabela4[[#All],[Cenário]],Tabela4[[#This Row],[Cenário]],Tabela4[[#All],[Status]],"Keyuser - Concluído ") -> 7 | S42: =IF(Tabela4[[#This Row],[Tarefas por Cenário]]-Tabela4[[#This Row],[Tarefas Concluídas]]>0,"Não","Sim") -> Não | T42: =COUNTIFS(Tabela4[[#All],[Cenário]],Tabela4[[#This Row],[Cenário]],Tabela4[[#All],[Status]],Tabela4[[#Headers],[Elo - Em correção ]]) -> 0 | U42: =COUNTIFS(Tabela4[[#All],[Cenário]],Tabela4[[#This Row],[Cenário]],Tabela4[[#All],[Status]],Tabela4[[#Headers],[Keyuser - Aguardando tarefa precedente]]) -> 0 | V42: =COUNTIFS(Tabela4[[#All],[Cenário]],Tabela4[[#This Row],[Cenário]],Tabela4[[#All],[Status]],Tabela4[[#Headers],[Não liberado para testes]]) -> 1 | W42: =IF(Tabela4[[#This Row],[Elo - Em correção ]]>0,"Sim","Não") -> Não | X42: =IF(Tabela4[[#This Row],[Keyuser - Aguardando tarefa precedente]]>0,"Sim","Não") -> Não | Y42: =IF(Tabela4[[#This Row],[Não liberado para testes]]>0,"Sim","Não") -> Sim | Z42: =IF(Tabela4[[#This Row],[Status]]="Keyuser - Pendente",NETWORKDAYS(Tabela4[[#This Row],[Dt Inicial]],TODAY()),"") | AA42: =AND(Tabela4[[#This Row],[Status]]="Keyuser - Aguardando tarefa precedente",K41="Keyuser - Concluído ") -> FALSE
A43: ="OUT-"&IFERROR(MID(Tabela4[[#This Row],[Cenário]],SEARCH("(",Tabela4[[#This Row],[Cenário]])+1,SEARCH(")",Tabela4[[#This Row],[Cenário]])-SEARCH("(",Tabela4[[#This Row],[Cenário]])-1),"")&"_"&ROW() -> OUT-Y002_43 | B43: Sim | C43: Venda Etanol Anidro F.E - Distribuidora (Y002) | D43: Realizar validação tributária - Ordem de venda | E43: 2 | F43: Realizar validação tributária - Ordem de venda | G43: Livia Beserra | H43: 15603605 | I43: BEP: 15581731 | J43: OK | K43: Keyuser - Concluído | L43: 45946 | N43: 45946 | Q43: =COUNTIF(Tabela4[[#All],[Cenário]],Tabela4[[#This Row],[Cenário]]) -> 8 | R43: =COUNTIFS(Tabela4[[#All],[Cenário]],Tabela4[[#This Row],[Cenário]],Tabela4[[#All],[Status]],"Keyuser - Concluído ") -> 7 | S43: =IF(Tabela4[[#This Row],[Tarefas por Cenário]]-Tabela4[[#This Row],[Tarefas Concluídas]]>0,"Não","Sim") -> Não | T43: =COUNTIFS(Tabela4[[#All],[Cenário]],Tabela4[[#This Row],[Cenário]],Tabela4[[#All],[Status]],Tabela4[[#Headers],[Elo - Em correção ]]) -> 0 | U43: =COUNTIFS(Tabela4[[#All],[Cenário]],Tabela4[[#This Row],[Cenário]],Tabela4[[#All],[Status]],Tabela4[[#Headers],[Keyuser - Aguardando tarefa precedente]]) -> 0 | V43: =COUNTIFS(Tabela4[[#All],[Cenário]],Tabela4[[#This Row],[Cenário]],Tabela4[[#All],[Status]],Tabela4[[#Headers],[Não liberado para testes]]) -> 1 | W43: =IF(Tabela4[[#This Row],[Elo - Em correção ]]>0,"Sim","Não") -> Não | X43: =IF(Tabela4[[#This Row],[Keyuser - Aguardando tarefa precedente]]>0,"Sim","Não") -> Não | Y43: =IF(Tabela4[[#This Row],[Não liberado para testes]]>0,"Sim","Não") -> Sim | Z43: =IF(Tabela4[[#This Row],[Status]]="Keyuser - Pendente",NETWORKDAYS(Tabela4[[#This Row],[Dt Inicial]],TODAY()),"") | AA43: =AND(Tabela4[[#This Row],[Status]]="Keyuser - Aguardando tarefa precedente",K42="Keyuser - Concluído ") -> FALSE
A44: ="OUT-"&IFERROR(MID(Tabela4[[#This Row],[Cenário]],SEARCH("(",Tabela4[[#This Row],[Cenário]])+1,SEARCH(")",Tabela4[[#This Row],[Cenário]])-SEARCH("(",Tabela4[[#This Row],[Cenário]])-1),"")&"_"&ROW() -> OUT-Y002_44 | B44: Sim | C44: Venda Etanol Anidro F.E - Distribuidora (Y002) | D44: Liberar ordem de venda | E44: 3 | F44: Liberar ordem de venda | G44: Patrick Vianna / Aline Russo | H44: 15603605 | I44: BEP: 15581731 | J44: OK | K44: Keyuser - Concluído | L44: 45946 | N44: 45946 | Q44: =COUNTIF(Tabela4[[#All],[Cenário]],Tabela4[[#This Row],[Cenário]]) -> 8 | R44: =COUNTIFS(Tabela4[[#All],[Cenário]],Tabela4[[#This Row],[Cenário]],Tabela4[[#All],[Status]],"Keyuser - Concluído ") -> 7 | S44: =IF(Tabela4[[#This Row],[Tarefas por Cenário]]-Tabela4[[#This Row],[Tarefas Concluídas]]>0,"Não","Sim") -> Não | T44: =COUNTIFS(Tabela4[[#All],[Cenário]],Tabela4[[#This Row],[Cenário]],Tabela4[[#All],[Status]],Tabela4[[#Headers],[Elo - Em correção ]]) -> 0 | U44: =COUNTIFS(Tabela4[[#All],[Cenário]],Tabela4[[#This Row],[Cenário]],Tabela4[[#All],[Status]],Tabela4[[#Headers],[Keyuser - Aguardando tarefa precedente]]) -> 0 | V44: =COUNTIFS(Tabela4[[#All],[Cenário]],Tabela4[[#This Row],[Cenário]],Tabela4[[#All],[Status]],Tabela4[[#Headers],[Não liberado para testes]]) -> 1 | W44: =IF(Tabela4[[#This Row],[Elo - Em correção ]]>0,"Sim","Não") -> Não | X44: =IF(Tabela4[[#This Row],[Keyuser - Aguardando tarefa precedente]]>0,"Sim","Não") -> Não | Y44: =IF(Tabela4[[#This Row],[Não liberado para testes]]>0,"Sim","Não") -> Sim | Z44: =IF(Tabela4[[#This Row],[Status]]="Keyuser - Pendente",NETWORKDAYS(Tabela4[[#This Row],[Dt Inicial]],TODAY()),"") | AA44: =AND(Tabela4[[#This Row],[Status]]="Keyuser - Aguardando tarefa precedente",K43="Keyuser - Concluído ") -> FALSE
A45: ="OUT-"&IFERROR(MID(Tabela4[[#This Row],[Cenário]],SEARCH("(",Tabela4[[#This Row],[Cenário]])+1,SEARCH(")",Tabela4[[#This Row],[Cenário]])-SEARCH("(",Tabela4[[#This Row],[Cenário]])-1),"")&"_"&ROW() -> OUT-Y002_45 | B45: Sim | C45: Venda Etanol Anidro F.E - Distribuidora (Y002) | D45: Realizar faturamento | E45: 4 | F45: Realizar faturamento | G45: Francisco Netto | H45: DocNum - 46482197 | K45: Keyuser - Concluído | L45: 45947 | N45: 45947 | Q45: =COUNTIF(Tabela4[[#All],[Cenário]],Tabela4[[#This Row],[Cenário]]) -> 8 | R45: =COUNTIFS(Tabela4[[#All],[Cenário]],Tabela4[[#This Row],[Cenário]],Tabela4[[#All],[Status]],"Keyuser - Concluído ") -> 7 | S45: =IF(Tabela4[[#This Row],[Tarefas por Cenário]]-Tabela4[[#This Row],[Tarefas Concluídas]]>0,"Não","Sim") -> Não | T45: =COUNTIFS(Tabela4[[#All],[Cenário]],Tabela4[[#This Row],[Cenário]],Tabela4[[#All],[Status]],Tabela4[[#Headers],[Elo - Em correção ]]) -> 0 | U45: =COUNTIFS(Tabela4[[#All],[Cenário]],Tabela4[[#This Row],[Cenário]],Tabela4[[#All],[Status]],Tabela4[[#Headers],[Keyuser - Aguardando tarefa precedente]]) -> 0 | V45: =COUNTIFS(Tabela4[[#All],[Cenário]],Tabela4[[#This Row],[Cenário]],Tabela4[[#All],[Status]],Tabela4[[#Headers],[Não liberado para testes]]) -> 1 | W45: =IF(Tabela4[[#This Row],[Elo - Em correção ]]>0,"Sim","Não") -> Não | X45: =IF(Tabela4[[#This Row],[Keyuser - Aguardando tarefa precedente]]>0,"Sim","Não") -> Não | Y45: =IF(Tabela4[[#This Row],[Não liberado para testes]]>0,"Sim","Não") -> Sim | Z45: =IF(Tabela4[[#This Row],[Status]]="Keyuser - Pendente",NETWORKDAYS(Tabela4[[#This Row],[Dt Inicial]],TODAY()),"") | AA45: =AND(Tabela4[[#This Row],[Status]]="Keyuser - Aguardando tarefa precedente",K44="Keyuser - Concluído ") -> FALSE
A46: ="OUT-"&IFERROR(MID(Tabela4[[#This Row],[Cenário]],SEARCH("(",Tabela4[[#This Row],[Cenário]])+1,SEARCH(")",Tabela4[[#This Row],[Cenário]])-SEARCH("(",Tabela4[[#This Row],[Cenário]])-1),"")&"_"&ROW() -> OUT-Y002_46 | B46: Sim | C46: Venda Etanol Anidro F.E - Distribuidora (Y002) | D46: Realizar validação tributária - SAP, XML e DANFE | E46: 5 | F46: Realizar validação tributária - SAP (xml e DANFE) | G46: Sergio Souza / Giovana Gonçalves | H46: DocNum - 46482197 | K46: Keyuser - Concluído | L46: 45947 | N46: 45947 | Q46: =COUNTIF(Tabela4[[#All],[Cenário]],Tabela4[[#This Row],[Cenário]]) -> 8 | R46: =COUNTIFS(Tabela4[[#All],[Cenário]],Tabela4[[#This Row],[Cenário]],Tabela4[[#All],[Status]],"Keyuser - Concluído ") -> 7 | S46: =IF(Tabela4[[#This Row],[Tarefas por Cenário]]-Tabela4[[#This Row],[Tarefas Concluídas]]>0,"Não","Sim") -> Não | T46: =COUNTIFS(Tabela4[[#All],[Cenário]],Tabela4[[#This Row],[Cenário]],Tabela4[[#All],[Status]],Tabela4[[#Headers],[Elo - Em correção ]]) -> 0 | U46: =COUNTIFS(Tabela4[[#All],[Cenário]],Tabela4[[#This Row],[Cenário]],Tabela4[[#All],[Status]],Tabela4[[#Headers],[Keyuser - Aguardando tarefa precedente]]) -> 0 | V46: =COUNTIFS(Tabela4[[#All],[Cenário]],Tabela4[[#This Row],[Cenário]],Tabela4[[#All],[Status]],Tabela4[[#Headers],[Não liberado para testes]]) -> 1 | W46: =IF(Tabela4[[#This Row],[Elo - Em correção ]]>0,"Sim","Não") -> Não | X46: =IF(Tabela4[[#This Row],[Keyuser - Aguardando tarefa precedente]]>0,"Sim","Não") -> Não | Y46: =IF(Tabela4[[#This Row],[Não liberado para testes]]>0,"Sim","Não") -> Sim | Z46: =IF(Tabela4[[#This Row],[Status]]="Keyuser - Pendente",NETWORKDAYS(Tabela4[[#This Row],[Dt Inicial]],TODAY()),"") | AA46: =AND(Tabela4[[#This Row],[Status]]="Keyuser - Aguardando tarefa precedente",K45="Keyuser - Concluído ") -> FALSE
A47: ="OUT-"&IFERROR(MID(Tabela4[[#This Row],[Cenário]],SEARCH("(",Tabela4[[#This Row],[Cenário]])+1,SEARCH(")",Tabela4[[#This Row],[Cenário]])-SEARCH("(",Tabela4[[#This Row],[Cenário]])-1),"")&"_"&ROW() -> OUT-Y002_47 | B47: Sim | C47: Venda Etanol Anidro F.E - Distribuidora (Y002) | D47: Realizar validação contábil | E47: 6 | F47: Realizar validação contábil | G47: Naiara Toledo | H47: DocNum - 46482197 | K47: Keyuser - Concluído | L47: 45950 | N47: 45950 | Q47: =COUNTIF(Tabela4[[#All],[Cenário]],Tabela4[[#This Row],[Cenário]]) -> 8 | R47: =COUNTIFS(Tabela4[[#All],[Cenário]],Tabela4[[#This Row],[Cenário]],Tabela4[[#All],[Status]],"Keyuser - Concluído ") -> 7 | S47: =IF(Tabela4[[#This Row],[Tarefas por Cenário]]-Tabela4[[#This Row],[Tarefas Concluídas]]>0,"Não","Sim") -> Não | T47: =COUNTIFS(Tabela4[[#All],[Cenário]],Tabela4[[#This Row],[Cenário]],Tabela4[[#All],[Status]],Tabela4[[#Headers],[Elo - Em correção ]]) -> 0 | U47: =COUNTIFS(Tabela4[[#All],[Cenário]],Tabela4[[#This Row],[Cenário]],Tabela4[[#All],[Status]],Tabela4[[#Headers],[Keyuser - Aguardando tarefa precedente]]) -> 0 | V47: =COUNTIFS(Tabela4[[#All],[Cenário]],Tabela4[[#This Row],[Cenário]],Tabela4[[#All],[Status]],Tabela4[[#Headers],[Não liberado para testes]]) -> 1 | W47: =IF(Tabela4[[#This Row],[Elo - Em correção ]]>0,"Sim","Não") -> Não | X47: =IF(Tabela4[[#This Row],[Keyuser - Aguardando tarefa precedente]]>0,"Sim","Não") -> Não | Y47: =IF(Tabela4[[#This Row],[Não liberado para testes]]>0,"Sim","Não") -> Sim | Z47: =IF(Tabela4[[#This Row],[Status]]="Keyuser - Pendente",NETWORKDAYS(Tabela4[[#This Row],[Dt Inicial]],TODAY()),"") | AA47: =AND(Tabela4[[#This Row],[Status]]="Keyuser - Aguardando tarefa precedente",K46="Keyuser - Concluído ") -> FALSE
A48: ="OUT-"&IFERROR(MID(Tabela4[[#This Row],[Cenário]],SEARCH("(",Tabela4[[#This Row],[Cenário]])+1,SEARCH(")",Tabela4[[#This Row],[Cenário]])-SEARCH("(",Tabela4[[#This Row],[Cenário]])-1),"")&"_"&ROW() -> OUT-Y002_48 | B48: Não | C48: Venda Etanol Anidro F.E - Distribuidora (Y002) | D48: Realizar validação Obrigações Acessórias - TaxOne | E48: 7 | F48: Realizar validação Obrigações Acessórias - TaxOne | G48: Sergio Souza / Giovana Gonçalves | K48: Não liberado para testes | Q48: =COUNTIF(Tabela4[[#All],[Cenário]],Tabela4[[#This Row],[Cenário]]) -> 8 | R48: =COUNTIFS(Tabela4[[#All],[Cenário]],Tabela4[[#This Row],[Cenário]],Tabela4[[#All],[Status]],"Keyuser - Concluído ") -> 7 | S48: =IF(Tabela4[[#This Row],[Tarefas por Cenário]]-Tabela4[[#This Row],[Tarefas Concluídas]]>0,"Não","Sim") -> Não | T48: =COUNTIFS(Tabela4[[#All],[Cenário]],Tabela4[[#This Row],[Cenário]],Tabela4[[#All],[Status]],Tabela4[[#Headers],[Elo - Em correção ]]) -> 0 | U48: =COUNTIFS(Tabela4[[#All],[Cenário]],Tabela4[[#This Row],[Cenário]],Tabela4[[#All],[Status]],Tabela4[[#Headers],[Keyuser - Aguardando tarefa precedente]]) -> 0 | V48: =COUNTIFS(Tabela4[[#All],[Cenário]],Tabela4[[#This Row],[Cenário]],Tabela4[[#All],[Status]],Tabela4[[#Headers],[Não liberado para testes]]) -> 1 | W48: =IF(Tabela4[[#This Row],[Elo - Em correção ]]>0,"Sim","Não") -> Não | X48: =IF(Tabela4[[#This Row],[Keyuser - Aguardando tarefa precedente]]>0,"Sim","Não") -> Não | Y48: =IF(Tabela4[[#This Row],[Não liberado para testes]]>0,"Sim","Não") -> Sim | Z48: =IF(Tabela4[[#This Row],[Status]]="Keyuser - Pendente",NETWORKDAYS(Tabela4[[#This Row],[Dt Inicial]],TODAY()),"") | AA48: =AND(Tabela4[[#This Row],[Status]]="Keyuser - Aguardando tarefa precedente",K47="Keyuser - Concluído ") -> FALSE
A49: ="OUT-"&IFERROR(MID(Tabela4[[#This Row],[Cenário]],SEARCH("(",Tabela4[[#This Row],[Cenário]])+1,SEARCH(")",Tabela4[[#This Row],[Cenário]])-SEARCH("(",Tabela4[[#This Row],[Cenário]])-1),"")&"_"&ROW() -> OUT-Y002_49 | B49: Sim | C49: Venda Etanol Anidro F.E - Distribuidora (Y002) | D49: Realizar validação Títulos Financeiros | E49: 8 | F49: Realizar validação Títulos Financeiros | G49: Patrick Vianna / Aline Russo | H49: 15603605 | I49: BEP: 15581731 | J49: OK | K49: Keyuser - Concluído | L49: 45951 | N49: 45951 | Q49: =COUNTIF(Tabela4[[#All],[Cenário]],Tabela4[[#This Row],[Cenário]]) -> 8 | R49: =COUNTIFS(Tabela4[[#All],[Cenário]],Tabela4[[#This Row],[Cenário]],Tabela4[[#All],[Status]],"Keyuser - Concluído ") -> 7 | S49: =IF(Tabela4[[#This Row],[Tarefas por Cenário]]-Tabela4[[#This Row],[Tarefas Concluídas]]>0,"Não","Sim") -> Não | T49: =COUNTIFS(Tabela4[[#All],[Cenário]],Tabela4[[#This Row],[Cenário]],Tabela4[[#All],[Status]],Tabela4[[#Headers],[Elo - Em correção ]]) -> 0 | U49: =COUNTIFS(Tabela4[[#All],[Cenário]],Tabela4[[#This Row],[Cenário]],Tabela4[[#All],[Status]],Tabela4[[#Headers],[Keyuser - Aguardando tarefa precedente]]) -> 0 | V49: =COUNTIFS(Tabela4[[#All],[Cenário]],Tabela4[[#This Row],[Cenário]],Tabela4[[#All],[Status]],Tabela4[[#Headers],[Não liberado para testes]]) -> 1 | W49: =IF(Tabela4[[#This Row],[Elo - Em correção ]]>0,"Sim","Não") -> Não | X49: =IF(Tabela4[[#This Row],[Keyuser - Aguardando tarefa precedente]]>0,"Sim","Não") -> Não | Y49: =IF(Tabela4[[#This Row],[Não liberado para testes]]>0,"Sim","Não") -> Sim | Z49: =IF(Tabela4[[#This Row],[Status]]="Keyuser - Pendente",NETWORKDAYS(Tabela4[[#This Row],[Dt Inicial]],TODAY()),"") | AA49: =AND(Tabela4[[#This Row],[Status]]="Keyuser - Aguardando tarefa precedente",K48="Keyuser - Concluído ") -> FALSE
A50: ="OUT-"&IFERROR(MID(Tabela4[[#This Row],[Cenário]],SEARCH("(",Tabela4[[#This Row],[Cenário]])+1,SEARCH(")",Tabela4[[#This Row],[Cenário]])-SEARCH("(",Tabela4[[#This Row],[Cenário]])-1),"")&"_"&ROW() -> OUT-YDEV_50 | B50: Sim | C50: Venda Etanol Anidro F.E - Distribuidora (YDEV) | D50: Criar ordem de venda | E50: 1 | F50: Criar ordem de venda | G50: Marcos Nunes | H50: 60668331 | K50: Keyuser - Concluído | L50: 45958 | N50: 45958 | Q50: =COUNTIF(Tabela4[[#All],[Cenário]],Tabela4[[#This Row],[Cenário]]) -> 6 | R50: =COUNTIFS(Tabela4[[#All],[Cenário]],Tabela4[[#This Row],[Cenário]],Tabela4[[#All],[Status]],"Keyuser - Concluído ") -> 5 | S50: =IF(Tabela4[[#This Row],[Tarefas por Cenário]]-Tabela4[[#This Row],[Tarefas Concluídas]]>0,"Não","Sim") -> Não | T50: =COUNTIFS(Tabela4[[#All],[Cenário]],Tabela4[[#This Row],[Cenário]],Tabela4[[#All],[Status]],Tabela4[[#Headers],[Elo - Em correção ]]) -> 0 | U50: =COUNTIFS(Tabela4[[#All],[Cenário]],Tabela4[[#This Row],[Cenário]],Tabela4[[#All],[Status]],Tabela4[[#Headers],[Keyuser - Aguardando tarefa precedente]]) -> 0 | V50: =COUNTIFS(Tabela4[[#All],[Cenário]],Tabela4[[#This Row],[Cenário]],Tabela4[[#All],[Status]],Tabela4[[#Headers],[Não liberado para testes]]) -> 1 | W50: =IF(Tabela4[[#This Row],[Elo - Em correção ]]>0,"Sim","Não") -> Não | X50: =IF(Tabela4[[#This Row],[Keyuser - Aguardando tarefa precedente]]>0,"Sim","Não") -> Não | Y50: =IF(Tabela4[[#This Row],[Não liberado para testes]]>0,"Sim","Não") -> Sim | Z50: =IF(Tabela4[[#This Row],[Status]]="Keyuser - Pendente",NETWORKDAYS(Tabela4[[#This Row],[Dt Inicial]],TODAY()),"") | AA50: =AND(Tabela4[[#This Row],[Status]]="Keyuser - Aguardando tarefa precedente",K49="Keyuser - Concluído ") -> FALSE
A51: ="OUT-"&IFERROR(MID(Tabela4[[#This Row],[Cenário]],SEARCH("(",Tabela4[[#This Row],[Cenário]])+1,SEARCH(")",Tabela4[[#This Row],[Cenário]])-SEARCH("(",Tabela4[[#This Row],[Cenário]])-1),"")&"_"&ROW() -> OUT-YDEV_51 | B51: Sim | C51: Venda Etanol Anidro F.E - Distribuidora (YDEV) | D51: Realizar validação tributária - Ordem de venda | E51: 2 | F51: Realizar validação tributária - Ordem de venda | G51: Livia Beserra | H51: 60668331 | K51: Keyuser - Concluído | L51: 45958 | N51: 45958 | Q51: =COUNTIF(Tabela4[[#All],[Cenário]],Tabela4[[#This Row],[Cenário]]) -> 6 | R51: =COUNTIFS(Tabela4[[#All],[Cenário]],Tabela4[[#This Row],[Cenário]],Tabela4[[#All],[Status]],"Keyuser - Concluído ") -> 5 | S51: =IF(Tabela4[[#This Row],[Tarefas por Cenário]]-Tabela4[[#This Row],[Tarefas Concluídas]]>0,"Não","Sim") -> Não | T51: =COUNTIFS(Tabela4[[#All],[Cenário]],Tabela4[[#This Row],[Cenário]],Tabela4[[#All],[Status]],Tabela4[[#Headers],[Elo - Em correção ]]) -> 0 | U51: =COUNTIFS(Tabela4[[#All],[Cenário]],Tabela4[[#This Row],[Cenário]],Tabela4[[#All],[Status]],Tabela4[[#Headers],[Keyuser - Aguardando tarefa precedente]]) -> 0 | V51: =COUNTIFS(Tabela4[[#All],[Cenário]],Tabela4[[#This Row],[Cenário]],Tabela4[[#All],[Status]],Tabela4[[#Headers],[Não liberado para testes]]) -> 1 | W51: =IF(Tabela4[[#This Row],[Elo - Em correção ]]>0,"Sim","Não") -> Não | X51: =IF(Tabela4[[#This Row],[Keyuser - Aguardando tarefa precedente]]>0,"Sim","Não") -> Não | Y51: =IF(Tabela4[[#This Row],[Não liberado para testes]]>0,"Sim","Não") -> Sim | Z51: =IF(Tabela4[[#This Row],[Status]]="Keyuser - Pendente",NETWORKDAYS(Tabela4[[#This Row],[Dt Inicial]],TODAY()),"") | AA51: =AND(Tabela4[[#This Row],[Status]]="Keyuser - Aguardando tarefa precedente",K50="Keyuser - Concluído ") -> FALSE
A52: ="OUT-"&IFERROR(MID(Tabela4[[#This Row],[Cenário]],SEARCH("(",Tabela4[[#This Row],[Cenário]])+1,SEARCH(")",Tabela4[[#This Row],[Cenário]])-SEARCH("(",Tabela4[[#This Row],[Cenário]])-1),"")&"_"&ROW() -> OUT-YDEV_52 | B52: Sim | C52: Venda Etanol Anidro F.E - Distribuidora (YDEV) | D52: Realizar faturamento | E52: 3 | F52: Realizar faturamento | G52: Marcos Nunes | H52: DocNum - 46482286 | K52: Keyuser - Concluído | L52: 45959 | N52: 45959 | O52: Nota nr 70463 | Q52: =COUNTIF(Tabela4[[#All],[Cenário]],Tabela4[[#This Row],[Cenário]]) -> 6 | R52: =COUNTIFS(Tabela4[[#All],[Cenário]],Tabela4[[#This Row],[Cenário]],Tabela4[[#All],[Status]],"Keyuser - Concluído ") -> 5 | S52: =IF(Tabela4[[#This Row],[Tarefas por Cenário]]-Tabela4[[#This Row],[Tarefas Concluídas]]>0,"Não","Sim") -> Não | T52: =COUNTIFS(Tabela4[[#All],[Cenário]],Tabela4[[#This Row],[Cenário]],Tabela4[[#All],[Status]],Tabela4[[#Headers],[Elo - Em correção ]]) -> 0 | U52: =COUNTIFS(Tabela4[[#All],[Cenário]],Tabela4[[#This Row],[Cenário]],Tabela4[[#All],[Status]],Tabela4[[#Headers],[Keyuser - Aguardando tarefa precedente]]) -> 0 | V52: =COUNTIFS(Tabela4[[#All],[Cenário]],Tabela4[[#This Row],[Cenário]],Tabela4[[#All],[Status]],Tabela4[[#Headers],[Não liberado para testes]]) -> 1 | W52: =IF(Tabela4[[#This Row],[Elo - Em correção ]]>0,"Sim","Não") -> Não | X52: =IF(Tabela4[[#This Row],[Keyuser - Aguardando tarefa precedente]]>0,"Sim","Não") -> Não | Y52: =IF(Tabela4[[#This Row],[Não liberado para testes]]>0,"Sim","Não") -> Sim | Z52: =IF(Tabela4[[#This Row],[Status]]="Keyuser - Pendente",NETWORKDAYS(Tabela4[[#This Row],[Dt Inicial]],TODAY()),"") | AA52: =AND(Tabela4[[#This Row],[Status]]="Keyuser - Aguardando tarefa precedente",K51="Keyuser - Concluído ") -> FALSE
A53: ="OUT-"&IFERROR(MID(Tabela4[[#This Row],[Cenário]],SEARCH("(",Tabela4[[#This Row],[Cenário]])+1,SEARCH(")",Tabela4[[#This Row],[Cenário]])-SEARCH("(",Tabela4[[#This Row],[Cenário]])-1),"")&"_"&ROW() -> OUT-YDEV_53 | B53: Sim | C53: Venda Etanol Anidro F.E - Distribuidora (YDEV) | D53: Realizar validação tributária - SAP, XML e DANFE | E53: 4 | F53: Realizar validação tributária - SAP (xml e DANFE) | G53: Sergio Souza / Giovana Gonçalves | H53: DocNum - 46482286 | K53: Keyuser - Concluído | L53: 45959 | N53: 45959 | Q53: =COUNTIF(Tabela4[[#All],[Cenário]],Tabela4[[#This Row],[Cenário]]) -> 6 | R53: =COUNTIFS(Tabela4[[#All],[Cenário]],Tabela4[[#This Row],[Cenário]],Tabela4[[#All],[Status]],"Keyuser - Concluído ") -> 5 | S53: =IF(Tabela4[[#This Row],[Tarefas por Cenário]]-Tabela4[[#This Row],[Tarefas Concluídas]]>0,"Não","Sim") -> Não | T53: =COUNTIFS(Tabela4[[#All],[Cenário]],Tabela4[[#This Row],[Cenário]],Tabela4[[#All],[Status]],Tabela4[[#Headers],[Elo - Em correção ]]) -> 0 | U53: =COUNTIFS(Tabela4[[#All],[Cenário]],Tabela4[[#This Row],[Cenário]],Tabela4[[#All],[Status]],Tabela4[[#Headers],[Keyuser - Aguardando tarefa precedente]]) -> 0 | V53: =COUNTIFS(Tabela4[[#All],[Cenário]],Tabela4[[#This Row],[Cenário]],Tabela4[[#All],[Status]],Tabela4[[#Headers],[Não liberado para testes]]) -> 1 | W53: =IF(Tabela4[[#This Row],[Elo - Em correção ]]>0,"Sim","Não") -> Não | X53: =IF(Tabela4[[#This Row],[Keyuser - Aguardando tarefa precedente]]>0,"Sim","Não") -> Não | Y53: =IF(Tabela4[[#This Row],[Não liberado para testes]]>0,"Sim","Não") -> Sim | Z53: =IF(Tabela4[[#This Row],[Status]]="Keyuser - Pendente",NETWORKDAYS(Tabela4[[#This Row],[Dt Inicial]],TODAY()),"") | AA53: =AND(Tabela4[[#This Row],[Status]]="Keyuser - Aguardando tarefa precedente",K52="Keyuser - Concluído ") -> FALSE
A54: ="OUT-"&IFERROR(MID(Tabela4[[#This Row],[Cenário]],SEARCH("(",Tabela4[[#This Row],[Cenário]])+1,SEARCH(")",Tabela4[[#This Row],[Cenário]])-SEARCH("(",Tabela4[[#This Row],[Cenário]])-1),"")&"_"&ROW() -> OUT-YDEV_54 | B54: Sim | C54: Venda Etanol Anidro F.E - Distribuidora (YDEV) | D54: Realizar validação contábil | E54: 5 | F54: Realizar validação contábil | G54: Naiara Toledo | H54: DocNum - 46482286 | K54: Keyuser - Concluído | L54: 45960 | N54: 45960 | Q54: =COUNTIF(Tabela4[[#All],[Cenário]],Tabela4[[#This Row],[Cenário]]) -> 6 | R54: =COUNTIFS(Tabela4[[#All],[Cenário]],Tabela4[[#This Row],[Cenário]],Tabela4[[#All],[Status]],"Keyuser - Concluído ") -> 5 | S54: =IF(Tabela4[[#This Row],[Tarefas por Cenário]]-Tabela4[[#This Row],[Tarefas Concluídas]]>0,"Não","Sim") -> Não | T54: =COUNTIFS(Tabela4[[#All],[Cenário]],Tabela4[[#This Row],[Cenário]],Tabela4[[#All],[Status]],Tabela4[[#Headers],[Elo - Em correção ]]) -> 0 | U54: =COUNTIFS(Tabela4[[#All],[Cenário]],Tabela4[[#This Row],[Cenário]],Tabela4[[#All],[Status]],Tabela4[[#Headers],[Keyuser - Aguardando tarefa precedente]]) -> 0 | V54: =COUNTIFS(Tabela4[[#All],[Cenário]],Tabela4[[#This Row],[Cenário]],Tabela4[[#All],[Status]],Tabela4[[#Headers],[Não liberado para testes]]) -> 1 | W54: =IF(Tabela4[[#This Row],[Elo - Em correção ]]>0,"Sim","Não") -> Não | X54: =IF(Tabela4[[#This Row],[Keyuser - Aguardando tarefa precedente]]>0,"Sim","Não") -> Não | Y54: =IF(Tabela4[[#This Row],[Não liberado para testes]]>0,"Sim","Não") -> Sim | Z54: =IF(Tabela4[[#This Row],[Status]]="Keyuser - Pendente",NETWORKDAYS(Tabela4[[#This Row],[Dt Inicial]],TODAY()),"") | AA54: =AND(Tabela4[[#This Row],[Status]]="Keyuser - Aguardando tarefa precedente",K53="Keyuser - Concluído ") -> FALSE
A55: ="OUT-"&IFERROR(MID(Tabela4[[#This Row],[Cenário]],SEARCH("(",Tabela4[[#This Row],[Cenário]])+1,SEARCH(")",Tabela4[[#This Row],[Cenário]])-SEARCH("(",Tabela4[[#This Row],[Cenário]])-1),"")&"_"&ROW() -> OUT-YDEV_55 | B55: Não | C55: Venda Etanol Anidro F.E - Distribuidora (YDEV) | D55: Realizar validação Obrigações Acessórias - TaxOne | E55: 6 | F55: Realizar validação Obrigações Acessórias - TaxOne | G55: Sergio Souza / Giovana Gonçalves | K55: Não liberado para testes | Q55: =COUNTIF(Tabela4[[#All],[Cenário]],Tabela4[[#This Row],[Cenário]]) -> 6 | R55: =COUNTIFS(Tabela4[[#All],[Cenário]],Tabela4[[#This Row],[Cenário]],Tabela4[[#All],[Status]],"Keyuser - Concluído ") -> 5 | S55: =IF(Tabela4[[#This Row],[Tarefas por Cenário]]-Tabela4[[#This Row],[Tarefas Concluídas]]>0,"Não","Sim") -> Não | T55: =COUNTIFS(Tabela4[[#All],[Cenário]],Tabela4[[#This Row],[Cenário]],Tabela4[[#All],[Status]],Tabela4[[#Headers],[Elo - Em correção ]]) -> 0 | U55: =COUNTIFS(Tabela4[[#All],[Cenário]],Tabela4[[#This Row],[Cenário]],Tabela4[[#All],[Status]],Tabela4[[#Headers],[Keyuser - Aguardando tarefa precedente]]) -> 0 | V55: =COUNTIFS(Tabela4[[#All],[Cenário]],Tabela4[[#This Row],[Cenário]],Tabela4[[#All],[Status]],Tabela4[[#Headers],[Não liberado para testes]]) -> 1 | W55: =IF(Tabela4[[#This Row],[Elo - Em correção ]]>0,"Sim","Não") -> Não | X55: =IF(Tabela4[[#This Row],[Keyuser - Aguardando tarefa precedente]]>0,"Sim","Não") -> Não | Y55: =IF(Tabela4[[#This Row],[Não liberado para testes]]>0,"Sim","Não") -> Sim | Z55: =IF(Tabela4[[#This Row],[Status]]="Keyuser - Pendente",NETWORKDAYS(Tabela4[[#This Row],[Dt Inicial]],TODAY()),"") | AA55: =AND(Tabela4[[#This Row],[Status]]="Keyuser - Aguardando tarefa precedente",K54="Keyuser - Concluído ") -> FALSE
A56: ="OUT-"&IFERROR(MID(Tabela4[[#This Row],[Cenário]],SEARCH("(",Tabela4[[#This Row],[Cenário]])+1,SEARCH(")",Tabela4[[#This Row],[Cenário]])-SEARCH("(",Tabela4[[#This Row],[Cenário]])-1),"")&"_"&ROW() -> OUT-YRET_56 | B56: Sim | C56: Venda Etanol Anidro F.E - Distribuidora (YRET) | D56: Criar ordem de venda | E56: 1 | F56: Criar ordem de venda | G56: Marcos Nunes | H56: 60668338 | K56: Keyuser - Concluído | L56: 45958 | N56: 45958 | Q56: =COUNTIF(Tabela4[[#All],[Cenário]],Tabela4[[#This Row],[Cenário]]) -> 6 | R56: =COUNTIFS(Tabela4[[#All],[Cenário]],Tabela4[[#This Row],[Cenário]],Tabela4[[#All],[Status]],"Keyuser - Concluído ") -> 5 | S56: =IF(Tabela4[[#This Row],[Tarefas por Cenário]]-Tabela4[[#This Row],[Tarefas Concluídas]]>0,"Não","Sim") -> Não | T56: =COUNTIFS(Tabela4[[#All],[Cenário]],Tabela4[[#This Row],[Cenário]],Tabela4[[#All],[Status]],Tabela4[[#Headers],[Elo - Em correção ]]) -> 0 | U56: =COUNTIFS(Tabela4[[#All],[Cenário]],Tabela4[[#This Row],[Cenário]],Tabela4[[#All],[Status]],Tabela4[[#Headers],[Keyuser - Aguardando tarefa precedente]]) -> 0 | V56: =COUNTIFS(Tabela4[[#All],[Cenário]],Tabela4[[#This Row],[Cenário]],Tabela4[[#All],[Status]],Tabela4[[#Headers],[Não liberado para testes]]) -> 1 | W56: =IF(Tabela4[[#This Row],[Elo - Em correção ]]>0,"Sim","Não") -> Não | X56: =IF(Tabela4[[#This Row],[Keyuser - Aguardando tarefa precedente]]>0,"Sim","Não") -> Não | Y56: =IF(Tabela4[[#This Row],[Não liberado para testes]]>0,"Sim","Não") -> Sim | Z56: =IF(Tabela4[[#This Row],[Status]]="Keyuser - Pendente",NETWORKDAYS(Tabela4[[#This Row],[Dt Inicial]],TODAY()),"") | AA56: =AND(Tabela4[[#This Row],[Status]]="Keyuser - Aguardando tarefa precedente",K55="Keyuser - Concluído ") -> FALSE
A57: ="OUT-"&IFERROR(MID(Tabela4[[#This Row],[Cenário]],SEARCH("(",Tabela4[[#This Row],[Cenário]])+1,SEARCH(")",Tabela4[[#This Row],[Cenário]])-SEARCH("(",Tabela4[[#This Row],[Cenário]])-1),"")&"_"&ROW() -> OUT-YRET_57 | B57: Sim | C57: Venda Etanol Anidro F.E - Distribuidora (YRET) | D57: Realizar validação tributária - Ordem de venda | E57: 2 | F57: Realizar validação tributária - Ordem de venda | G57: Livia Beserra | H57: 60668338 | K57: Keyuser - Concluído | L57: 45958 | N57: 45958 | Q57: =COUNTIF(Tabela4[[#All],[Cenário]],Tabela4[[#This Row],[Cenário]]) -> 6 | R57: =COUNTIFS(Tabela4[[#All],[Cenário]],Tabela4[[#This Row],[Cenário]],Tabela4[[#All],[Status]],"Keyuser - Concluído ") -> 5 | S57: =IF(Tabela4[[#This Row],[Tarefas por Cenário]]-Tabela4[[#This Row],[Tarefas Concluídas]]>0,"Não","Sim") -> Não | T57: =COUNTIFS(Tabela4[[#All],[Cenário]],Tabela4[[#This Row],[Cenário]],Tabela4[[#All],[Status]],Tabela4[[#Headers],[Elo - Em correção ]]) -> 0 | U57: =COUNTIFS(Tabela4[[#All],[Cenário]],Tabela4[[#This Row],[Cenário]],Tabela4[[#All],[Status]],Tabela4[[#Headers],[Keyuser - Aguardando tarefa precedente]]) -> 0 | V57: =COUNTIFS(Tabela4[[#All],[Cenário]],Tabela4[[#This Row],[Cenário]],Tabela4[[#All],[Status]],Tabela4[[#Headers],[Não liberado para testes]]) -> 1 | W57: =IF(Tabela4[[#This Row],[Elo - Em correção ]]>0,"Sim","Não") -> Não | X57: =IF(Tabela4[[#This Row],[Keyuser - Aguardando tarefa precedente]]>0,"Sim","Não") -> Não | Y57: =IF(Tabela4[[#This Row],[Não liberado para testes]]>0,"Sim","Não") -> Sim | Z57: =IF(Tabela4[[#This Row],[Status]]="Keyuser - Pendente",NETWORKDAYS(Tabela4[[#This Row],[Dt Inicial]],TODAY()),"") | AA57: =AND(Tabela4[[#This Row],[Status]]="Keyuser - Aguardando tarefa precedente",K56="Keyuser - Concluído ") -> FALSE
A58: ="OUT-"&IFERROR(MID(Tabela4[[#This Row],[Cenário]],SEARCH("(",Tabela4[[#This Row],[Cenário]])+1,SEARCH(")",Tabela4[[#This Row],[Cenário]])-SEARCH("(",Tabela4[[#This Row],[Cenário]])-1),"")&"_"&ROW() -> OUT-YRET_58 | B58: Sim | C58: Venda Etanol Anidro F.E - Distribuidora (YRET) | D58: Realizar faturamento | E58: 3 | F58: Realizar faturamento | G58: Marcos Nunes | H58: DocNum - 46482294 | K58: Keyuser - Concluído | L58: 45959 | N58: 45959 | O58: Nota nr 681 | Q58: =COUNTIF(Tabela4[[#All],[Cenário]],Tabela4[[#This Row],[Cenário]]) -> 6 | R58: =COUNTIFS(Tabela4[[#All],[Cenário]],Tabela4[[#This Row],[Cenário]],Tabela4[[#All],[Status]],"Keyuser - Concluído ") -> 5 | S58: =IF(Tabela4[[#This Row],[Tarefas por Cenário]]-Tabela4[[#This Row],[Tarefas Concluídas]]>0,"Não","Sim") -> Não | T58: =COUNTIFS(Tabela4[[#All],[Cenário]],Tabela4[[#This Row],[Cenário]],Tabela4[[#All],[Status]],Tabela4[[#Headers],[Elo - Em correção ]]) -> 0 | U58: =COUNTIFS(Tabela4[[#All],[Cenário]],Tabela4[[#This Row],[Cenário]],Tabela4[[#All],[Status]],Tabela4[[#Headers],[Keyuser - Aguardando tarefa precedente]]) -> 0 | V58: =COUNTIFS(Tabela4[[#All],[Cenário]],Tabela4[[#This Row],[Cenário]],Tabela4[[#All],[Status]],Tabela4[[#Headers],[Não liberado para testes]]) -> 1 | W58: =IF(Tabela4[[#This Row],[Elo - Em correção ]]>0,"Sim","Não") -> Não | X58: =IF(Tabela4[[#This Row],[Keyuser - Aguardando tarefa precedente]]>0,"Sim","Não") -> Não | Y58: =IF(Tabela4[[#This Row],[Não liberado para testes]]>0,"Sim","Não") -> Sim | Z58: =IF(Tabela4[[#This Row],[Status]]="Keyuser - Pendente",NETWORKDAYS(Tabela4[[#This Row],[Dt Inicial]],TODAY()),"") | AA58: =AND(Tabela4[[#This Row],[Status]]="Keyuser - Aguardando tarefa precedente",K57="Keyuser - Concluído ") -> FALSE
A59: ="OUT-"&IFERROR(MID(Tabela4[[#This Row],[Cenário]],SEARCH("(",Tabela4[[#This Row],[Cenário]])+1,SEARCH(")",Tabela4[[#This Row],[Cenário]])-SEARCH("(",Tabela4[[#This Row],[Cenário]])-1),"")&"_"&ROW() -> OUT-YRET_59 | B59: Sim | C59: Venda Etanol Anidro F.E - Distribuidora (YRET) | D59: Realizar validação tributária - SAP, XML e DANFE | E59: 4 | F59: Realizar validação tributária - SAP (xml e DANFE) | G59: Sergio Souza / Giovana Gonçalves | H59: DocNum - 46482294 | K59: Keyuser - Concluído | L59: 45960 | N59: 45960 | Q59: =COUNTIF(Tabela4[[#All],[Cenário]],Tabela4[[#This Row],[Cenário]]) -> 6 | R59: =COUNTIFS(Tabela4[[#All],[Cenário]],Tabela4[[#This Row],[Cenário]],Tabela4[[#All],[Status]],"Keyuser - Concluído ") -> 5 | S59: =IF(Tabela4[[#This Row],[Tarefas por Cenário]]-Tabela4[[#This Row],[Tarefas Concluídas]]>0,"Não","Sim") -> Não | T59: =COUNTIFS(Tabela4[[#All],[Cenário]],Tabela4[[#This Row],[Cenário]],Tabela4[[#All],[Status]],Tabela4[[#Headers],[Elo - Em correção ]]) -> 0 | U59: =COUNTIFS(Tabela4[[#All],[Cenário]],Tabela4[[#This Row],[Cenário]],Tabela4[[#All],[Status]],Tabela4[[#Headers],[Keyuser - Aguardando tarefa precedente]]) -> 0 | V59: =COUNTIFS(Tabela4[[#All],[Cenário]],Tabela4[[#This Row],[Cenário]],Tabela4[[#All],[Status]],Tabela4[[#Headers],[Não liberado para testes]]) -> 1 | W59: =IF(Tabela4[[#This Row],[Elo - Em correção ]]>0,"Sim","Não") -> Não | X59: =IF(Tabela4[[#This Row],[Keyuser - Aguardando tarefa precedente]]>0,"Sim","Não") -> Não | Y59: =IF(Tabela4[[#This Row],[Não liberado para testes]]>0,"Sim","Não") -> Sim | Z59: =IF(Tabela4[[#This Row],[Status]]="Keyuser - Pendente",NETWORKDAYS(Tabela4[[#This Row],[Dt Inicial]],TODAY()),"") | AA59: =AND(Tabela4[[#This Row],[Status]]="Keyuser - Aguardando tarefa precedente",K58="Keyuser - Concluído ") -> FALSE
A60: ="OUT-"&IFERROR(MID(Tabela4[[#This Row],[Cenário]],SEARCH("(",Tabela4[[#This Row],[Cenário]])+1,SEARCH(")",Tabela4[[#This Row],[Cenário]])-SEARCH("(",Tabela4[[#This Row],[Cenário]])-1),"")&"_"&ROW() -> OUT-YRET_60 | B60: Sim | C60: Venda Etanol Anidro F.E - Distribuidora (YRET) | D60: Realizar validação contábil | E60: 5 | F60: Realizar validação contábil | G60: Naiara Toledo | H60: DocNum - 46482294 | K60: Keyuser - Concluído | L60: 45960 | N60: 45960 | Q60: =COUNTIF(Tabela4[[#All],[Cenário]],Tabela4[[#This Row],[Cenário]]) -> 6 | R60: =COUNTIFS(Tabela4[[#All],[Cenário]],Tabela4[[#This Row],[Cenário]],Tabela4[[#All],[Status]],"Keyuser - Concluído ") -> 5 | S60: =IF(Tabela4[[#This Row],[Tarefas por Cenário]]-Tabela4[[#This Row],[Tarefas Concluídas]]>0,"Não","Sim") -> Não | T60: =COUNTIFS(Tabela4[[#All],[Cenário]],Tabela4[[#This Row],[Cenário]],Tabela4[[#All],[Status]],Tabela4[[#Headers],[Elo - Em correção ]]) -> 0 | U60: =COUNTIFS(Tabela4[[#All],[Cenário]],Tabela4[[#This Row],[Cenário]],Tabela4[[#All],[Status]],Tabela4[[#Headers],[Keyuser - Aguardando tarefa precedente]]) -> 0 | V60: =COUNTIFS(Tabela4[[#All],[Cenário]],Tabela4[[#This Row],[Cenário]],Tabela4[[#All],[Status]],Tabela4[[#Headers],[Não liberado para testes]]) -> 1 | W60: =IF(Tabela4[[#This Row],[Elo - Em correção ]]>0,"Sim","Não") -> Não | X60: =IF(Tabela4[[#This Row],[Keyuser - Aguardando tarefa precedente]]>0,"Sim","Não") -> Não | Y60: =IF(Tabela4[[#This Row],[Não liberado para testes]]>0,"Sim","Não") -> Sim | Z60: =IF(Tabela4[[#This Row],[Status]]="Keyuser - Pendente",NETWORKDAYS(Tabela4[[#This Row],[Dt Inicial]],TODAY()),"") | AA60: =AND(Tabela4[[#This Row],[Status]]="Keyuser - Aguardando tarefa precedente",K59="Keyuser - Concluído ") -> FALSE
A61: ="OUT-"&IFERROR(MID(Tabela4[[#This Row],[Cenário]],SEARCH("(",Tabela4[[#This Row],[Cenário]])+1,SEARCH(")",Tabela4[[#This Row],[Cenário]])-SEARCH("(",Tabela4[[#This Row],[Cenário]])-1),"")&"_"&ROW() -> OUT-YRET_61 | B61: Não | C61: Venda Etanol Anidro F.E - Distribuidora (YRET) | D61: Realizar validação Obrigações Acessórias - TaxOne | E61: 6 | F61: Realizar validação Obrigações Acessórias - TaxOne | G61: Sergio Souza / Giovana Gonçalves | K61: Não liberado para testes | Q61: =COUNTIF(Tabela4[[#All],[Cenário]],Tabela4[[#This Row],[Cenário]]) -> 6 | R61: =COUNTIFS(Tabela4[[#All],[Cenário]],Tabela4[[#This Row],[Cenário]],Tabela4[[#All],[Status]],"Keyuser - Concluído ") -> 5 | S61: =IF(Tabela4[[#This Row],[Tarefas por Cenário]]-Tabela4[[#This Row],[Tarefas Concluídas]]>0,"Não","Sim") -> Não | T61: =COUNTIFS(Tabela4[[#All],[Cenário]],Tabela4[[#This Row],[Cenário]],Tabela4[[#All],[Status]],Tabela4[[#Headers],[Elo - Em correção ]]) -> 0 | U61: =COUNTIFS(Tabela4[[#All],[Cenário]],Tabela4[[#This Row],[Cenário]],Tabela4[[#All],[Status]],Tabela4[[#Headers],[Keyuser - Aguardando tarefa precedente]]) -> 0 | V61: =COUNTIFS(Tabela4[[#All],[Cenário]],Tabela4[[#This Row],[Cenário]],Tabela4[[#All],[Status]],Tabela4[[#Headers],[Não liberado para testes]]) -> 1 | W61: =IF(Tabela4[[#This Row],[Elo - Em correção ]]>0,"Sim","Não") -> Não | X61: =IF(Tabela4[[#This Row],[Keyuser - Aguardando tarefa precedente]]>0,"Sim","Não") -> Não | Y61: =IF(Tabela4[[#This Row],[Não liberado para testes]]>0,"Sim","Não") -> Sim | Z61: =IF(Tabela4[[#This Row],[Status]]="Keyuser - Pendente",NETWORKDAYS(Tabela4[[#This Row],[Dt Inicial]],TODAY()),"") | AA61: =AND(Tabela4[[#This Row],[Status]]="Keyuser - Aguardando tarefa precedente",K60="Keyuser - Concluído ") -> FALSE
A62: ="OUT-"&IFERROR(MID(Tabela4[[#This Row],[Cenário]],SEARCH("(",Tabela4[[#This Row],[Cenário]])+1,SEARCH(")",Tabela4[[#This Row],[Cenário]])-SEARCH("(",Tabela4[[#This Row],[Cenário]])-1),"")&"_"&ROW() -> OUT-Y002_62 | B62: Sim | C62: Venda Etanol Anidro D.E - Distribuidora (Y002) | D62: Criar ordem de venda | E62: 1 | F62: Criar ordem de venda | G62: Vania Esteves | H62: 15603630 | I62: BEP: 15597290 | J62: OK | K62: Keyuser - Concluído | L62: 45951 | N62: 45951 | Q62: =COUNTIF(Tabela4[[#All],[Cenário]],Tabela4[[#This Row],[Cenário]]) -> 8 | R62: =COUNTIFS(Tabela4[[#All],[Cenário]],Tabela4[[#This Row],[Cenário]],Tabela4[[#All],[Status]],"Keyuser - Concluído ") -> 7 | S62: =IF(Tabela4[[#This Row],[Tarefas por Cenário]]-Tabela4[[#This Row],[Tarefas Concluídas]]>0,"Não","Sim") -> Não | T62: =COUNTIFS(Tabela4[[#All],[Cenário]],Tabela4[[#This Row],[Cenário]],Tabela4[[#All],[Status]],Tabela4[[#Headers],[Elo - Em correção ]]) -> 0 | U62: =COUNTIFS(Tabela4[[#All],[Cenário]],Tabela4[[#This Row],[Cenário]],Tabela4[[#All],[Status]],Tabela4[[#Headers],[Keyuser - Aguardando tarefa precedente]]) -> 0 | V62: =COUNTIFS(Tabela4[[#All],[Cenário]],Tabela4[[#This Row],[Cenário]],Tabela4[[#All],[Status]],Tabela4[[#Headers],[Não liberado para testes]]) -> 1 | W62: =IF(Tabela4[[#This Row],[Elo - Em correção ]]>0,"Sim","Não") -> Não | X62: =IF(Tabela4[[#This Row],[Keyuser - Aguardando tarefa precedente]]>0,"Sim","Não") -> Não | Y62: =IF(Tabela4[[#This Row],[Não liberado para testes]]>0,"Sim","Não") -> Sim | Z62: =IF(Tabela4[[#This Row],[Status]]="Keyuser - Pendente",NETWORKDAYS(Tabela4[[#This Row],[Dt Inicial]],TODAY()),"") | AA62: =AND(Tabela4[[#This Row],[Status]]="Keyuser - Aguardando tarefa precedente",K61="Keyuser - Concluído ") -> FALSE
A63: ="OUT-"&IFERROR(MID(Tabela4[[#This Row],[Cenário]],SEARCH("(",Tabela4[[#This Row],[Cenário]])+1,SEARCH(")",Tabela4[[#This Row],[Cenário]])-SEARCH("(",Tabela4[[#This Row],[Cenário]])-1),"")&"_"&ROW() -> OUT-Y002_63 | B63: Sim | C63: Venda Etanol Anidro D.E - Distribuidora (Y002) | D63: Realizar validação tributária - Ordem de venda | E63: 2 | F63: Realizar validação tributária - Ordem de venda | G63: Livia Beserra | H63: 15603630 | I63: BEP: 15597290 | J63: OK | K63: Keyuser - Concluído | L63: 45951 | N63: 45951 | Q63: =COUNTIF(Tabela4[[#All],[Cenário]],Tabela4[[#This Row],[Cenário]]) -> 8 | R63: =COUNTIFS(Tabela4[[#All],[Cenário]],Tabela4[[#This Row],[Cenário]],Tabela4[[#All],[Status]],"Keyuser - Concluído ") -> 7 | S63: =IF(Tabela4[[#This Row],[Tarefas por Cenário]]-Tabela4[[#This Row],[Tarefas Concluídas]]>0,"Não","Sim") -> Não | T63: =COUNTIFS(Tabela4[[#All],[Cenário]],Tabela4[[#This Row],[Cenário]],Tabela4[[#All],[Status]],Tabela4[[#Headers],[Elo - Em correção ]]) -> 0 | U63: =COUNTIFS(Tabela4[[#All],[Cenário]],Tabela4[[#This Row],[Cenário]],Tabela4[[#All],[Status]],Tabela4[[#Headers],[Keyuser - Aguardando tarefa precedente]]) -> 0 | V63: =COUNTIFS(Tabela4[[#All],[Cenário]],Tabela4[[#This Row],[Cenário]],Tabela4[[#All],[Status]],Tabela4[[#Headers],[Não liberado para testes]]) -> 1 | W63: =IF(Tabela4[[#This Row],[Elo - Em correção ]]>0,"Sim","Não") -> Não | X63: =IF(Tabela4[[#This Row],[Keyuser - Aguardando tarefa precedente]]>0,"Sim","Não") -> Não | Y63: =IF(Tabela4[[#This Row],[Não liberado para testes]]>0,"Sim","Não") -> Sim | Z63: =IF(Tabela4[[#This Row],[Status]]="Keyuser - Pendente",NETWORKDAYS(Tabela4[[#This Row],[Dt Inicial]],TODAY()),"") | AA63: =AND(Tabela4[[#This Row],[Status]]="Keyuser - Aguardando tarefa precedente",K62="Keyuser - Concluído ") -> FALSE
A64: ="OUT-"&IFERROR(MID(Tabela4[[#This Row],[Cenário]],SEARCH("(",Tabela4[[#This Row],[Cenário]])+1,SEARCH(")",Tabela4[[#This Row],[Cenário]])-SEARCH("(",Tabela4[[#This Row],[Cenário]])-1),"")&"_"&ROW() -> OUT-Y002_64 | B64: Sim | C64: Venda Etanol Anidro D.E - Distribuidora (Y002) | D64: Liberar ordem de venda | E64: 3 | F64: Liberar ordem de venda | G64: Patrick Vianna / Aline Russo | H64: 15603630 | I64: BEP: 15597290 | J64: OK | K64: Keyuser - Concluído | L64: 45951 | N64: 45951 | Q64: =COUNTIF(Tabela4[[#All],[Cenário]],Tabela4[[#This Row],[Cenário]]) -> 8 | R64: =COUNTIFS(Tabela4[[#All],[Cenário]],Tabela4[[#This Row],[Cenário]],Tabela4[[#All],[Status]],"Keyuser - Concluído ") -> 7 | S64: =IF(Tabela4[[#This Row],[Tarefas por Cenário]]-Tabela4[[#This Row],[Tarefas Concluídas]]>0,"Não","Sim") -> Não | T64: =COUNTIFS(Tabela4[[#All],[Cenário]],Tabela4[[#This Row],[Cenário]],Tabela4[[#All],[Status]],Tabela4[[#Headers],[Elo - Em correção ]]) -> 0 | U64: =COUNTIFS(Tabela4[[#All],[Cenário]],Tabela4[[#This Row],[Cenário]],Tabela4[[#All],[Status]],Tabela4[[#Headers],[Keyuser - Aguardando tarefa precedente]]) -> 0 | V64: =COUNTIFS(Tabela4[[#All],[Cenário]],Tabela4[[#This Row],[Cenário]],Tabela4[[#All],[Status]],Tabela4[[#Headers],[Não liberado para testes]]) -> 1 | W64: =IF(Tabela4[[#This Row],[Elo - Em correção ]]>0,"Sim","Não") -> Não | X64: =IF(Tabela4[[#This Row],[Keyuser - Aguardando tarefa precedente]]>0,"Sim","Não") -> Não | Y64: =IF(Tabela4[[#This Row],[Não liberado para testes]]>0,"Sim","Não") -> Sim | Z64: =IF(Tabela4[[#This Row],[Status]]="Keyuser - Pendente",NETWORKDAYS(Tabela4[[#This Row],[Dt Inicial]],TODAY()),"") | AA64: =AND(Tabela4[[#This Row],[Status]]="Keyuser - Aguardando tarefa precedente",K63="Keyuser - Concluído ") -> FALSE
A65: ="OUT-"&IFERROR(MID(Tabela4[[#This Row],[Cenário]],SEARCH("(",Tabela4[[#This Row],[Cenário]])+1,SEARCH(")",Tabela4[[#This Row],[Cenário]])-SEARCH("(",Tabela4[[#This Row],[Cenário]])-1),"")&"_"&ROW() -> OUT-Y002_65 | B65: Sim | C65: Venda Etanol Anidro D.E - Distribuidora (Y002) | D65: Realizar faturamento | E65: 4 | F65: Realizar faturamento | G65: Francisco Netto | H65: DocNum - 46482220 | K65: Keyuser - Concluído | L65: 45951 | N65: 45951 | Q65: =COUNTIF(Tabela4[[#All],[Cenário]],Tabela4[[#This Row],[Cenário]]) -> 8 | R65: =COUNTIFS(Tabela4[[#All],[Cenário]],Tabela4[[#This Row],[Cenário]],Tabela4[[#All],[Status]],"Keyuser - Concluído ") -> 7 | S65: =IF(Tabela4[[#This Row],[Tarefas por Cenário]]-Tabela4[[#This Row],[Tarefas Concluídas]]>0,"Não","Sim") -> Não | T65: =COUNTIFS(Tabela4[[#All],[Cenário]],Tabela4[[#This Row],[Cenário]],Tabela4[[#All],[Status]],Tabela4[[#Headers],[Elo - Em correção ]]) -> 0 | U65: =COUNTIFS(Tabela4[[#All],[Cenário]],Tabela4[[#This Row],[Cenário]],Tabela4[[#All],[Status]],Tabela4[[#Headers],[Keyuser - Aguardando tarefa precedente]]) -> 0 | V65: =COUNTIFS(Tabela4[[#All],[Cenário]],Tabela4[[#This Row],[Cenário]],Tabela4[[#All],[Status]],Tabela4[[#Headers],[Não liberado para testes]]) -> 1 | W65: =IF(Tabela4[[#This Row],[Elo - Em correção ]]>0,"Sim","Não") -> Não | X65: =IF(Tabela4[[#This Row],[Keyuser - Aguardando tarefa precedente]]>0,"Sim","Não") -> Não | Y65: =IF(Tabela4[[#This Row],[Não liberado para testes]]>0,"Sim","Não") -> Sim | Z65: =IF(Tabela4[[#This Row],[Status]]="Keyuser - Pendente",NETWORKDAYS(Tabela4[[#This Row],[Dt Inicial]],TODAY()),"") | AA65: =AND(Tabela4[[#This Row],[Status]]="Keyuser - Aguardando tarefa precedente",K64="Keyuser - Concluído ") -> FALSE
A66: ="OUT-"&IFERROR(MID(Tabela4[[#This Row],[Cenário]],SEARCH("(",Tabela4[[#This Row],[Cenário]])+1,SEARCH(")",Tabela4[[#This Row],[Cenário]])-SEARCH("(",Tabela4[[#This Row],[Cenário]])-1),"")&"_"&ROW() -> OUT-Y002_66 | B66: Sim | C66: Venda Etanol Anidro D.E - Distribuidora (Y002) | D66: Realizar validação tributária - SAP, XML e DANFE | E66: 5 | F66: Realizar validação tributária - SAP (xml e DANFE) | G66: Sergio Souza / Giovana Gonçalves | H66: DocNum - 46482220 | K66: Keyuser - Concluído | L66: 45952 | N66: 45952 | Q66: =COUNTIF(Tabela4[[#All],[Cenário]],Tabela4[[#This Row],[Cenário]]) -> 8 | R66: =COUNTIFS(Tabela4[[#All],[Cenário]],Tabela4[[#This Row],[Cenário]],Tabela4[[#All],[Status]],"Keyuser - Concluído ") -> 7 | S66: =IF(Tabela4[[#This Row],[Tarefas por Cenário]]-Tabela4[[#This Row],[Tarefas Concluídas]]>0,"Não","Sim") -> Não | T66: =COUNTIFS(Tabela4[[#All],[Cenário]],Tabela4[[#This Row],[Cenário]],Tabela4[[#All],[Status]],Tabela4[[#Headers],[Elo - Em correção ]]) -> 0 | U66: =COUNTIFS(Tabela4[[#All],[Cenário]],Tabela4[[#This Row],[Cenário]],Tabela4[[#All],[Status]],Tabela4[[#Headers],[Keyuser - Aguardando tarefa precedente]]) -> 0 | V66: =COUNTIFS(Tabela4[[#All],[Cenário]],Tabela4[[#This Row],[Cenário]],Tabela4[[#All],[Status]],Tabela4[[#Headers],[Não liberado para testes]]) -> 1 | W66: =IF(Tabela4[[#This Row],[Elo - Em correção ]]>0,"Sim","Não") -> Não | X66: =IF(Tabela4[[#This Row],[Keyuser - Aguardando tarefa precedente]]>0,"Sim","Não") -> Não | Y66: =IF(Tabela4[[#This Row],[Não liberado para testes]]>0,"Sim","Não") -> Sim | Z66: =IF(Tabela4[[#This Row],[Status]]="Keyuser - Pendente",NETWORKDAYS(Tabela4[[#This Row],[Dt Inicial]],TODAY()),"") | AA66: =AND(Tabela4[[#This Row],[Status]]="Keyuser - Aguardando tarefa precedente",K65="Keyuser - Concluído ") -> FALSE
A67: ="OUT-"&IFERROR(MID(Tabela4[[#This Row],[Cenário]],SEARCH("(",Tabela4[[#This Row],[Cenário]])+1,SEARCH(")",Tabela4[[#This Row],[Cenário]])-SEARCH("(",Tabela4[[#This Row],[Cenário]])-1),"")&"_"&ROW() -> OUT-Y002_67 | B67: Sim | C67: Venda Etanol Anidro D.E - Distribuidora (Y002) | D67: Realizar validação contábil | E67: 6 | F67: Realizar validação contábil | G67: Naiara Toledo | H67: Doc Num - 46482220 | K67: Keyuser - Concluído | L67: 45952 | N67: 45952 | Q67: =COUNTIF(Tabela4[[#All],[Cenário]],Tabela4[[#This Row],[Cenário]]) -> 8 | R67: =COUNTIFS(Tabela4[[#All],[Cenário]],Tabela4[[#This Row],[Cenário]],Tabela4[[#All],[Status]],"Keyuser - Concluído ") -> 7 | S67: =IF(Tabela4[[#This Row],[Tarefas por Cenário]]-Tabela4[[#This Row],[Tarefas Concluídas]]>0,"Não","Sim") -> Não | T67: =COUNTIFS(Tabela4[[#All],[Cenário]],Tabela4[[#This Row],[Cenário]],Tabela4[[#All],[Status]],Tabela4[[#Headers],[Elo - Em correção ]]) -> 0 | U67: =COUNTIFS(Tabela4[[#All],[Cenário]],Tabela4[[#This Row],[Cenário]],Tabela4[[#All],[Status]],Tabela4[[#Headers],[Keyuser - Aguardando tarefa precedente]]) -> 0 | V67: =COUNTIFS(Tabela4[[#All],[Cenário]],Tabela4[[#This Row],[Cenário]],Tabela4[[#All],[Status]],Tabela4[[#Headers],[Não liberado para testes]]) -> 1 | W67: =IF(Tabela4[[#This Row],[Elo - Em correção ]]>0,"Sim","Não") -> Não | X67: =IF(Tabela4[[#This Row],[Keyuser - Aguardando tarefa precedente]]>0,"Sim","Não") -> Não | Y67: =IF(Tabela4[[#This Row],[Não liberado para testes]]>0,"Sim","Não") -> Sim | Z67: =IF(Tabela4[[#This Row],[Status]]="Keyuser - Pendente",NETWORKDAYS(Tabela4[[#This Row],[Dt Inicial]],TODAY()),"") | AA67: =AND(Tabela4[[#This Row],[Status]]="Keyuser - Aguardando tarefa precedente",K66="Keyuser - Concluído ") -> FALSE
A68: ="OUT-"&IFERROR(MID(Tabela4[[#This Row],[Cenário]],SEARCH("(",Tabela4[[#This Row],[Cenário]])+1,SEARCH(")",Tabela4[[#This Row],[Cenário]])-SEARCH("(",Tabela4[[#This Row],[Cenário]])-1),"")&"_"&ROW() -> OUT-Y002_68 | B68: Não | C68: Venda Etanol Anidro D.E - Distribuidora (Y002) | D68: Realizar validação Obrigações Acessórias - TaxOne | E68: 7 | F68: Realizar validação Obrigações Acessórias - TaxOne | G68: Sergio Souza / Giovana Gonçalves | K68: Não liberado para testes | Q68: =COUNTIF(Tabela4[[#All],[Cenário]],Tabela4[[#This Row],[Cenário]]) -> 8 | R68: =COUNTIFS(Tabela4[[#All],[Cenário]],Tabela4[[#This Row],[Cenário]],Tabela4[[#All],[Status]],"Keyuser - Concluído ") -> 7 | S68: =IF(Tabela4[[#This Row],[Tarefas por Cenário]]-Tabela4[[#This Row],[Tarefas Concluídas]]>0,"Não","Sim") -> Não | T68: =COUNTIFS(Tabela4[[#All],[Cenário]],Tabela4[[#This Row],[Cenário]],Tabela4[[#All],[Status]],Tabela4[[#Headers],[Elo - Em correção ]]) -> 0 | U68: =COUNTIFS(Tabela4[[#All],[Cenário]],Tabela4[[#This Row],[Cenário]],Tabela4[[#All],[Status]],Tabela4[[#Headers],[Keyuser - Aguardando tarefa precedente]]) -> 0 | V68: =COUNTIFS(Tabela4[[#All],[Cenário]],Tabela4[[#This Row],[Cenário]],Tabela4[[#All],[Status]],Tabela4[[#Headers],[Não liberado para testes]]) -> 1 | W68: =IF(Tabela4[[#This Row],[Elo - Em correção ]]>0,"Sim","Não") -> Não | X68: =IF(Tabela4[[#This Row],[Keyuser - Aguardando tarefa precedente]]>0,"Sim","Não") -> Não | Y68: =IF(Tabela4[[#This Row],[Não liberado para testes]]>0,"Sim","Não") -> Sim | Z68: =IF(Tabela4[[#This Row],[Status]]="Keyuser - Pendente",NETWORKDAYS(Tabela4[[#This Row],[Dt Inicial]],TODAY()),"") | AA68: =AND(Tabela4[[#This Row],[Status]]="Keyuser - Aguardando tarefa precedente",K67="Keyuser - Concluído ") -> FALSE
A69: ="OUT-"&IFERROR(MID(Tabela4[[#This Row],[Cenário]],SEARCH("(",Tabela4[[#This Row],[Cenário]])+1,SEARCH(")",Tabela4[[#This Row],[Cenário]])-SEARCH("(",Tabela4[[#This Row],[Cenário]])-1),"")&"_"&ROW() -> OUT-Y002_69 | B69: Sim | C69: Venda Etanol Anidro D.E - Distribuidora (Y002) | D69: Realizar validação Títulos Financeiros | E69: 8 | F69: Realizar validação Títulos Financeiros | G69: Patrick Vianna / Aline Russo | H69: 15603630 | I69: BEP: 15597290 | J69: OK | K69: Keyuser - Concluído | L69: 45952 | N69: 45952 | Q69: =COUNTIF(Tabela4[[#All],[Cenário]],Tabela4[[#This Row],[Cenário]]) -> 8 | R69: =COUNTIFS(Tabela4[[#All],[Cenário]],Tabela4[[#This Row],[Cenário]],Tabela4[[#All],[Status]],"Keyuser - Concluído ") -> 7 | S69: =IF(Tabela4[[#This Row],[Tarefas por Cenário]]-Tabela4[[#This Row],[Tarefas Concluídas]]>0,"Não","Sim") -> Não | T69: =COUNTIFS(Tabela4[[#All],[Cenário]],Tabela4[[#This Row],[Cenário]],Tabela4[[#All],[Status]],Tabela4[[#Headers],[Elo - Em correção ]]) -> 0 | U69: =COUNTIFS(Tabela4[[#All],[Cenário]],Tabela4[[#This Row],[Cenário]],Tabela4[[#All],[Status]],Tabela4[[#Headers],[Keyuser - Aguardando tarefa precedente]]) -> 0 | V69: =COUNTIFS(Tabela4[[#All],[Cenário]],Tabela4[[#This Row],[Cenário]],Tabela4[[#All],[Status]],Tabela4[[#Headers],[Não liberado para testes]]) -> 1 | W69: =IF(Tabela4[[#This Row],[Elo - Em correção ]]>0,"Sim","Não") -> Não | X69: =IF(Tabela4[[#This Row],[Keyuser - Aguardando tarefa precedente]]>0,"Sim","Não") -> Não | Y69: =IF(Tabela4[[#This Row],[Não liberado para testes]]>0,"Sim","Não") -> Sim | Z69: =IF(Tabela4[[#This Row],[Status]]="Keyuser - Pendente",NETWORKDAYS(Tabela4[[#This Row],[Dt Inicial]],TODAY()),"") | AA69: =AND(Tabela4[[#This Row],[Status]]="Keyuser - Aguardando tarefa precedente",K68="Keyuser - Concluído ") -> FALSE
A70: ="OUT-"&IFERROR(MID(Tabela4[[#This Row],[Cenário]],SEARCH("(",Tabela4[[#This Row],[Cenário]])+1,SEARCH(")",Tabela4[[#This Row],[Cenário]])-SEARCH("(",Tabela4[[#This Row],[Cenário]])-1),"")&"_"&ROW() -> OUT-YDEV_70 | B70: Sim | C70: Venda Etanol Anidro D.E - Distribuidora (YDEV) | D70: Criar ordem de venda | E70: 1 | F70: Criar ordem de venda | G70: Marcos Nunes | H70: 60668332 | K70: Keyuser - Concluído | L70: 45958 | N70: 45958 | Q70: =COUNTIF(Tabela4[[#All],[Cenário]],Tabela4[[#This Row],[Cenário]]) -> 6 | R70: =COUNTIFS(Tabela4[[#All],[Cenário]],Tabela4[[#This Row],[Cenário]],Tabela4[[#All],[Status]],"Keyuser - Concluído ") -> 5 | S70: =IF(Tabela4[[#This Row],[Tarefas por Cenário]]-Tabela4[[#This Row],[Tarefas Concluídas]]>0,"Não","Sim") -> Não | T70: =COUNTIFS(Tabela4[[#All],[Cenário]],Tabela4[[#This Row],[Cenário]],Tabela4[[#All],[Status]],Tabela4[[#Headers],[Elo - Em correção ]]) -> 0 | U70: =COUNTIFS(Tabela4[[#All],[Cenário]],Tabela4[[#This Row],[Cenário]],Tabela4[[#All],[Status]],Tabela4[[#Headers],[Keyuser - Aguardando tarefa precedente]]) -> 0 | V70: =COUNTIFS(Tabela4[[#All],[Cenário]],Tabela4[[#This Row],[Cenário]],Tabela4[[#All],[Status]],Tabela4[[#Headers],[Não liberado para testes]]) -> 1 | W70: =IF(Tabela4[[#This Row],[Elo - Em correção ]]>0,"Sim","Não") -> Não | X70: =IF(Tabela4[[#This Row],[Keyuser - Aguardando tarefa precedente]]>0,"Sim","Não") -> Não | Y70: =IF(Tabela4[[#This Row],[Não liberado para testes]]>0,"Sim","Não") -> Sim | Z70: =IF(Tabela4[[#This Row],[Status]]="Keyuser - Pendente",NETWORKDAYS(Tabela4[[#This Row],[Dt Inicial]],TODAY()),"") | AA70: =AND(Tabela4[[#This Row],[Status]]="Keyuser - Aguardando tarefa precedente",K69="Keyuser - Concluído ") -> FALSE
A71: ="OUT-"&IFERROR(MID(Tabela4[[#This Row],[Cenário]],SEARCH("(",Tabela4[[#This Row],[Cenário]])+1,SEARCH(")",Tabela4[[#This Row],[Cenário]])-SEARCH("(",Tabela4[[#This Row],[Cenário]])-1),"")&"_"&ROW() -> OUT-YDEV_71 | B71: Sim | C71: Venda Etanol Anidro D.E - Distribuidora (YDEV) | D71: Realizar validação tributária - Ordem de venda | E71: 2 | F71: Realizar validação tributária - Ordem de venda | G71: Livia Beserra | H71: 60668332 | K71: Keyuser - Concluído | L71: 45958 | N71: 45958 | Q71: =COUNTIF(Tabela4[[#All],[Cenário]],Tabela4[[#This Row],[Cenário]]) -> 6 | R71: =COUNTIFS(Tabela4[[#All],[Cenário]],Tabela4[[#This Row],[Cenário]],Tabela4[[#All],[Status]],"Keyuser - Concluído ") -> 5 | S71: =IF(Tabela4[[#This Row],[Tarefas por Cenário]]-Tabela4[[#This Row],[Tarefas Concluídas]]>0,"Não","Sim") -> Não | T71: =COUNTIFS(Tabela4[[#All],[Cenário]],Tabela4[[#This Row],[Cenário]],Tabela4[[#All],[Status]],Tabela4[[#Headers],[Elo - Em correção ]]) -> 0 | U71: =COUNTIFS(Tabela4[[#All],[Cenário]],Tabela4[[#This Row],[Cenário]],Tabela4[[#All],[Status]],Tabela4[[#Headers],[Keyuser - Aguardando tarefa precedente]]) -> 0 | V71: =COUNTIFS(Tabela4[[#All],[Cenário]],Tabela4[[#This Row],[Cenário]],Tabela4[[#All],[Status]],Tabela4[[#Headers],[Não liberado para testes]]) -> 1 | W71: =IF(Tabela4[[#This Row],[Elo - Em correção ]]>0,"Sim","Não") -> Não | X71: =IF(Tabela4[[#This Row],[Keyuser - Aguardando tarefa precedente]]>0,"Sim","Não") -> Não | Y71: =IF(Tabela4[[#This Row],[Não liberado para testes]]>0,"Sim","Não") -> Sim | Z71: =IF(Tabela4[[#This Row],[Status]]="Keyuser - Pendente",NETWORKDAYS(Tabela4[[#This Row],[Dt Inicial]],TODAY()),"") | AA71: =AND(Tabela4[[#This Row],[Status]]="Keyuser - Aguardando tarefa precedente",K70="Keyuser - Concluído ") -> FALSE
A72: ="OUT-"&IFERROR(MID(Tabela4[[#This Row],[Cenário]],SEARCH("(",Tabela4[[#This Row],[Cenário]])+1,SEARCH(")",Tabela4[[#This Row],[Cenário]])-SEARCH("(",Tabela4[[#This Row],[Cenário]])-1),"")&"_"&ROW() -> OUT-YDEV_72 | B72: Sim | C72: Venda Etanol Anidro D.E - Distribuidora (YDEV) | D72: Realizar faturamento | E72: 3 | F72: Realizar faturamento | G72: Marcos Nunes | H72: DocNum - 46482287 | K72: Keyuser - Concluído | L72: 45959 | N72: 45959 | O72: Nota nr 367457 | Q72: =COUNTIF(Tabela4[[#All],[Cenário]],Tabela4[[#This Row],[Cenário]]) -> 6 | R72: =COUNTIFS(Tabela4[[#All],[Cenário]],Tabela4[[#This Row],[Cenário]],Tabela4[[#All],[Status]],"Keyuser - Concluído ") -> 5 | S72: =IF(Tabela4[[#This Row],[Tarefas por Cenário]]-Tabela4[[#This Row],[Tarefas Concluídas]]>0,"Não","Sim") -> Não | T72: =COUNTIFS(Tabela4[[#All],[Cenário]],Tabela4[[#This Row],[Cenário]],Tabela4[[#All],[Status]],Tabela4[[#Headers],[Elo - Em correção ]]) -> 0 | U72: =COUNTIFS(Tabela4[[#All],[Cenário]],Tabela4[[#This Row],[Cenário]],Tabela4[[#All],[Status]],Tabela4[[#Headers],[Keyuser - Aguardando tarefa precedente]]) -> 0 | V72: =COUNTIFS(Tabela4[[#All],[Cenário]],Tabela4[[#This Row],[Cenário]],Tabela4[[#All],[Status]],Tabela4[[#Headers],[Não liberado para testes]]) -> 1 | W72: =IF(Tabela4[[#This Row],[Elo - Em correção ]]>0,"Sim","Não") -> Não | X72: =IF(Tabela4[[#This Row],[Keyuser - Aguardando tarefa precedente]]>0,"Sim","Não") -> Não | Y72: =IF(Tabela4[[#This Row],[Não liberado para testes]]>0,"Sim","Não") -> Sim | Z72: =IF(Tabela4[[#This Row],[Status]]="Keyuser - Pendente",NETWORKDAYS(Tabela4[[#This Row],[Dt Inicial]],TODAY()),"") | AA72: =AND(Tabela4[[#This Row],[Status]]="Keyuser - Aguardando tarefa precedente",K71="Keyuser - Concluído ") -> FALSE
A73: ="OUT-"&IFERROR(MID(Tabela4[[#This Row],[Cenário]],SEARCH("(",Tabela4[[#This Row],[Cenário]])+1,SEARCH(")",Tabela4[[#This Row],[Cenário]])-SEARCH("(",Tabela4[[#This Row],[Cenário]])-1),"")&"_"&ROW() -> OUT-YDEV_73 | B73: Sim | C73: Venda Etanol Anidro D.E - Distribuidora (YDEV) | D73: Realizar validação tributária - SAP, XML e DANFE | E73: 4 | F73: Realizar validação tributária - SAP (xml e DANFE) | G73: Sergio Souza / Giovana Gonçalves | H73: DocNum - 46482287 | K73: Keyuser - Concluído | L73: 45959 | N73: 45959 | Q73: =COUNTIF(Tabela4[[#All],[Cenário]],Tabela4[[#This Row],[Cenário]]) -> 6 | R73: =COUNTIFS(Tabela4[[#All],[Cenário]],Tabela4[[#This Row],[Cenário]],Tabela4[[#All],[Status]],"Keyuser - Concluído ") -> 5 | S73: =IF(Tabela4[[#This Row],[Tarefas por Cenário]]-Tabela4[[#This Row],[Tarefas Concluídas]]>0,"Não","Sim") -> Não | T73: =COUNTIFS(Tabela4[[#All],[Cenário]],Tabela4[[#This Row],[Cenário]],Tabela4[[#All],[Status]],Tabela4[[#Headers],[Elo - Em correção ]]) -> 0 | U73: =COUNTIFS(Tabela4[[#All],[Cenário]],Tabela4[[#This Row],[Cenário]],Tabela4[[#All],[Status]],Tabela4[[#Headers],[Keyuser - Aguardando tarefa precedente]]) -> 0 | V73: =COUNTIFS(Tabela4[[#All],[Cenário]],Tabela4[[#This Row],[Cenário]],Tabela4[[#All],[Status]],Tabela4[[#Headers],[Não liberado para testes]]) -> 1 | W73: =IF(Tabela4[[#This Row],[Elo - Em correção ]]>0,"Sim","Não") -> Não | X73: =IF(Tabela4[[#This Row],[Keyuser - Aguardando tarefa precedente]]>0,"Sim","Não") -> Não | Y73: =IF(Tabela4[[#This Row],[Não liberado para testes]]>0,"Sim","Não") -> Sim | Z73: =IF(Tabela4[[#This Row],[Status]]="Keyuser - Pendente",NETWORKDAYS(Tabela4[[#This Row],[Dt Inicial]],TODAY()),"") | AA73: =AND(Tabela4[[#This Row],[Status]]="Keyuser - Aguardando tarefa precedente",K72="Keyuser - Concluído ") -> FALSE
A74: ="OUT-"&IFERROR(MID(Tabela4[[#This Row],[Cenário]],SEARCH("(",Tabela4[[#This Row],[Cenário]])+1,SEARCH(")",Tabela4[[#This Row],[Cenário]])-SEARCH("(",Tabela4[[#This Row],[Cenário]])-1),"")&"_"&ROW() -> OUT-YDEV_74 | B74: Sim | C74: Venda Etanol Anidro D.E - Distribuidora (YDEV) | D74: Realizar validação contábil | E74: 5 | F74: Realizar validação contábil | G74: Naiara Toledo | H74: DocNum - 46482287 | K74: Keyuser - Concluído | L74: 45960 | N74: 45960 | Q74: =COUNTIF(Tabela4[[#All],[Cenário]],Tabela4[[#This Row],[Cenário]]) -> 6 | R74: =COUNTIFS(Tabela4[[#All],[Cenário]],Tabela4[[#This Row],[Cenário]],Tabela4[[#All],[Status]],"Keyuser - Concluído ") -> 5 | S74: =IF(Tabela4[[#This Row],[Tarefas por Cenário]]-Tabela4[[#This Row],[Tarefas Concluídas]]>0,"Não","Sim") -> Não | T74: =COUNTIFS(Tabela4[[#All],[Cenário]],Tabela4[[#This Row],[Cenário]],Tabela4[[#All],[Status]],Tabela4[[#Headers],[Elo - Em correção ]]) -> 0 | U74: =COUNTIFS(Tabela4[[#All],[Cenário]],Tabela4[[#This Row],[Cenário]],Tabela4[[#All],[Status]],Tabela4[[#Headers],[Keyuser - Aguardando tarefa precedente]]) -> 0 | V74: =COUNTIFS(Tabela4[[#All],[Cenário]],Tabela4[[#This Row],[Cenário]],Tabela4[[#All],[Status]],Tabela4[[#Headers],[Não liberado para testes]]) -> 1 | W74: =IF(Tabela4[[#This Row],[Elo - Em correção ]]>0,"Sim","Não") -> Não | X74: =IF(Tabela4[[#This Row],[Keyuser - Aguardando tarefa precedente]]>0,"Sim","Não") -> Não | Y74: =IF(Tabela4[[#This Row],[Não liberado para testes]]>0,"Sim","Não") -> Sim | Z74: =IF(Tabela4[[#This Row],[Status]]="Keyuser - Pendente",NETWORKDAYS(Tabela4[[#This Row],[Dt Inicial]],TODAY()),"") | AA74: =AND(Tabela4[[#This Row],[Status]]="Keyuser - Aguardando tarefa precedente",K73="Keyuser - Concluído ") -> FALSE
A75: ="OUT-"&IFERROR(MID(Tabela4[[#This Row],[Cenário]],SEARCH("(",Tabela4[[#This Row],[Cenário]])+1,SEARCH(")",Tabela4[[#This Row],[Cenário]])-SEARCH("(",Tabela4[[#This Row],[Cenário]])-1),"")&"_"&ROW() -> OUT-YDEV_75 | B75: Não | C75: Venda Etanol Anidro D.E - Distribuidora (YDEV) | D75: Realizar validação Obrigações Acessórias - TaxOne | E75: 6 | F75: Realizar validação Obrigações Acessórias - TaxOne | G75: Sergio Souza / Giovana Gonçalves | K75: Não liberado para testes | Q75: =COUNTIF(Tabela4[[#All],[Cenário]],Tabela4[[#This Row],[Cenário]]) -> 6 | R75: =COUNTIFS(Tabela4[[#All],[Cenário]],Tabela4[[#This Row],[Cenário]],Tabela4[[#All],[Status]],"Keyuser - Concluído ") -> 5 | S75: =IF(Tabela4[[#This Row],[Tarefas por Cenário]]-Tabela4[[#This Row],[Tarefas Concluídas]]>0,"Não","Sim") -> Não | T75: =COUNTIFS(Tabela4[[#All],[Cenário]],Tabela4[[#This Row],[Cenário]],Tabela4[[#All],[Status]],Tabela4[[#Headers],[Elo - Em correção ]]) -> 0 | U75: =COUNTIFS(Tabela4[[#All],[Cenário]],Tabela4[[#This Row],[Cenário]],Tabela4[[#All],[Status]],Tabela4[[#Headers],[Keyuser - Aguardando tarefa precedente]]) -> 0 | V75: =COUNTIFS(Tabela4[[#All],[Cenário]],Tabela4[[#This Row],[Cenário]],Tabela4[[#All],[Status]],Tabela4[[#Headers],[Não liberado para testes]]) -> 1 | W75: =IF(Tabela4[[#This Row],[Elo - Em correção ]]>0,"Sim","Não") -> Não | X75: =IF(Tabela4[[#This Row],[Keyuser - Aguardando tarefa precedente]]>0,"Sim","Não") -> Não | Y75: =IF(Tabela4[[#This Row],[Não liberado para testes]]>0,"Sim","Não") -> Sim | Z75: =IF(Tabela4[[#This Row],[Status]]="Keyuser - Pendente",NETWORKDAYS(Tabela4[[#This Row],[Dt Inicial]],TODAY()),"") | AA75: =AND(Tabela4[[#This Row],[Status]]="Keyuser - Aguardando tarefa precedente",K74="Keyuser - Concluído ") -> FALSE
A76: ="OUT-"&IFERROR(MID(Tabela4[[#This Row],[Cenário]],SEARCH("(",Tabela4[[#This Row],[Cenário]])+1,SEARCH(")",Tabela4[[#This Row],[Cenário]])-SEARCH("(",Tabela4[[#This Row],[Cenário]])-1),"")&"_"&ROW() -> OUT-YRET_76 | B76: Sim | C76: Venda Etanol Anidro D.E - Distribuidora (YRET) | D76: Criar ordem de venda | E76: 1 | F76: Criar ordem de venda | G76: Marcos Nunes | H76: 60668339 | K76: Keyuser - Concluído | L76: 45958 | N76: 45958 | Q76: =COUNTIF(Tabela4[[#All],[Cenário]],Tabela4[[#This Row],[Cenário]]) -> 6 | R76: =COUNTIFS(Tabela4[[#All],[Cenário]],Tabela4[[#This Row],[Cenário]],Tabela4[[#All],[Status]],"Keyuser - Concluído ") -> 5 | S76: =IF(Tabela4[[#This Row],[Tarefas por Cenário]]-Tabela4[[#This Row],[Tarefas Concluídas]]>0,"Não","Sim") -> Não | T76: =COUNTIFS(Tabela4[[#All],[Cenário]],Tabela4[[#This Row],[Cenário]],Tabela4[[#All],[Status]],Tabela4[[#Headers],[Elo - Em correção ]]) -> 0 | U76: =COUNTIFS(Tabela4[[#All],[Cenário]],Tabela4[[#This Row],[Cenário]],Tabela4[[#All],[Status]],Tabela4[[#Headers],[Keyuser - Aguardando tarefa precedente]]) -> 0 | V76: =COUNTIFS(Tabela4[[#All],[Cenário]],Tabela4[[#This Row],[Cenário]],Tabela4[[#All],[Status]],Tabela4[[#Headers],[Não liberado para testes]]) -> 1 | W76: =IF(Tabela4[[#This Row],[Elo - Em correção ]]>0,"Sim","Não") -> Não | X76: =IF(Tabela4[[#This Row],[Keyuser - Aguardando tarefa precedente]]>0,"Sim","Não") -> Não | Y76: =IF(Tabela4[[#This Row],[Não liberado para testes]]>0,"Sim","Não") -> Sim | Z76: =IF(Tabela4[[#This Row],[Status]]="Keyuser - Pendente",NETWORKDAYS(Tabela4[[#This Row],[Dt Inicial]],TODAY()),"") | AA76: =AND(Tabela4[[#This Row],[Status]]="Keyuser - Aguardando tarefa precedente",K75="Keyuser - Concluído ") -> FALSE
A77: ="OUT-"&IFERROR(MID(Tabela4[[#This Row],[Cenário]],SEARCH("(",Tabela4[[#This Row],[Cenário]])+1,SEARCH(")",Tabela4[[#This Row],[Cenário]])-SEARCH("(",Tabela4[[#This Row],[Cenário]])-1),"")&"_"&ROW() -> OUT-YRET_77 | B77: Sim | C77: Venda Etanol Anidro D.E - Distribuidora (YRET) | D77: Realizar validação tributária - Ordem de venda | E77: 2 | F77: Realizar validação tributária - Ordem de venda | G77: Livia Beserra | H77: 60668339 | K77: Keyuser - Concluído | L77: 45958 | N77: 45958 | Q77: =COUNTIF(Tabela4[[#All],[Cenário]],Tabela4[[#This Row],[Cenário]]) -> 6 | R77: =COUNTIFS(Tabela4[[#All],[Cenário]],Tabela4[[#This Row],[Cenário]],Tabela4[[#All],[Status]],"Keyuser - Concluído ") -> 5 | S77: =IF(Tabela4[[#This Row],[Tarefas por Cenário]]-Tabela4[[#This Row],[Tarefas Concluídas]]>0,"Não","Sim") -> Não | T77: =COUNTIFS(Tabela4[[#All],[Cenário]],Tabela4[[#This Row],[Cenário]],Tabela4[[#All],[Status]],Tabela4[[#Headers],[Elo - Em correção ]]) -> 0 | U77: =COUNTIFS(Tabela4[[#All],[Cenário]],Tabela4[[#This Row],[Cenário]],Tabela4[[#All],[Status]],Tabela4[[#Headers],[Keyuser - Aguardando tarefa precedente]]) -> 0 | V77: =COUNTIFS(Tabela4[[#All],[Cenário]],Tabela4[[#This Row],[Cenário]],Tabela4[[#All],[Status]],Tabela4[[#Headers],[Não liberado para testes]]) -> 1 | W77: =IF(Tabela4[[#This Row],[Elo - Em correção ]]>0,"Sim","Não") -> Não | X77: =IF(Tabela4[[#This Row],[Keyuser - Aguardando tarefa precedente]]>0,"Sim","Não") -> Não | Y77: =IF(Tabela4[[#This Row],[Não liberado para testes]]>0,"Sim","Não") -> Sim | Z77: =IF(Tabela4[[#This Row],[Status]]="Keyuser - Pendente",NETWORKDAYS(Tabela4[[#This Row],[Dt Inicial]],TODAY()),"") | AA77: =AND(Tabela4[[#This Row],[Status]]="Keyuser - Aguardando tarefa precedente",K76="Keyuser - Concluído ") -> FALSE
A78: ="OUT-"&IFERROR(MID(Tabela4[[#This Row],[Cenário]],SEARCH("(",Tabela4[[#This Row],[Cenário]])+1,SEARCH(")",Tabela4[[#This Row],[Cenário]])-SEARCH("(",Tabela4[[#This Row],[Cenário]])-1),"")&"_"&ROW() -> OUT-YRET_78 | B78: Sim | C78: Venda Etanol Anidro D.E - Distribuidora (YRET) | D78: Realizar faturamento | E78: 3 | F78: Realizar faturamento | G78: Marcos Nunes | H78: DocNum - 46482295 | K78: Keyuser - Concluído | L78: 45959 | N78: 45959 | O78: Nota nr 3458 | Q78: =COUNTIF(Tabela4[[#All],[Cenário]],Tabela4[[#This Row],[Cenário]]) -> 6 | R78: =COUNTIFS(Tabela4[[#All],[Cenário]],Tabela4[[#This Row],[Cenário]],Tabela4[[#All],[Status]],"Keyuser - Concluído ") -> 5 | S78: =IF(Tabela4[[#This Row],[Tarefas por Cenário]]-Tabela4[[#This Row],[Tarefas Concluídas]]>0,"Não","Sim") -> Não | T78: =COUNTIFS(Tabela4[[#All],[Cenário]],Tabela4[[#This Row],[Cenário]],Tabela4[[#All],[Status]],Tabela4[[#Headers],[Elo - Em correção ]]) -> 0 | U78: =COUNTIFS(Tabela4[[#All],[Cenário]],Tabela4[[#This Row],[Cenário]],Tabela4[[#All],[Status]],Tabela4[[#Headers],[Keyuser - Aguardando tarefa precedente]]) -> 0 | V78: =COUNTIFS(Tabela4[[#All],[Cenário]],Tabela4[[#This Row],[Cenário]],Tabela4[[#All],[Status]],Tabela4[[#Headers],[Não liberado para testes]]) -> 1 | W78: =IF(Tabela4[[#This Row],[Elo - Em correção ]]>0,"Sim","Não") -> Não | X78: =IF(Tabela4[[#This Row],[Keyuser - Aguardando tarefa precedente]]>0,"Sim","Não") -> Não | Y78: =IF(Tabela4[[#This Row],[Não liberado para testes]]>0,"Sim","Não") -> Sim | Z78: =IF(Tabela4[[#This Row],[Status]]="Keyuser - Pendente",NETWORKDAYS(Tabela4[[#This Row],[Dt Inicial]],TODAY()),"") | AA78: =AND(Tabela4[[#This Row],[Status]]="Keyuser - Aguardando tarefa precedente",K77="Keyuser - Concluído ") -> FALSE
A79: ="OUT-"&IFERROR(MID(Tabela4[[#This Row],[Cenário]],SEARCH("(",Tabela4[[#This Row],[Cenário]])+1,SEARCH(")",Tabela4[[#This Row],[Cenário]])-SEARCH("(",Tabela4[[#This Row],[Cenário]])-1),"")&"_"&ROW() -> OUT-YRET_79 | B79: Sim | C79: Venda Etanol Anidro D.E - Distribuidora (YRET) | D79: Realizar validação tributária - SAP, XML e DANFE | E79: 4 | F79: Realizar validação tributária - SAP (xml e DANFE) | G79: Sergio Souza / Giovana Gonçalves | H79: DocNum - 46482295 | K79: Keyuser - Concluído | L79: 45960 | N79: 45960 | Q79: =COUNTIF(Tabela4[[#All],[Cenário]],Tabela4[[#This Row],[Cenário]]) -> 6 | R79: =COUNTIFS(Tabela4[[#All],[Cenário]],Tabela4[[#This Row],[Cenário]],Tabela4[[#All],[Status]],"Keyuser - Concluído ") -> 5 | S79: =IF(Tabela4[[#This Row],[Tarefas por Cenário]]-Tabela4[[#This Row],[Tarefas Concluídas]]>0,"Não","Sim") -> Não | T79: =COUNTIFS(Tabela4[[#All],[Cenário]],Tabela4[[#This Row],[Cenário]],Tabela4[[#All],[Status]],Tabela4[[#Headers],[Elo - Em correção ]]) -> 0 | U79: =COUNTIFS(Tabela4[[#All],[Cenário]],Tabela4[[#This Row],[Cenário]],Tabela4[[#All],[Status]],Tabela4[[#Headers],[Keyuser - Aguardando tarefa precedente]]) -> 0 | V79: =COUNTIFS(Tabela4[[#All],[Cenário]],Tabela4[[#This Row],[Cenário]],Tabela4[[#All],[Status]],Tabela4[[#Headers],[Não liberado para testes]]) -> 1 | W79: =IF(Tabela4[[#This Row],[Elo - Em correção ]]>0,"Sim","Não") -> Não | X79: =IF(Tabela4[[#This Row],[Keyuser - Aguardando tarefa precedente]]>0,"Sim","Não") -> Não | Y79: =IF(Tabela4[[#This Row],[Não liberado para testes]]>0,"Sim","Não") -> Sim | Z79: =IF(Tabela4[[#This Row],[Status]]="Keyuser - Pendente",NETWORKDAYS(Tabela4[[#This Row],[Dt Inicial]],TODAY()),"") | AA79: =AND(Tabela4[[#This Row],[Status]]="Keyuser - Aguardando tarefa precedente",K78="Keyuser - Concluído ") -> FALSE
A80: ="OUT-"&IFERROR(MID(Tabela4[[#This Row],[Cenário]],SEARCH("(",Tabela4[[#This Row],[Cenário]])+1,SEARCH(")",Tabela4[[#This Row],[Cenário]])-SEARCH("(",Tabela4[[#This Row],[Cenário]])-1),"")&"_"&ROW() -> OUT-YRET_80 | B80: Sim | C80: Venda Etanol Anidro D.E - Distribuidora (YRET) | D80: Realizar validação contábil | E80: 5 | F80: Realizar validação contábil | G80: Naiara Toledo | H80: DocNum - 46482295 | K80: Keyuser - Concluído | L80: 45960 | N80: 45960 | Q80: =COUNTIF(Tabela4[[#All],[Cenário]],Tabela4[[#This Row],[Cenário]]) -> 6 | R80: =COUNTIFS(Tabela4[[#All],[Cenário]],Tabela4[[#This Row],[Cenário]],Tabela4[[#All],[Status]],"Keyuser - Concluído ") -> 5 | S80: =IF(Tabela4[[#This Row],[Tarefas por Cenário]]-Tabela4[[#This Row],[Tarefas Concluídas]]>0,"Não","Sim") -> Não | T80: =COUNTIFS(Tabela4[[#All],[Cenário]],Tabela4[[#This Row],[Cenário]],Tabela4[[#All],[Status]],Tabela4[[#Headers],[Elo - Em correção ]]) -> 0 | U80: =COUNTIFS(Tabela4[[#All],[Cenário]],Tabela4[[#This Row],[Cenário]],Tabela4[[#All],[Status]],Tabela4[[#Headers],[Keyuser - Aguardando tarefa precedente]]) -> 0 | V80: =COUNTIFS(Tabela4[[#All],[Cenário]],Tabela4[[#This Row],[Cenário]],Tabela4[[#All],[Status]],Tabela4[[#Headers],[Não liberado para testes]]) -> 1 | W80: =IF(Tabela4[[#This Row],[Elo - Em correção ]]>0,"Sim","Não") -> Não | X80: =IF(Tabela4[[#This Row],[Keyuser - Aguardando tarefa precedente]]>0,"Sim","Não") -> Não | Y80: =IF(Tabela4[[#This Row],[Não liberado para testes]]>0,"Sim","Não") -> Sim | Z80: =IF(Tabela4[[#This Row],[Status]]="Keyuser - Pendente",NETWORKDAYS(Tabela4[[#This Row],[Dt Inicial]],TODAY()),"") | AA80: =AND(Tabela4[[#This Row],[Status]]="Keyuser - Aguardando tarefa precedente",K79="Keyuser - Concluído ") -> FALSE
A81: ="OUT-"&IFERROR(MID(Tabela4[[#This Row],[Cenário]],SEARCH("(",Tabela4[[#This Row],[Cenário]])+1,SEARCH(")",Tabela4[[#This Row],[Cenário]])-SEARCH("(",Tabela4[[#This Row],[Cenário]])-1),"")&"_"&ROW() -> OUT-YRET_81 | B81: Não | C81: Venda Etanol Anidro D.E - Distribuidora (YRET) | D81: Realizar validação Obrigações Acessórias - TaxOne | E81: 6 | F81: Realizar validação Obrigações Acessórias - TaxOne | G81: Sergio Souza / Giovana Gonçalves | K81: Não liberado para testes | Q81: =COUNTIF(Tabela4[[#All],[Cenário]],Tabela4[[#This Row],[Cenário]]) -> 6 | R81: =COUNTIFS(Tabela4[[#All],[Cenário]],Tabela4[[#This Row],[Cenário]],Tabela4[[#All],[Status]],"Keyuser - Concluído ") -> 5 | S81: =IF(Tabela4[[#This Row],[Tarefas por Cenário]]-Tabela4[[#This Row],[Tarefas Concluídas]]>0,"Não","Sim") -> Não | T81: =COUNTIFS(Tabela4[[#All],[Cenário]],Tabela4[[#This Row],[Cenário]],Tabela4[[#All],[Status]],Tabela4[[#Headers],[Elo - Em correção ]]) -> 0 | U81: =COUNTIFS(Tabela4[[#All],[Cenário]],Tabela4[[#This Row],[Cenário]],Tabela4[[#All],[Status]],Tabela4[[#Headers],[Keyuser - Aguardando tarefa precedente]]) -> 0 | V81: =COUNTIFS(Tabela4[[#All],[Cenário]],Tabela4[[#This Row],[Cenário]],Tabela4[[#All],[Status]],Tabela4[[#Headers],[Não liberado para testes]]) -> 1 | W81: =IF(Tabela4[[#This Row],[Elo - Em correção ]]>0,"Sim","Não") -> Não | X81: =IF(Tabela4[[#This Row],[Keyuser - Aguardando tarefa precedente]]>0,"Sim","Não") -> Não | Y81: =IF(Tabela4[[#This Row],[Não liberado para testes]]>0,"Sim","Não") -> Sim | Z81: =IF(Tabela4[[#This Row],[Status]]="Keyuser - Pendente",NETWORKDAYS(Tabela4[[#This Row],[Dt Inicial]],TODAY()),"") | AA81: =AND(Tabela4[[#This Row],[Status]]="Keyuser - Aguardando tarefa precedente",K80="Keyuser - Concluído ") -> FALSE
A82: ="OUT-"&IFERROR(MID(Tabela4[[#This Row],[Cenário]],SEARCH("(",Tabela4[[#This Row],[Cenário]])+1,SEARCH(")",Tabela4[[#This Row],[Cenário]])-SEARCH("(",Tabela4[[#This Row],[Cenário]])-1),"")&"_"&ROW() -> OUT-Y002_82 | B82: Sim | C82: Venda Etanol Anidro F.E - Comercializadora (Y002) | D82: Criar ordem de venda | E82: 1 | F82: Criar ordem de venda | G82: Vania Esteves | H82: 15603606 | I82: NT | K82: Keyuser - Concluído | L82: 45946 | N82: 45946 | Q82: =COUNTIF(Tabela4[[#All],[Cenário]],Tabela4[[#This Row],[Cenário]]) -> 8 | R82: =COUNTIFS(Tabela4[[#All],[Cenário]],Tabela4[[#This Row],[Cenário]],Tabela4[[#All],[Status]],"Keyuser - Concluído ") -> 7 | S82: =IF(Tabela4[[#This Row],[Tarefas por Cenário]]-Tabela4[[#This Row],[Tarefas Concluídas]]>0,"Não","Sim") -> Não | T82: =COUNTIFS(Tabela4[[#All],[Cenário]],Tabela4[[#This Row],[Cenário]],Tabela4[[#All],[Status]],Tabela4[[#Headers],[Elo - Em correção ]]) -> 0 | U82: =COUNTIFS(Tabela4[[#All],[Cenário]],Tabela4[[#This Row],[Cenário]],Tabela4[[#All],[Status]],Tabela4[[#Headers],[Keyuser - Aguardando tarefa precedente]]) -> 0 | V82: =COUNTIFS(Tabela4[[#All],[Cenário]],Tabela4[[#This Row],[Cenário]],Tabela4[[#All],[Status]],Tabela4[[#Headers],[Não liberado para testes]]) -> 1 | W82: =IF(Tabela4[[#This Row],[Elo - Em correção ]]>0,"Sim","Não") -> Não | X82: =IF(Tabela4[[#This Row],[Keyuser - Aguardando tarefa precedente]]>0,"Sim","Não") -> Não | Y82: =IF(Tabela4[[#This Row],[Não liberado para testes]]>0,"Sim","Não") -> Sim | Z82: =IF(Tabela4[[#This Row],[Status]]="Keyuser - Pendente",NETWORKDAYS(Tabela4[[#This Row],[Dt Inicial]],TODAY()),"") | AA82: =AND(Tabela4[[#This Row],[Status]]="Keyuser - Aguardando tarefa precedente",K81="Keyuser - Concluído ") -> FALSE
A83: ="OUT-"&IFERROR(MID(Tabela4[[#This Row],[Cenário]],SEARCH("(",Tabela4[[#This Row],[Cenário]])+1,SEARCH(")",Tabela4[[#This Row],[Cenário]])-SEARCH("(",Tabela4[[#This Row],[Cenário]])-1),"")&"_"&ROW() -> OUT-Y002_83 | B83: Sim | C83: Venda Etanol Anidro F.E - Comercializadora (Y002) | D83: Realizar validação tributária - Ordem de venda | E83: 2 | F83: Realizar validação tributária - Ordem de venda | G83: Livia Beserra | H83: 15603606 | I83: NT | K83: Keyuser - Concluído | L83: 45946 | N83: 45946 | Q83: =COUNTIF(Tabela4[[#All],[Cenário]],Tabela4[[#This Row],[Cenário]]) -> 8 | R83: =COUNTIFS(Tabela4[[#All],[Cenário]],Tabela4[[#This Row],[Cenário]],Tabela4[[#All],[Status]],"Keyuser - Concluído ") -> 7 | S83: =IF(Tabela4[[#This Row],[Tarefas por Cenário]]-Tabela4[[#This Row],[Tarefas Concluídas]]>0,"Não","Sim") -> Não | T83: =COUNTIFS(Tabela4[[#All],[Cenário]],Tabela4[[#This Row],[Cenário]],Tabela4[[#All],[Status]],Tabela4[[#Headers],[Elo - Em correção ]]) -> 0 | U83: =COUNTIFS(Tabela4[[#All],[Cenário]],Tabela4[[#This Row],[Cenário]],Tabela4[[#All],[Status]],Tabela4[[#Headers],[Keyuser - Aguardando tarefa precedente]]) -> 0 | V83: =COUNTIFS(Tabela4[[#All],[Cenário]],Tabela4[[#This Row],[Cenário]],Tabela4[[#All],[Status]],Tabela4[[#Headers],[Não liberado para testes]]) -> 1 | W83: =IF(Tabela4[[#This Row],[Elo - Em correção ]]>0,"Sim","Não") -> Não | X83: =IF(Tabela4[[#This Row],[Keyuser - Aguardando tarefa precedente]]>0,"Sim","Não") -> Não | Y83: =IF(Tabela4[[#This Row],[Não liberado para testes]]>0,"Sim","Não") -> Sim | Z83: =IF(Tabela4[[#This Row],[Status]]="Keyuser - Pendente",NETWORKDAYS(Tabela4[[#This Row],[Dt Inicial]],TODAY()),"") | AA83: =AND(Tabela4[[#This Row],[Status]]="Keyuser - Aguardando tarefa precedente",K82="Keyuser - Concluído ") -> FALSE
A84: ="OUT-"&IFERROR(MID(Tabela4[[#This Row],[Cenário]],SEARCH("(",Tabela4[[#This Row],[Cenário]])+1,SEARCH(")",Tabela4[[#This Row],[Cenário]])-SEARCH("(",Tabela4[[#This Row],[Cenário]])-1),"")&"_"&ROW() -> OUT-Y002_84 | B84: Sim | C84: Venda Etanol Anidro F.E - Comercializadora (Y002) | D84: Liberar ordem de venda | E84: 3 | F84: Liberar ordem de venda | G84: Patrick Vianna / Aline Russo | H84: 15603606 | I84: NT | K84: Keyuser - Concluído | L84: 45946 | N84: 45946 | Q84: =COUNTIF(Tabela4[[#All],[Cenário]],Tabela4[[#This Row],[Cenário]]) -> 8 | R84: =COUNTIFS(Tabela4[[#All],[Cenário]],Tabela4[[#This Row],[Cenário]],Tabela4[[#All],[Status]],"Keyuser - Concluído ") -> 7 | S84: =IF(Tabela4[[#This Row],[Tarefas por Cenário]]-Tabela4[[#This Row],[Tarefas Concluídas]]>0,"Não","Sim") -> Não | T84: =COUNTIFS(Tabela4[[#All],[Cenário]],Tabela4[[#This Row],[Cenário]],Tabela4[[#All],[Status]],Tabela4[[#Headers],[Elo - Em correção ]]) -> 0 | U84: =COUNTIFS(Tabela4[[#All],[Cenário]],Tabela4[[#This Row],[Cenário]],Tabela4[[#All],[Status]],Tabela4[[#Headers],[Keyuser - Aguardando tarefa precedente]]) -> 0 | V84: =COUNTIFS(Tabela4[[#All],[Cenário]],Tabela4[[#This Row],[Cenário]],Tabela4[[#All],[Status]],Tabela4[[#Headers],[Não liberado para testes]]) -> 1 | W84: =IF(Tabela4[[#This Row],[Elo - Em correção ]]>0,"Sim","Não") -> Não | X84: =IF(Tabela4[[#This Row],[Keyuser - Aguardando tarefa precedente]]>0,"Sim","Não") -> Não | Y84: =IF(Tabela4[[#This Row],[Não liberado para testes]]>0,"Sim","Não") -> Sim | Z84: =IF(Tabela4[[#This Row],[Status]]="Keyuser - Pendente",NETWORKDAYS(Tabela4[[#This Row],[Dt Inicial]],TODAY()),"") | AA84: =AND(Tabela4[[#This Row],[Status]]="Keyuser - Aguardando tarefa precedente",K83="Keyuser - Concluído ") -> FALSE
A85: ="OUT-"&IFERROR(MID(Tabela4[[#This Row],[Cenário]],SEARCH("(",Tabela4[[#This Row],[Cenário]])+1,SEARCH(")",Tabela4[[#This Row],[Cenário]])-SEARCH("(",Tabela4[[#This Row],[Cenário]])-1),"")&"_"&ROW() -> OUT-Y002_85 | B85: Sim | C85: Venda Etanol Anidro F.E - Comercializadora (Y002) | D85: Realizar faturamento | E85: 4 | F85: Realizar faturamento | G85: Francisco Netto | H85: DocNum - 46482202 | K85: Keyuser - Concluído | L85: 45947 | N85: 45947 | Q85: =COUNTIF(Tabela4[[#All],[Cenário]],Tabela4[[#This Row],[Cenário]]) -> 8 | R85: =COUNTIFS(Tabela4[[#All],[Cenário]],Tabela4[[#This Row],[Cenário]],Tabela4[[#All],[Status]],"Keyuser - Concluído ") -> 7 | S85: =IF(Tabela4[[#This Row],[Tarefas por Cenário]]-Tabela4[[#This Row],[Tarefas Concluídas]]>0,"Não","Sim") -> Não | T85: =COUNTIFS(Tabela4[[#All],[Cenário]],Tabela4[[#This Row],[Cenário]],Tabela4[[#All],[Status]],Tabela4[[#Headers],[Elo - Em correção ]]) -> 0 | U85: =COUNTIFS(Tabela4[[#All],[Cenário]],Tabela4[[#This Row],[Cenário]],Tabela4[[#All],[Status]],Tabela4[[#Headers],[Keyuser - Aguardando tarefa precedente]]) -> 0 | V85: =COUNTIFS(Tabela4[[#All],[Cenário]],Tabela4[[#This Row],[Cenário]],Tabela4[[#All],[Status]],Tabela4[[#Headers],[Não liberado para testes]]) -> 1 | W85: =IF(Tabela4[[#This Row],[Elo - Em correção ]]>0,"Sim","Não") -> Não | X85: =IF(Tabela4[[#This Row],[Keyuser - Aguardando tarefa precedente]]>0,"Sim","Não") -> Não | Y85: =IF(Tabela4[[#This Row],[Não liberado para testes]]>0,"Sim","Não") -> Sim | Z85: =IF(Tabela4[[#This Row],[Status]]="Keyuser - Pendente",NETWORKDAYS(Tabela4[[#This Row],[Dt Inicial]],TODAY()),"") | AA85: =AND(Tabela4[[#This Row],[Status]]="Keyuser - Aguardando tarefa precedente",K84="Keyuser - Concluído ") -> FALSE
A86: ="OUT-"&IFERROR(MID(Tabela4[[#This Row],[Cenário]],SEARCH("(",Tabela4[[#This Row],[Cenário]])+1,SEARCH(")",Tabela4[[#This Row],[Cenário]])-SEARCH("(",Tabela4[[#This Row],[Cenário]])-1),"")&"_"&ROW() -> OUT-Y002_86 | B86: Sim | C86: Venda Etanol Anidro F.E - Comercializadora (Y002) | D86: Realizar validação tributária - SAP, XML e DANFE | E86: 5 | F86: Realizar validação tributária - SAP (xml e DANFE) | G86: Sergio Souza / Giovana Gonçalves | H86: DocNum - 46482202 | K86: Keyuser - Concluído | L86: 45947 | N86: 45947 | Q86: =COUNTIF(Tabela4[[#All],[Cenário]],Tabela4[[#This Row],[Cenário]]) -> 8 | R86: =COUNTIFS(Tabela4[[#All],[Cenário]],Tabela4[[#This Row],[Cenário]],Tabela4[[#All],[Status]],"Keyuser - Concluído ") -> 7 | S86: =IF(Tabela4[[#This Row],[Tarefas por Cenário]]-Tabela4[[#This Row],[Tarefas Concluídas]]>0,"Não","Sim") -> Não | T86: =COUNTIFS(Tabela4[[#All],[Cenário]],Tabela4[[#This Row],[Cenário]],Tabela4[[#All],[Status]],Tabela4[[#Headers],[Elo - Em correção ]]) -> 0 | U86: =COUNTIFS(Tabela4[[#All],[Cenário]],Tabela4[[#This Row],[Cenário]],Tabela4[[#All],[Status]],Tabela4[[#Headers],[Keyuser - Aguardando tarefa precedente]]) -> 0 | V86: =COUNTIFS(Tabela4[[#All],[Cenário]],Tabela4[[#This Row],[Cenário]],Tabela4[[#All],[Status]],Tabela4[[#Headers],[Não liberado para testes]]) -> 1 | W86: =IF(Tabela4[[#This Row],[Elo - Em correção ]]>0,"Sim","Não") -> Não | X86: =IF(Tabela4[[#This Row],[Keyuser - Aguardando tarefa precedente]]>0,"Sim","Não") -> Não | Y86: =IF(Tabela4[[#This Row],[Não liberado para testes]]>0,"Sim","Não") -> Sim | Z86: =IF(Tabela4[[#This Row],[Status]]="Keyuser - Pendente",NETWORKDAYS(Tabela4[[#This Row],[Dt Inicial]],TODAY()),"") | AA86: =AND(Tabela4[[#This Row],[Status]]="Keyuser - Aguardando tarefa precedente",K85="Keyuser - Concluído ") -> FALSE
A87: ="OUT-"&IFERROR(MID(Tabela4[[#This Row],[Cenário]],SEARCH("(",Tabela4[[#This Row],[Cenário]])+1,SEARCH(")",Tabela4[[#This Row],[Cenário]])-SEARCH("(",Tabela4[[#This Row],[Cenário]])-1),"")&"_"&ROW() -> OUT-Y002_87 | B87: Sim | C87: Venda Etanol Anidro F.E - Comercializadora (Y002) | D87: Realizar validação contábil | E87: 6 | F87: Realizar validação contábil | G87: Naiara Toledo | H87: DocNum - 46482202 | K87: Keyuser - Concluído | L87: 45950 | N87: 45950 | Q87: =COUNTIF(Tabela4[[#All],[Cenário]],Tabela4[[#This Row],[Cenário]]) -> 8 | R87: =COUNTIFS(Tabela4[[#All],[Cenário]],Tabela4[[#This Row],[Cenário]],Tabela4[[#All],[Status]],"Keyuser - Concluído ") -> 7 | S87: =IF(Tabela4[[#This Row],[Tarefas por Cenário]]-Tabela4[[#This Row],[Tarefas Concluídas]]>0,"Não","Sim") -> Não | T87: =COUNTIFS(Tabela4[[#All],[Cenário]],Tabela4[[#This Row],[Cenário]],Tabela4[[#All],[Status]],Tabela4[[#Headers],[Elo - Em correção ]]) -> 0 | U87: =COUNTIFS(Tabela4[[#All],[Cenário]],Tabela4[[#This Row],[Cenário]],Tabela4[[#All],[Status]],Tabela4[[#Headers],[Keyuser - Aguardando tarefa precedente]]) -> 0 | V87: =COUNTIFS(Tabela4[[#All],[Cenário]],Tabela4[[#This Row],[Cenário]],Tabela4[[#All],[Status]],Tabela4[[#Headers],[Não liberado para testes]]) -> 1 | W87: =IF(Tabela4[[#This Row],[Elo - Em correção ]]>0,"Sim","Não") -> Não | X87: =IF(Tabela4[[#This Row],[Keyuser - Aguardando tarefa precedente]]>0,"Sim","Não") -> Não | Y87: =IF(Tabela4[[#This Row],[Não liberado para testes]]>0,"Sim","Não") -> Sim | Z87: =IF(Tabela4[[#This Row],[Status]]="Keyuser - Pendente",NETWORKDAYS(Tabela4[[#This Row],[Dt Inicial]],TODAY()),"") | AA87: =AND(Tabela4[[#This Row],[Status]]="Keyuser - Aguardando tarefa precedente",K86="Keyuser - Concluído ") -> FALSE
A88: ="OUT-"&IFERROR(MID(Tabela4[[#This Row],[Cenário]],SEARCH("(",Tabela4[[#This Row],[Cenário]])+1,SEARCH(")",Tabela4[[#This Row],[Cenário]])-SEARCH("(",Tabela4[[#This Row],[Cenário]])-1),"")&"_"&ROW() -> OUT-Y002_88 | B88: Não | C88: Venda Etanol Anidro F.E - Comercializadora (Y002) | D88: Realizar validação Obrigações Acessórias - TaxOne | E88: 7 | F88: Realizar validação Obrigações Acessórias - TaxOne | G88: Sergio Souza / Giovana Gonçalves | K88: Não liberado para testes | Q88: =COUNTIF(Tabela4[[#All],[Cenário]],Tabela4[[#This Row],[Cenário]]) -> 8 | R88: =COUNTIFS(Tabela4[[#All],[Cenário]],Tabela4[[#This Row],[Cenário]],Tabela4[[#All],[Status]],"Keyuser - Concluído ") -> 7 | S88: =IF(Tabela4[[#This Row],[Tarefas por Cenário]]-Tabela4[[#This Row],[Tarefas Concluídas]]>0,"Não","Sim") -> Não | T88: =COUNTIFS(Tabela4[[#All],[Cenário]],Tabela4[[#This Row],[Cenário]],Tabela4[[#All],[Status]],Tabela4[[#Headers],[Elo - Em correção ]]) -> 0 | U88: =COUNTIFS(Tabela4[[#All],[Cenário]],Tabela4[[#This Row],[Cenário]],Tabela4[[#All],[Status]],Tabela4[[#Headers],[Keyuser - Aguardando tarefa precedente]]) -> 0 | V88: =COUNTIFS(Tabela4[[#All],[Cenário]],Tabela4[[#This Row],[Cenário]],Tabela4[[#All],[Status]],Tabela4[[#Headers],[Não liberado para testes]]) -> 1 | W88: =IF(Tabela4[[#This Row],[Elo - Em correção ]]>0,"Sim","Não") -> Não | X88: =IF(Tabela4[[#This Row],[Keyuser - Aguardando tarefa precedente]]>0,"Sim","Não") -> Não | Y88: =IF(Tabela4[[#This Row],[Não liberado para testes]]>0,"Sim","Não") -> Sim | Z88: =IF(Tabela4[[#This Row],[Status]]="Keyuser - Pendente",NETWORKDAYS(Tabela4[[#This Row],[Dt Inicial]],TODAY()),"") | AA88: =AND(Tabela4[[#This Row],[Status]]="Keyuser - Aguardando tarefa precedente",K87="Keyuser - Concluído ") -> FALSE
A89: ="OUT-"&IFERROR(MID(Tabela4[[#This Row],[Cenário]],SEARCH("(",Tabela4[[#This Row],[Cenário]])+1,SEARCH(")",Tabela4[[#This Row],[Cenário]])-SEARCH("(",Tabela4[[#This Row],[Cenário]])-1),"")&"_"&ROW() -> OUT-Y002_89 | B89: Sim | C89: Venda Etanol Anidro F.E - Comercializadora (Y002) | D89: Realizar validação Títulos Financeiros | E89: 8 | F89: Realizar validação Títulos Financeiros | G89: Patrick Vianna / Aline Russo | H89: 15603606 | I89: NT | K89: Keyuser - Concluído | L89: 45950 | N89: 45950 | Q89: =COUNTIF(Tabela4[[#All],[Cenário]],Tabela4[[#This Row],[Cenário]]) -> 8 | R89: =COUNTIFS(Tabela4[[#All],[Cenário]],Tabela4[[#This Row],[Cenário]],Tabela4[[#All],[Status]],"Keyuser - Concluído ") -> 7 | S89: =IF(Tabela4[[#This Row],[Tarefas por Cenário]]-Tabela4[[#This Row],[Tarefas Concluídas]]>0,"Não","Sim") -> Não | T89: =COUNTIFS(Tabela4[[#All],[Cenário]],Tabela4[[#This Row],[Cenário]],Tabela4[[#All],[Status]],Tabela4[[#Headers],[Elo - Em correção ]]) -> 0 | U89: =COUNTIFS(Tabela4[[#All],[Cenário]],Tabela4[[#This Row],[Cenário]],Tabela4[[#All],[Status]],Tabela4[[#Headers],[Keyuser - Aguardando tarefa precedente]]) -> 0 | V89: =COUNTIFS(Tabela4[[#All],[Cenário]],Tabela4[[#This Row],[Cenário]],Tabela4[[#All],[Status]],Tabela4[[#Headers],[Não liberado para testes]]) -> 1 | W89: =IF(Tabela4[[#This Row],[Elo - Em correção ]]>0,"Sim","Não") -> Não | X89: =IF(Tabela4[[#This Row],[Keyuser - Aguardando tarefa precedente]]>0,"Sim","Não") -> Não | Y89: =IF(Tabela4[[#This Row],[Não liberado para testes]]>0,"Sim","Não") -> Sim | Z89: =IF(Tabela4[[#This Row],[Status]]="Keyuser - Pendente",NETWORKDAYS(Tabela4[[#This Row],[Dt Inicial]],TODAY()),"") | AA89: =AND(Tabela4[[#This Row],[Status]]="Keyuser - Aguardando tarefa precedente",K88="Keyuser - Concluído ") -> FALSE
A90: ="OUT-"&IFERROR(MID(Tabela4[[#This Row],[Cenário]],SEARCH("(",Tabela4[[#This Row],[Cenário]])+1,SEARCH(")",Tabela4[[#This Row],[Cenário]])-SEARCH("(",Tabela4[[#This Row],[Cenário]])-1),"")&"_"&ROW() -> OUT-YDEV_90 | B90: Sim | C90: Venda Etanol Anidro F.E - Comercializadora (YDEV) | D90: Criar ordem de venda | E90: 1 | F90: Criar ordem de venda | G90: Marcos Nunes | H90: 60668333 | K90: Keyuser - Concluído | L90: 45958 | N90: 45958 | Q90: =COUNTIF(Tabela4[[#All],[Cenário]],Tabela4[[#This Row],[Cenário]]) -> 6 | R90: =COUNTIFS(Tabela4[[#All],[Cenário]],Tabela4[[#This Row],[Cenário]],Tabela4[[#All],[Status]],"Keyuser - Concluído ") -> 5 | S90: =IF(Tabela4[[#This Row],[Tarefas por Cenário]]-Tabela4[[#This Row],[Tarefas Concluídas]]>0,"Não","Sim") -> Não | T90: =COUNTIFS(Tabela4[[#All],[Cenário]],Tabela4[[#This Row],[Cenário]],Tabela4[[#All],[Status]],Tabela4[[#Headers],[Elo - Em correção ]]) -> 0 | U90: =COUNTIFS(Tabela4[[#All],[Cenário]],Tabela4[[#This Row],[Cenário]],Tabela4[[#All],[Status]],Tabela4[[#Headers],[Keyuser - Aguardando tarefa precedente]]) -> 0 | V90: =COUNTIFS(Tabela4[[#All],[Cenário]],Tabela4[[#This Row],[Cenário]],Tabela4[[#All],[Status]],Tabela4[[#Headers],[Não liberado para testes]]) -> 1 | W90: =IF(Tabela4[[#This Row],[Elo - Em correção ]]>0,"Sim","Não") -> Não | X90: =IF(Tabela4[[#This Row],[Keyuser - Aguardando tarefa precedente]]>0,"Sim","Não") -> Não | Y90: =IF(Tabela4[[#This Row],[Não liberado para testes]]>0,"Sim","Não") -> Sim | Z90: =IF(Tabela4[[#This Row],[Status]]="Keyuser - Pendente",NETWORKDAYS(Tabela4[[#This Row],[Dt Inicial]],TODAY()),"") | AA90: =AND(Tabela4[[#This Row],[Status]]="Keyuser - Aguardando tarefa precedente",K89="Keyuser - Concluído ") -> FALSE
A91: ="OUT-"&IFERROR(MID(Tabela4[[#This Row],[Cenário]],SEARCH("(",Tabela4[[#This Row],[Cenário]])+1,SEARCH(")",Tabela4[[#This Row],[Cenário]])-SEARCH("(",Tabela4[[#This Row],[Cenário]])-1),"")&"_"&ROW() -> OUT-YDEV_91 | B91: Sim | C91: Venda Etanol Anidro F.E - Comercializadora (YDEV) | D91: Realizar validação tributária - Ordem de venda | E91: 2 | F91: Realizar validação tributária - Ordem de venda | G91: Livia Beserra | H91: 60668333 | K91: Keyuser - Concluído | L91: 45958 | N91: 45958 | Q91: =COUNTIF(Tabela4[[#All],[Cenário]],Tabela4[[#This Row],[Cenário]]) -> 6 | R91: =COUNTIFS(Tabela4[[#All],[Cenário]],Tabela4[[#This Row],[Cenário]],Tabela4[[#All],[Status]],"Keyuser - Concluído ") -> 5 | S91: =IF(Tabela4[[#This Row],[Tarefas por Cenário]]-Tabela4[[#This Row],[Tarefas Concluídas]]>0,"Não","Sim") -> Não | T91: =COUNTIFS(Tabela4[[#All],[Cenário]],Tabela4[[#This Row],[Cenário]],Tabela4[[#All],[Status]],Tabela4[[#Headers],[Elo - Em correção ]]) -> 0 | U91: =COUNTIFS(Tabela4[[#All],[Cenário]],Tabela4[[#This Row],[Cenário]],Tabela4[[#All],[Status]],Tabela4[[#Headers],[Keyuser - Aguardando tarefa precedente]]) -> 0 | V91: =COUNTIFS(Tabela4[[#All],[Cenário]],Tabela4[[#This Row],[Cenário]],Tabela4[[#All],[Status]],Tabela4[[#Headers],[Não liberado para testes]]) -> 1 | W91: =IF(Tabela4[[#This Row],[Elo - Em correção ]]>0,"Sim","Não") -> Não | X91: =IF(Tabela4[[#This Row],[Keyuser - Aguardando tarefa precedente]]>0,"Sim","Não") -> Não | Y91: =IF(Tabela4[[#This Row],[Não liberado para testes]]>0,"Sim","Não") -> Sim | Z91: =IF(Tabela4[[#This Row],[Status]]="Keyuser - Pendente",NETWORKDAYS(Tabela4[[#This Row],[Dt Inicial]],TODAY()),"") | AA91: =AND(Tabela4[[#This Row],[Status]]="Keyuser - Aguardando tarefa precedente",K90="Keyuser - Concluído ") -> FALSE
A92: ="OUT-"&IFERROR(MID(Tabela4[[#This Row],[Cenário]],SEARCH("(",Tabela4[[#This Row],[Cenário]])+1,SEARCH(")",Tabela4[[#This Row],[Cenário]])-SEARCH("(",Tabela4[[#This Row],[Cenário]])-1),"")&"_"&ROW() -> OUT-YDEV_92 | B92: Sim | C92: Venda Etanol Anidro F.E - Comercializadora (YDEV) | D92: Realizar faturamento | E92: 3 | F92: Realizar faturamento | G92: Marcos Nunes | H92: DocNum - 46482288 | K92: Keyuser - Concluído | L92: 45959 | N92: 45959 | O92: Nota nr 214297 | Q92: =COUNTIF(Tabela4[[#All],[Cenário]],Tabela4[[#This Row],[Cenário]]) -> 6 | R92: =COUNTIFS(Tabela4[[#All],[Cenário]],Tabela4[[#This Row],[Cenário]],Tabela4[[#All],[Status]],"Keyuser - Concluído ") -> 5 | S92: =IF(Tabela4[[#This Row],[Tarefas por Cenário]]-Tabela4[[#This Row],[Tarefas Concluídas]]>0,"Não","Sim") -> Não | T92: =COUNTIFS(Tabela4[[#All],[Cenário]],Tabela4[[#This Row],[Cenário]],Tabela4[[#All],[Status]],Tabela4[[#Headers],[Elo - Em correção ]]) -> 0 | U92: =COUNTIFS(Tabela4[[#All],[Cenário]],Tabela4[[#This Row],[Cenário]],Tabela4[[#All],[Status]],Tabela4[[#Headers],[Keyuser - Aguardando tarefa precedente]]) -> 0 | V92: =COUNTIFS(Tabela4[[#All],[Cenário]],Tabela4[[#This Row],[Cenário]],Tabela4[[#All],[Status]],Tabela4[[#Headers],[Não liberado para testes]]) -> 1 | W92: =IF(Tabela4[[#This Row],[Elo - Em correção ]]>0,"Sim","Não") -> Não | X92: =IF(Tabela4[[#This Row],[Keyuser - Aguardando tarefa precedente]]>0,"Sim","Não") -> Não | Y92: =IF(Tabela4[[#This Row],[Não liberado para testes]]>0,"Sim","Não") -> Sim | Z92: =IF(Tabela4[[#This Row],[Status]]="Keyuser - Pendente",NETWORKDAYS(Tabela4[[#This Row],[Dt Inicial]],TODAY()),"") | AA92: =AND(Tabela4[[#This Row],[Status]]="Keyuser - Aguardando tarefa precedente",K91="Keyuser - Concluído ") -> FALSE
